{"words":["Peyton","Manning","broke","Dan","Marino","'s","season","touchdown","record","today","with","49","against","the","San","Diego","Chargers","in","a","thrilling","game","that","ended","in","overtime","."]
,"lemmas":["Peyton","Manning","break","Dan","Marino","'s","season","touchdown","record","today","with","49","against","the","San","Diego","Chargers","in","a","thrilling","game","that","end","in","overtime","."]
,"posTags":["NNP","NNP","VBD","NNP","NNP","POS","NN","NN","NN","NN","IN","CD","IN","DT","NNP","NNP","NNPS","IN","DT","NN","NN","WDT","VBD","IN","NN","."]
,"chunks":["B-NP","I-NP","B-VP","B-NP","I-NP","B-NP","I-NP","I-NP","I-NP","B-NP","B-PP","B-NP","B-PP","B-NP","I-NP","I-NP","I-NP","B-PP","B-NP","I-NP","I-NP","B-NP","B-VP","B-PP","B-NP","O"]
,"parents":[1,2,-1,4,8,4,8,8,2,2,2,10,11,16,16,16,12,16,20,20,17,22,11,22,23,-2]
,"deprels":["nn","nsubj","root","nn","poss","possessive","nn","nn","dobj","tmod","prep","pobj","prep","det","nn","nn","pobj","prep","det","nn","pobj","nsubj","rcmod","prep","pobj",null]
,"naryTree":"((ROOT (S (NP (NNP Peyton) (NNP Manning)) (VP (VBD broke) (NP (NP (NNP Dan) (NNP Marino) (POS 's)) (NN season) (NN touchdown) (NN record)) (NP-TMP (NN today)) (PP (IN with) (NP (NP (CD 49)) (PP (IN against) (NP (NP (DT the) (NNP San) (NNP Diego) (NNPS Chargers)) (PP (IN in) (NP (DT a) (NN thrilling) (NN game))))) (SBAR (WHNP (WDT that)) (S (VP (VBD ended) (PP (IN in) (NP (NN overtime))))))))) (. .))))"
,"nePairs":"[{\"m1\":{\"start\":0,\"end\":2,\"head\":1,\"type\":null,\"subtype\":null,\"phraseType\":\"NAM\",\"id\":\"8411bf51-6d1c-5c97-884a-00005a980875\"},\"m2\":{\"start\":3,\"end\":5,\"head\":4,\"type\":null,\"subtype\":null,\"phraseType\":\"NAM\",\"id\":\"8411bf51-6d1c-5c97-884a-00005a980883\"}}]"
,"relLabels":["NO_RELATION"]}

{"words":["Peyton","Manning","broke","Dan","Marino","'s","season","touchdown","record","today","with","49","against","the","San","Diego","Chargers","in","a","thrilling","game","that","ended","in","overtime","."]
,"lemmas":["Peyton","Manning","break","Dan","Marino","'s","season","touchdown","record","today","with","49","against","the","San","Diego","Chargers","in","a","thrilling","game","that","end","in","overtime","."]
,"posTags":["NNP","NNP","VBD","NNP","NNP","POS","NN","NN","NN","NN","IN","CD","IN","DT","NNP","NNP","NNPS","IN","DT","NN","NN","WDT","VBD","IN","NN","."]
,"chunks":["B-NP","I-NP","B-VP","B-NP","I-NP","B-NP","I-NP","I-NP","I-NP","B-NP","B-PP","B-NP","B-PP","B-NP","I-NP","I-NP","I-NP","B-PP","B-NP","I-NP","I-NP","B-NP","B-VP","B-PP","B-NP","O"]
,"parents":[1,2,-1,4,8,4,8,8,2,2,2,10,11,16,16,16,12,16,20,20,17,22,11,22,23,-2]
,"deprels":["nn","nsubj","root","nn","poss","possessive","nn","nn","dobj","tmod","prep","pobj","prep","det","nn","nn","pobj","prep","det","nn","pobj","nsubj","rcmod","prep","pobj",null]
,"naryTree":"((ROOT (S (NP (NNP Peyton) (NNP Manning)) (VP (VBD broke) (NP (NP (NNP Dan) (NNP Marino) (POS 's)) (NN season) (NN touchdown) (NN record)) (NP-TMP (NN today)) (PP (IN with) (NP (NP (CD 49)) (PP (IN against) (NP (NP (DT the) (NNP San) (NNP Diego) (NNPS Chargers)) (PP (IN in) (NP (DT a) (NN thrilling) (NN game))))) (SBAR (WHNP (WDT that)) (S (VP (VBD ended) (PP (IN in) (NP (NN overtime))))))))) (. .))))"
,"nePairs":"[{\"m1\":{\"start\":0,\"end\":2,\"head\":1,\"type\":null,\"subtype\":null,\"phraseType\":\"NAM\",\"id\":\"8411bf51-6d1c-5c97-884a-00005a980875\"},\"m2\":{\"start\":13,\"end\":17,\"head\":16,\"type\":null,\"subtype\":null,\"phraseType\":\"NAM\",\"id\":\"8411bf51-6d1c-5c97-884a-00005a98087f\"}}]"
,"relLabels":["NO_RELATION"]}

{"words":["Peyton","Manning","broke","Dan","Marino","'s","season","touchdown","record","today","with","49","against","the","San","Diego","Chargers","in","a","thrilling","game","that","ended","in","overtime","."]
,"lemmas":["Peyton","Manning","break","Dan","Marino","'s","season","touchdown","record","today","with","49","against","the","San","Diego","Chargers","in","a","thrilling","game","that","end","in","overtime","."]
,"posTags":["NNP","NNP","VBD","NNP","NNP","POS","NN","NN","NN","NN","IN","CD","IN","DT","NNP","NNP","NNPS","IN","DT","NN","NN","WDT","VBD","IN","NN","."]
,"chunks":["B-NP","I-NP","B-VP","B-NP","I-NP","B-NP","I-NP","I-NP","I-NP","B-NP","B-PP","B-NP","B-PP","B-NP","I-NP","I-NP","I-NP","B-PP","B-NP","I-NP","I-NP","B-NP","B-VP","B-PP","B-NP","O"]
,"parents":[1,2,-1,4,8,4,8,8,2,2,2,10,11,16,16,16,12,16,20,20,17,22,11,22,23,-2]
,"deprels":["nn","nsubj","root","nn","poss","possessive","nn","nn","dobj","tmod","prep","pobj","prep","det","nn","nn","pobj","prep","det","nn","pobj","nsubj","rcmod","prep","pobj",null]
,"naryTree":"((ROOT (S (NP (NNP Peyton) (NNP Manning)) (VP (VBD broke) (NP (NP (NNP Dan) (NNP Marino) (POS 's)) (NN season) (NN touchdown) (NN record)) (NP-TMP (NN today)) (PP (IN with) (NP (NP (CD 49)) (PP (IN against) (NP (NP (DT the) (NNP San) (NNP Diego) (NNPS Chargers)) (PP (IN in) (NP (DT a) (NN thrilling) (NN game))))) (SBAR (WHNP (WDT that)) (S (VP (VBD ended) (PP (IN in) (NP (NN overtime))))))))) (. .))))"
,"nePairs":"[{\"m1\":{\"start\":3,\"end\":5,\"head\":4,\"type\":null,\"subtype\":null,\"phraseType\":\"NAM\",\"id\":\"8411bf51-6d1c-5c97-884a-00005a980883\"},\"m2\":{\"start\":13,\"end\":17,\"head\":16,\"type\":null,\"subtype\":null,\"phraseType\":\"NAM\",\"id\":\"8411bf51-6d1c-5c97-884a-00005a98087f\"}}]"
,"relLabels":["NO_RELATION"]}

{"words":["I","was","happy","to","see","Manning","break","the","record",",","as","last","week","he","decided","to","take","a","knee","to","end","the","game","against","the","Baltimore","Ravens","when","he","could","have","tried","to","increase","the","lead","even","more","by","throwing","a","touchdown","."]
,"lemmas":["I","be","happy","to","see","Manning","break","the","record",",","as","last","week","he","decide","to","take","a","knee","to","end","the","game","against","the","Baltimore","Ravens","when","he","could","have","try","to","increase","the","lead","even","more","by","throw","a","touchdown","."]
,"posTags":["PRP","VBD","JJ","TO","VB","NNP","VB","DT","NN",",","IN","JJ","NN","PRP","VBD","TO","VB","DT","NN","TO","VB","DT","NN","IN","DT","NNP","NNPS","WRB","PRP","MD","VB","VBN","TO","VB","DT","NN","RB","RBR","IN","VBG","DT","NN","."]
,"chunks":["B-NP","B-VP","B-ADJP","B-VP","I-VP","B-NP","B-VP","B-NP","I-NP","O","B-SBAR","B-NP","I-NP","B-NP","B-VP","B-VP","I-VP","B-NP","I-NP","B-VP","I-VP","B-NP","I-NP","B-PP","B-NP","I-NP","I-NP","B-ADVP","B-NP","B-VP","I-VP","I-VP","B-VP","I-VP","B-NP","I-NP","B-ADVP","I-ADVP","B-PP","B-VP","B-NP","I-NP","O"]
,"parents":[2,2,-1,4,2,6,4,8,6,-2,14,12,14,14,2,16,14,18,16,20,18,22,20,20,26,26,23,31,31,31,31,20,33,31,35,33,37,33,33,38,41,39,-2]
,"deprels":["nsubj","cop","root","aux","xcomp","nsubj","ccomp","det","dobj",null,"mark","amod","tmod","nsubj","advcl","aux","xcomp","det","dobj","aux","vmod","det","dobj","prep","det","nn","pobj","advmod","nsubj","aux","aux","advcl","aux","xcomp","det","dobj","advmod","advmod","prep","pcomp","det","dobj",null]
,"naryTree":"((ROOT (S (NP (PRP I)) (VP (VBD was) (ADJP (JJ happy) (S (VP (TO to) (VP (VB see) (S (NP (NNP Manning)) (VP (VB break) (NP (DT the) (NN record)))))))) (, ,) (SBAR (IN as) (S (NP-TMP (JJ last) (NN week)) (NP (PRP he)) (VP (VBD decided) (S (VP (TO to) (VP (VB take) (NP (DT a) (NN knee) (S (VP (TO to) (VP (VB end) (NP (DT the) (NN game)) (PP (IN against) (NP (DT the) (NNP Baltimore) (NNPS Ravens))) (SBAR (WHADVP (WRB when)) (S (NP (PRP he)) (VP (MD could) (VP (VB have) (VP (VBN tried) (S (VP (TO to) (VP (VB increase) (NP (DT the) (NN lead)) (ADVP (RB even) (RBR more)) (PP (IN by) (S (VP (VBG throwing) (NP (DT a) (NN touchdown)))))))))))))))))))))))) (. .))))"
,"nePairs":"[{\"m1\":{\"start\":0,\"end\":1,\"head\":0,\"type\":null,\"subtype\":null,\"phraseType\":\"PRO\",\"id\":\"8411bf51-6d1c-5c97-884a-00005a98088a\"},\"m2\":{\"start\":5,\"end\":6,\"head\":5,\"type\":null,\"subtype\":null,\"phraseType\":\"NAM\",\"id\":\"8411bf51-6d1c-5c97-884a-00005a980876\"}}]"
,"relLabels":["NO_RELATION"]}

{"words":["I","was","happy","to","see","Manning","break","the","record",",","as","last","week","he","decided","to","take","a","knee","to","end","the","game","against","the","Baltimore","Ravens","when","he","could","have","tried","to","increase","the","lead","even","more","by","throwing","a","touchdown","."]
,"lemmas":["I","be","happy","to","see","Manning","break","the","record",",","as","last","week","he","decide","to","take","a","knee","to","end","the","game","against","the","Baltimore","Ravens","when","he","could","have","try","to","increase","the","lead","even","more","by","throw","a","touchdown","."]
,"posTags":["PRP","VBD","JJ","TO","VB","NNP","VB","DT","NN",",","IN","JJ","NN","PRP","VBD","TO","VB","DT","NN","TO","VB","DT","NN","IN","DT","NNP","NNPS","WRB","PRP","MD","VB","VBN","TO","VB","DT","NN","RB","RBR","IN","VBG","DT","NN","."]
,"chunks":["B-NP","B-VP","B-ADJP","B-VP","I-VP","B-NP","B-VP","B-NP","I-NP","O","B-SBAR","B-NP","I-NP","B-NP","B-VP","B-VP","I-VP","B-NP","I-NP","B-VP","I-VP","B-NP","I-NP","B-PP","B-NP","I-NP","I-NP","B-ADVP","B-NP","B-VP","I-VP","I-VP","B-VP","I-VP","B-NP","I-NP","B-ADVP","I-ADVP","B-PP","B-VP","B-NP","I-NP","O"]
,"parents":[2,2,-1,4,2,6,4,8,6,-2,14,12,14,14,2,16,14,18,16,20,18,22,20,20,26,26,23,31,31,31,31,20,33,31,35,33,37,33,33,38,41,39,-2]
,"deprels":["nsubj","cop","root","aux","xcomp","nsubj","ccomp","det","dobj",null,"mark","amod","tmod","nsubj","advcl","aux","xcomp","det","dobj","aux","vmod","det","dobj","prep","det","nn","pobj","advmod","nsubj","aux","aux","advcl","aux","xcomp","det","dobj","advmod","advmod","prep","pcomp","det","dobj",null]
,"naryTree":"((ROOT (S (NP (PRP I)) (VP (VBD was) (ADJP (JJ happy) (S (VP (TO to) (VP (VB see) (S (NP (NNP Manning)) (VP (VB break) (NP (DT the) (NN record)))))))) (, ,) (SBAR (IN as) (S (NP-TMP (JJ last) (NN week)) (NP (PRP he)) (VP (VBD decided) (S (VP (TO to) (VP (VB take) (NP (DT a) (NN knee) (S (VP (TO to) (VP (VB end) (NP (DT the) (NN game)) (PP (IN against) (NP (DT the) (NNP Baltimore) (NNPS Ravens))) (SBAR (WHADVP (WRB when)) (S (NP (PRP he)) (VP (MD could) (VP (VB have) (VP (VBN tried) (S (VP (TO to) (VP (VB increase) (NP (DT the) (NN lead)) (ADVP (RB even) (RBR more)) (PP (IN by) (S (VP (VBG throwing) (NP (DT a) (NN touchdown)))))))))))))))))))))))) (. .))))"
,"nePairs":"[{\"m1\":{\"start\":0,\"end\":1,\"head\":0,\"type\":null,\"subtype\":null,\"phraseType\":\"PRO\",\"id\":\"8411bf51-6d1c-5c97-884a-00005a98088a\"},\"m2\":{\"start\":13,\"end\":14,\"head\":13,\"type\":null,\"subtype\":null,\"phraseType\":\"PRO\",\"id\":\"8411bf51-6d1c-5c97-884a-00005a980877\"}}]"
,"relLabels":["NO_RELATION"]}

{"words":["I","was","happy","to","see","Manning","break","the","record",",","as","last","week","he","decided","to","take","a","knee","to","end","the","game","against","the","Baltimore","Ravens","when","he","could","have","tried","to","increase","the","lead","even","more","by","throwing","a","touchdown","."]
,"lemmas":["I","be","happy","to","see","Manning","break","the","record",",","as","last","week","he","decide","to","take","a","knee","to","end","the","game","against","the","Baltimore","Ravens","when","he","could","have","try","to","increase","the","lead","even","more","by","throw","a","touchdown","."]
,"posTags":["PRP","VBD","JJ","TO","VB","NNP","VB","DT","NN",",","IN","JJ","NN","PRP","VBD","TO","VB","DT","NN","TO","VB","DT","NN","IN","DT","NNP","NNPS","WRB","PRP","MD","VB","VBN","TO","VB","DT","NN","RB","RBR","IN","VBG","DT","NN","."]
,"chunks":["B-NP","B-VP","B-ADJP","B-VP","I-VP","B-NP","B-VP","B-NP","I-NP","O","B-SBAR","B-NP","I-NP","B-NP","B-VP","B-VP","I-VP","B-NP","I-NP","B-VP","I-VP","B-NP","I-NP","B-PP","B-NP","I-NP","I-NP","B-ADVP","B-NP","B-VP","I-VP","I-VP","B-VP","I-VP","B-NP","I-NP","B-ADVP","I-ADVP","B-PP","B-VP","B-NP","I-NP","O"]
,"parents":[2,2,-1,4,2,6,4,8,6,-2,14,12,14,14,2,16,14,18,16,20,18,22,20,20,26,26,23,31,31,31,31,20,33,31,35,33,37,33,33,38,41,39,-2]
,"deprels":["nsubj","cop","root","aux","xcomp","nsubj","ccomp","det","dobj",null,"mark","amod","tmod","nsubj","advcl","aux","xcomp","det","dobj","aux","vmod","det","dobj","prep","det","nn","pobj","advmod","nsubj","aux","aux","advcl","aux","xcomp","det","dobj","advmod","advmod","prep","pcomp","det","dobj",null]
,"naryTree":"((ROOT (S (NP (PRP I)) (VP (VBD was) (ADJP (JJ happy) (S (VP (TO to) (VP (VB see) (S (NP (NNP Manning)) (VP (VB break) (NP (DT the) (NN record)))))))) (, ,) (SBAR (IN as) (S (NP-TMP (JJ last) (NN week)) (NP (PRP he)) (VP (VBD decided) (S (VP (TO to) (VP (VB take) (NP (DT a) (NN knee) (S (VP (TO to) (VP (VB end) (NP (DT the) (NN game)) (PP (IN against) (NP (DT the) (NNP Baltimore) (NNPS Ravens))) (SBAR (WHADVP (WRB when)) (S (NP (PRP he)) (VP (MD could) (VP (VB have) (VP (VBN tried) (S (VP (TO to) (VP (VB increase) (NP (DT the) (NN lead)) (ADVP (RB even) (RBR more)) (PP (IN by) (S (VP (VBG throwing) (NP (DT a) (NN touchdown)))))))))))))))))))))))) (. .))))"
,"nePairs":"[{\"m1\":{\"start\":0,\"end\":1,\"head\":0,\"type\":null,\"subtype\":null,\"phraseType\":\"PRO\",\"id\":\"8411bf51-6d1c-5c97-884a-00005a98088a\"},\"m2\":{\"start\":24,\"end\":27,\"head\":26,\"type\":null,\"subtype\":null,\"phraseType\":\"NAM\",\"id\":\"8411bf51-6d1c-5c97-884a-00005a980886\"}}]"
,"relLabels":["NO_RELATION"]}

{"words":["I","was","happy","to","see","Manning","break","the","record",",","as","last","week","he","decided","to","take","a","knee","to","end","the","game","against","the","Baltimore","Ravens","when","he","could","have","tried","to","increase","the","lead","even","more","by","throwing","a","touchdown","."]
,"lemmas":["I","be","happy","to","see","Manning","break","the","record",",","as","last","week","he","decide","to","take","a","knee","to","end","the","game","against","the","Baltimore","Ravens","when","he","could","have","try","to","increase","the","lead","even","more","by","throw","a","touchdown","."]
,"posTags":["PRP","VBD","JJ","TO","VB","NNP","VB","DT","NN",",","IN","JJ","NN","PRP","VBD","TO","VB","DT","NN","TO","VB","DT","NN","IN","DT","NNP","NNPS","WRB","PRP","MD","VB","VBN","TO","VB","DT","NN","RB","RBR","IN","VBG","DT","NN","."]
,"chunks":["B-NP","B-VP","B-ADJP","B-VP","I-VP","B-NP","B-VP","B-NP","I-NP","O","B-SBAR","B-NP","I-NP","B-NP","B-VP","B-VP","I-VP","B-NP","I-NP","B-VP","I-VP","B-NP","I-NP","B-PP","B-NP","I-NP","I-NP","B-ADVP","B-NP","B-VP","I-VP","I-VP","B-VP","I-VP","B-NP","I-NP","B-ADVP","I-ADVP","B-PP","B-VP","B-NP","I-NP","O"]
,"parents":[2,2,-1,4,2,6,4,8,6,-2,14,12,14,14,2,16,14,18,16,20,18,22,20,20,26,26,23,31,31,31,31,20,33,31,35,33,37,33,33,38,41,39,-2]
,"deprels":["nsubj","cop","root","aux","xcomp","nsubj","ccomp","det","dobj",null,"mark","amod","tmod","nsubj","advcl","aux","xcomp","det","dobj","aux","vmod","det","dobj","prep","det","nn","pobj","advmod","nsubj","aux","aux","advcl","aux","xcomp","det","dobj","advmod","advmod","prep","pcomp","det","dobj",null]
,"naryTree":"((ROOT (S (NP (PRP I)) (VP (VBD was) (ADJP (JJ happy) (S (VP (TO to) (VP (VB see) (S (NP (NNP Manning)) (VP (VB break) (NP (DT the) (NN record)))))))) (, ,) (SBAR (IN as) (S (NP-TMP (JJ last) (NN week)) (NP (PRP he)) (VP (VBD decided) (S (VP (TO to) (VP (VB take) (NP (DT a) (NN knee) (S (VP (TO to) (VP (VB end) (NP (DT the) (NN game)) (PP (IN against) (NP (DT the) (NNP Baltimore) (NNPS Ravens))) (SBAR (WHADVP (WRB when)) (S (NP (PRP he)) (VP (MD could) (VP (VB have) (VP (VBN tried) (S (VP (TO to) (VP (VB increase) (NP (DT the) (NN lead)) (ADVP (RB even) (RBR more)) (PP (IN by) (S (VP (VBG throwing) (NP (DT a) (NN touchdown)))))))))))))))))))))))) (. .))))"
,"nePairs":"[{\"m1\":{\"start\":0,\"end\":1,\"head\":0,\"type\":null,\"subtype\":null,\"phraseType\":\"PRO\",\"id\":\"8411bf51-6d1c-5c97-884a-00005a98088a\"},\"m2\":{\"start\":28,\"end\":29,\"head\":28,\"type\":null,\"subtype\":null,\"phraseType\":\"PRO\",\"id\":\"8411bf51-6d1c-5c97-884a-00005a980878\"}}]"
,"relLabels":["NO_RELATION"]}

{"words":["I","was","happy","to","see","Manning","break","the","record",",","as","last","week","he","decided","to","take","a","knee","to","end","the","game","against","the","Baltimore","Ravens","when","he","could","have","tried","to","increase","the","lead","even","more","by","throwing","a","touchdown","."]
,"lemmas":["I","be","happy","to","see","Manning","break","the","record",",","as","last","week","he","decide","to","take","a","knee","to","end","the","game","against","the","Baltimore","Ravens","when","he","could","have","try","to","increase","the","lead","even","more","by","throw","a","touchdown","."]
,"posTags":["PRP","VBD","JJ","TO","VB","NNP","VB","DT","NN",",","IN","JJ","NN","PRP","VBD","TO","VB","DT","NN","TO","VB","DT","NN","IN","DT","NNP","NNPS","WRB","PRP","MD","VB","VBN","TO","VB","DT","NN","RB","RBR","IN","VBG","DT","NN","."]
,"chunks":["B-NP","B-VP","B-ADJP","B-VP","I-VP","B-NP","B-VP","B-NP","I-NP","O","B-SBAR","B-NP","I-NP","B-NP","B-VP","B-VP","I-VP","B-NP","I-NP","B-VP","I-VP","B-NP","I-NP","B-PP","B-NP","I-NP","I-NP","B-ADVP","B-NP","B-VP","I-VP","I-VP","B-VP","I-VP","B-NP","I-NP","B-ADVP","I-ADVP","B-PP","B-VP","B-NP","I-NP","O"]
,"parents":[2,2,-1,4,2,6,4,8,6,-2,14,12,14,14,2,16,14,18,16,20,18,22,20,20,26,26,23,31,31,31,31,20,33,31,35,33,37,33,33,38,41,39,-2]
,"deprels":["nsubj","cop","root","aux","xcomp","nsubj","ccomp","det","dobj",null,"mark","amod","tmod","nsubj","advcl","aux","xcomp","det","dobj","aux","vmod","det","dobj","prep","det","nn","pobj","advmod","nsubj","aux","aux","advcl","aux","xcomp","det","dobj","advmod","advmod","prep","pcomp","det","dobj",null]
,"naryTree":"((ROOT (S (NP (PRP I)) (VP (VBD was) (ADJP (JJ happy) (S (VP (TO to) (VP (VB see) (S (NP (NNP Manning)) (VP (VB break) (NP (DT the) (NN record)))))))) (, ,) (SBAR (IN as) (S (NP-TMP (JJ last) (NN week)) (NP (PRP he)) (VP (VBD decided) (S (VP (TO to) (VP (VB take) (NP (DT a) (NN knee) (S (VP (TO to) (VP (VB end) (NP (DT the) (NN game)) (PP (IN against) (NP (DT the) (NNP Baltimore) (NNPS Ravens))) (SBAR (WHADVP (WRB when)) (S (NP (PRP he)) (VP (MD could) (VP (VB have) (VP (VBN tried) (S (VP (TO to) (VP (VB increase) (NP (DT the) (NN lead)) (ADVP (RB even) (RBR more)) (PP (IN by) (S (VP (VBG throwing) (NP (DT a) (NN touchdown)))))))))))))))))))))))) (. .))))"
,"nePairs":"[{\"m1\":{\"start\":5,\"end\":6,\"head\":5,\"type\":null,\"subtype\":null,\"phraseType\":\"NAM\",\"id\":\"8411bf51-6d1c-5c97-884a-00005a980876\"},\"m2\":{\"start\":13,\"end\":14,\"head\":13,\"type\":null,\"subtype\":null,\"phraseType\":\"PRO\",\"id\":\"8411bf51-6d1c-5c97-884a-00005a980877\"}}]"
,"relLabels":["NO_RELATION"]}

{"words":["I","was","happy","to","see","Manning","break","the","record",",","as","last","week","he","decided","to","take","a","knee","to","end","the","game","against","the","Baltimore","Ravens","when","he","could","have","tried","to","increase","the","lead","even","more","by","throwing","a","touchdown","."]
,"lemmas":["I","be","happy","to","see","Manning","break","the","record",",","as","last","week","he","decide","to","take","a","knee","to","end","the","game","against","the","Baltimore","Ravens","when","he","could","have","try","to","increase","the","lead","even","more","by","throw","a","touchdown","."]
,"posTags":["PRP","VBD","JJ","TO","VB","NNP","VB","DT","NN",",","IN","JJ","NN","PRP","VBD","TO","VB","DT","NN","TO","VB","DT","NN","IN","DT","NNP","NNPS","WRB","PRP","MD","VB","VBN","TO","VB","DT","NN","RB","RBR","IN","VBG","DT","NN","."]
,"chunks":["B-NP","B-VP","B-ADJP","B-VP","I-VP","B-NP","B-VP","B-NP","I-NP","O","B-SBAR","B-NP","I-NP","B-NP","B-VP","B-VP","I-VP","B-NP","I-NP","B-VP","I-VP","B-NP","I-NP","B-PP","B-NP","I-NP","I-NP","B-ADVP","B-NP","B-VP","I-VP","I-VP","B-VP","I-VP","B-NP","I-NP","B-ADVP","I-ADVP","B-PP","B-VP","B-NP","I-NP","O"]
,"parents":[2,2,-1,4,2,6,4,8,6,-2,14,12,14,14,2,16,14,18,16,20,18,22,20,20,26,26,23,31,31,31,31,20,33,31,35,33,37,33,33,38,41,39,-2]
,"deprels":["nsubj","cop","root","aux","xcomp","nsubj","ccomp","det","dobj",null,"mark","amod","tmod","nsubj","advcl","aux","xcomp","det","dobj","aux","vmod","det","dobj","prep","det","nn","pobj","advmod","nsubj","aux","aux","advcl","aux","xcomp","det","dobj","advmod","advmod","prep","pcomp","det","dobj",null]
,"naryTree":"((ROOT (S (NP (PRP I)) (VP (VBD was) (ADJP (JJ happy) (S (VP (TO to) (VP (VB see) (S (NP (NNP Manning)) (VP (VB break) (NP (DT the) (NN record)))))))) (, ,) (SBAR (IN as) (S (NP-TMP (JJ last) (NN week)) (NP (PRP he)) (VP (VBD decided) (S (VP (TO to) (VP (VB take) (NP (DT a) (NN knee) (S (VP (TO to) (VP (VB end) (NP (DT the) (NN game)) (PP (IN against) (NP (DT the) (NNP Baltimore) (NNPS Ravens))) (SBAR (WHADVP (WRB when)) (S (NP (PRP he)) (VP (MD could) (VP (VB have) (VP (VBN tried) (S (VP (TO to) (VP (VB increase) (NP (DT the) (NN lead)) (ADVP (RB even) (RBR more)) (PP (IN by) (S (VP (VBG throwing) (NP (DT a) (NN touchdown)))))))))))))))))))))))) (. .))))"
,"nePairs":"[{\"m1\":{\"start\":5,\"end\":6,\"head\":5,\"type\":null,\"subtype\":null,\"phraseType\":\"NAM\",\"id\":\"8411bf51-6d1c-5c97-884a-00005a980876\"},\"m2\":{\"start\":24,\"end\":27,\"head\":26,\"type\":null,\"subtype\":null,\"phraseType\":\"NAM\",\"id\":\"8411bf51-6d1c-5c97-884a-00005a980886\"}}]"
,"relLabels":["NO_RELATION"]}

{"words":["I","was","happy","to","see","Manning","break","the","record",",","as","last","week","he","decided","to","take","a","knee","to","end","the","game","against","the","Baltimore","Ravens","when","he","could","have","tried","to","increase","the","lead","even","more","by","throwing","a","touchdown","."]
,"lemmas":["I","be","happy","to","see","Manning","break","the","record",",","as","last","week","he","decide","to","take","a","knee","to","end","the","game","against","the","Baltimore","Ravens","when","he","could","have","try","to","increase","the","lead","even","more","by","throw","a","touchdown","."]
,"posTags":["PRP","VBD","JJ","TO","VB","NNP","VB","DT","NN",",","IN","JJ","NN","PRP","VBD","TO","VB","DT","NN","TO","VB","DT","NN","IN","DT","NNP","NNPS","WRB","PRP","MD","VB","VBN","TO","VB","DT","NN","RB","RBR","IN","VBG","DT","NN","."]
,"chunks":["B-NP","B-VP","B-ADJP","B-VP","I-VP","B-NP","B-VP","B-NP","I-NP","O","B-SBAR","B-NP","I-NP","B-NP","B-VP","B-VP","I-VP","B-NP","I-NP","B-VP","I-VP","B-NP","I-NP","B-PP","B-NP","I-NP","I-NP","B-ADVP","B-NP","B-VP","I-VP","I-VP","B-VP","I-VP","B-NP","I-NP","B-ADVP","I-ADVP","B-PP","B-VP","B-NP","I-NP","O"]
,"parents":[2,2,-1,4,2,6,4,8,6,-2,14,12,14,14,2,16,14,18,16,20,18,22,20,20,26,26,23,31,31,31,31,20,33,31,35,33,37,33,33,38,41,39,-2]
,"deprels":["nsubj","cop","root","aux","xcomp","nsubj","ccomp","det","dobj",null,"mark","amod","tmod","nsubj","advcl","aux","xcomp","det","dobj","aux","vmod","det","dobj","prep","det","nn","pobj","advmod","nsubj","aux","aux","advcl","aux","xcomp","det","dobj","advmod","advmod","prep","pcomp","det","dobj",null]
,"naryTree":"((ROOT (S (NP (PRP I)) (VP (VBD was) (ADJP (JJ happy) (S (VP (TO to) (VP (VB see) (S (NP (NNP Manning)) (VP (VB break) (NP (DT the) (NN record)))))))) (, ,) (SBAR (IN as) (S (NP-TMP (JJ last) (NN week)) (NP (PRP he)) (VP (VBD decided) (S (VP (TO to) (VP (VB take) (NP (DT a) (NN knee) (S (VP (TO to) (VP (VB end) (NP (DT the) (NN game)) (PP (IN against) (NP (DT the) (NNP Baltimore) (NNPS Ravens))) (SBAR (WHADVP (WRB when)) (S (NP (PRP he)) (VP (MD could) (VP (VB have) (VP (VBN tried) (S (VP (TO to) (VP (VB increase) (NP (DT the) (NN lead)) (ADVP (RB even) (RBR more)) (PP (IN by) (S (VP (VBG throwing) (NP (DT a) (NN touchdown)))))))))))))))))))))))) (. .))))"
,"nePairs":"[{\"m1\":{\"start\":5,\"end\":6,\"head\":5,\"type\":null,\"subtype\":null,\"phraseType\":\"NAM\",\"id\":\"8411bf51-6d1c-5c97-884a-00005a980876\"},\"m2\":{\"start\":28,\"end\":29,\"head\":28,\"type\":null,\"subtype\":null,\"phraseType\":\"PRO\",\"id\":\"8411bf51-6d1c-5c97-884a-00005a980878\"}}]"
,"relLabels":["NO_RELATION"]}

{"words":["I","was","happy","to","see","Manning","break","the","record",",","as","last","week","he","decided","to","take","a","knee","to","end","the","game","against","the","Baltimore","Ravens","when","he","could","have","tried","to","increase","the","lead","even","more","by","throwing","a","touchdown","."]
,"lemmas":["I","be","happy","to","see","Manning","break","the","record",",","as","last","week","he","decide","to","take","a","knee","to","end","the","game","against","the","Baltimore","Ravens","when","he","could","have","try","to","increase","the","lead","even","more","by","throw","a","touchdown","."]
,"posTags":["PRP","VBD","JJ","TO","VB","NNP","VB","DT","NN",",","IN","JJ","NN","PRP","VBD","TO","VB","DT","NN","TO","VB","DT","NN","IN","DT","NNP","NNPS","WRB","PRP","MD","VB","VBN","TO","VB","DT","NN","RB","RBR","IN","VBG","DT","NN","."]
,"chunks":["B-NP","B-VP","B-ADJP","B-VP","I-VP","B-NP","B-VP","B-NP","I-NP","O","B-SBAR","B-NP","I-NP","B-NP","B-VP","B-VP","I-VP","B-NP","I-NP","B-VP","I-VP","B-NP","I-NP","B-PP","B-NP","I-NP","I-NP","B-ADVP","B-NP","B-VP","I-VP","I-VP","B-VP","I-VP","B-NP","I-NP","B-ADVP","I-ADVP","B-PP","B-VP","B-NP","I-NP","O"]
,"parents":[2,2,-1,4,2,6,4,8,6,-2,14,12,14,14,2,16,14,18,16,20,18,22,20,20,26,26,23,31,31,31,31,20,33,31,35,33,37,33,33,38,41,39,-2]
,"deprels":["nsubj","cop","root","aux","xcomp","nsubj","ccomp","det","dobj",null,"mark","amod","tmod","nsubj","advcl","aux","xcomp","det","dobj","aux","vmod","det","dobj","prep","det","nn","pobj","advmod","nsubj","aux","aux","advcl","aux","xcomp","det","dobj","advmod","advmod","prep","pcomp","det","dobj",null]
,"naryTree":"((ROOT (S (NP (PRP I)) (VP (VBD was) (ADJP (JJ happy) (S (VP (TO to) (VP (VB see) (S (NP (NNP Manning)) (VP (VB break) (NP (DT the) (NN record)))))))) (, ,) (SBAR (IN as) (S (NP-TMP (JJ last) (NN week)) (NP (PRP he)) (VP (VBD decided) (S (VP (TO to) (VP (VB take) (NP (DT a) (NN knee) (S (VP (TO to) (VP (VB end) (NP (DT the) (NN game)) (PP (IN against) (NP (DT the) (NNP Baltimore) (NNPS Ravens))) (SBAR (WHADVP (WRB when)) (S (NP (PRP he)) (VP (MD could) (VP (VB have) (VP (VBN tried) (S (VP (TO to) (VP (VB increase) (NP (DT the) (NN lead)) (ADVP (RB even) (RBR more)) (PP (IN by) (S (VP (VBG throwing) (NP (DT a) (NN touchdown)))))))))))))))))))))))) (. .))))"
,"nePairs":"[{\"m1\":{\"start\":13,\"end\":14,\"head\":13,\"type\":null,\"subtype\":null,\"phraseType\":\"PRO\",\"id\":\"8411bf51-6d1c-5c97-884a-00005a980877\"},\"m2\":{\"start\":24,\"end\":27,\"head\":26,\"type\":null,\"subtype\":null,\"phraseType\":\"NAM\",\"id\":\"8411bf51-6d1c-5c97-884a-00005a980886\"}}]"
,"relLabels":["NO_RELATION"]}

{"words":["I","was","happy","to","see","Manning","break","the","record",",","as","last","week","he","decided","to","take","a","knee","to","end","the","game","against","the","Baltimore","Ravens","when","he","could","have","tried","to","increase","the","lead","even","more","by","throwing","a","touchdown","."]
,"lemmas":["I","be","happy","to","see","Manning","break","the","record",",","as","last","week","he","decide","to","take","a","knee","to","end","the","game","against","the","Baltimore","Ravens","when","he","could","have","try","to","increase","the","lead","even","more","by","throw","a","touchdown","."]
,"posTags":["PRP","VBD","JJ","TO","VB","NNP","VB","DT","NN",",","IN","JJ","NN","PRP","VBD","TO","VB","DT","NN","TO","VB","DT","NN","IN","DT","NNP","NNPS","WRB","PRP","MD","VB","VBN","TO","VB","DT","NN","RB","RBR","IN","VBG","DT","NN","."]
,"chunks":["B-NP","B-VP","B-ADJP","B-VP","I-VP","B-NP","B-VP","B-NP","I-NP","O","B-SBAR","B-NP","I-NP","B-NP","B-VP","B-VP","I-VP","B-NP","I-NP","B-VP","I-VP","B-NP","I-NP","B-PP","B-NP","I-NP","I-NP","B-ADVP","B-NP","B-VP","I-VP","I-VP","B-VP","I-VP","B-NP","I-NP","B-ADVP","I-ADVP","B-PP","B-VP","B-NP","I-NP","O"]
,"parents":[2,2,-1,4,2,6,4,8,6,-2,14,12,14,14,2,16,14,18,16,20,18,22,20,20,26,26,23,31,31,31,31,20,33,31,35,33,37,33,33,38,41,39,-2]
,"deprels":["nsubj","cop","root","aux","xcomp","nsubj","ccomp","det","dobj",null,"mark","amod","tmod","nsubj","advcl","aux","xcomp","det","dobj","aux","vmod","det","dobj","prep","det","nn","pobj","advmod","nsubj","aux","aux","advcl","aux","xcomp","det","dobj","advmod","advmod","prep","pcomp","det","dobj",null]
,"naryTree":"((ROOT (S (NP (PRP I)) (VP (VBD was) (ADJP (JJ happy) (S (VP (TO to) (VP (VB see) (S (NP (NNP Manning)) (VP (VB break) (NP (DT the) (NN record)))))))) (, ,) (SBAR (IN as) (S (NP-TMP (JJ last) (NN week)) (NP (PRP he)) (VP (VBD decided) (S (VP (TO to) (VP (VB take) (NP (DT a) (NN knee) (S (VP (TO to) (VP (VB end) (NP (DT the) (NN game)) (PP (IN against) (NP (DT the) (NNP Baltimore) (NNPS Ravens))) (SBAR (WHADVP (WRB when)) (S (NP (PRP he)) (VP (MD could) (VP (VB have) (VP (VBN tried) (S (VP (TO to) (VP (VB increase) (NP (DT the) (NN lead)) (ADVP (RB even) (RBR more)) (PP (IN by) (S (VP (VBG throwing) (NP (DT a) (NN touchdown)))))))))))))))))))))))) (. .))))"
,"nePairs":"[{\"m1\":{\"start\":13,\"end\":14,\"head\":13,\"type\":null,\"subtype\":null,\"phraseType\":\"PRO\",\"id\":\"8411bf51-6d1c-5c97-884a-00005a980877\"},\"m2\":{\"start\":28,\"end\":29,\"head\":28,\"type\":null,\"subtype\":null,\"phraseType\":\"PRO\",\"id\":\"8411bf51-6d1c-5c97-884a-00005a980878\"}}]"
,"relLabels":["NO_RELATION"]}

{"words":["I","was","happy","to","see","Manning","break","the","record",",","as","last","week","he","decided","to","take","a","knee","to","end","the","game","against","the","Baltimore","Ravens","when","he","could","have","tried","to","increase","the","lead","even","more","by","throwing","a","touchdown","."]
,"lemmas":["I","be","happy","to","see","Manning","break","the","record",",","as","last","week","he","decide","to","take","a","knee","to","end","the","game","against","the","Baltimore","Ravens","when","he","could","have","try","to","increase","the","lead","even","more","by","throw","a","touchdown","."]
,"posTags":["PRP","VBD","JJ","TO","VB","NNP","VB","DT","NN",",","IN","JJ","NN","PRP","VBD","TO","VB","DT","NN","TO","VB","DT","NN","IN","DT","NNP","NNPS","WRB","PRP","MD","VB","VBN","TO","VB","DT","NN","RB","RBR","IN","VBG","DT","NN","."]
,"chunks":["B-NP","B-VP","B-ADJP","B-VP","I-VP","B-NP","B-VP","B-NP","I-NP","O","B-SBAR","B-NP","I-NP","B-NP","B-VP","B-VP","I-VP","B-NP","I-NP","B-VP","I-VP","B-NP","I-NP","B-PP","B-NP","I-NP","I-NP","B-ADVP","B-NP","B-VP","I-VP","I-VP","B-VP","I-VP","B-NP","I-NP","B-ADVP","I-ADVP","B-PP","B-VP","B-NP","I-NP","O"]
,"parents":[2,2,-1,4,2,6,4,8,6,-2,14,12,14,14,2,16,14,18,16,20,18,22,20,20,26,26,23,31,31,31,31,20,33,31,35,33,37,33,33,38,41,39,-2]
,"deprels":["nsubj","cop","root","aux","xcomp","nsubj","ccomp","det","dobj",null,"mark","amod","tmod","nsubj","advcl","aux","xcomp","det","dobj","aux","vmod","det","dobj","prep","det","nn","pobj","advmod","nsubj","aux","aux","advcl","aux","xcomp","det","dobj","advmod","advmod","prep","pcomp","det","dobj",null]
,"naryTree":"((ROOT (S (NP (PRP I)) (VP (VBD was) (ADJP (JJ happy) (S (VP (TO to) (VP (VB see) (S (NP (NNP Manning)) (VP (VB break) (NP (DT the) (NN record)))))))) (, ,) (SBAR (IN as) (S (NP-TMP (JJ last) (NN week)) (NP (PRP he)) (VP (VBD decided) (S (VP (TO to) (VP (VB take) (NP (DT a) (NN knee) (S (VP (TO to) (VP (VB end) (NP (DT the) (NN game)) (PP (IN against) (NP (DT the) (NNP Baltimore) (NNPS Ravens))) (SBAR (WHADVP (WRB when)) (S (NP (PRP he)) (VP (MD could) (VP (VB have) (VP (VBN tried) (S (VP (TO to) (VP (VB increase) (NP (DT the) (NN lead)) (ADVP (RB even) (RBR more)) (PP (IN by) (S (VP (VBG throwing) (NP (DT a) (NN touchdown)))))))))))))))))))))))) (. .))))"
,"nePairs":"[{\"m1\":{\"start\":24,\"end\":27,\"head\":26,\"type\":null,\"subtype\":null,\"phraseType\":\"NAM\",\"id\":\"8411bf51-6d1c-5c97-884a-00005a980886\"},\"m2\":{\"start\":28,\"end\":29,\"head\":28,\"type\":null,\"subtype\":null,\"phraseType\":\"PRO\",\"id\":\"8411bf51-6d1c-5c97-884a-00005a980878\"}}]"
,"relLabels":["NO_RELATION"]}

{"words":["Manning","is","all","class","and","ranks","with","the","best","quarterbacks","of","all","time","."]
,"lemmas":["man","be","all","class","and","rank","with","the","best","quarterback","of","all","time","."]
,"posTags":["VBG","VBZ","DT","NN","CC","VBZ","IN","DT","JJS","NNS","IN","DT","NN","."]
,"chunks":["B-NP","B-VP","B-NP","I-NP","O","B-VP","B-PP","B-NP","I-NP","I-NP","B-PP","B-NP","I-NP","O"]
,"parents":[3,3,3,-1,3,3,5,9,9,6,9,12,10,-2]
,"deprels":["nsubj","cop","det","root","cc","conj","prep","det","amod","pobj","prep","det","pobj",null]
,"naryTree":"((ROOT (S (NP (VBG Manning)) (VP (VP (VBZ is) (NP (DT all) (NN class))) (CC and) (VP (VBZ ranks) (PP (IN with) (NP (NP (DT the) (JJS best) (NNS quarterbacks)) (PP (IN of) (NP (DT all) (NN time))))))) (. .))))"
,"nePairs":"[{\"m1\":{\"start\":0,\"end\":1,\"head\":0,\"type\":null,\"subtype\":null,\"phraseType\":\"NAM\",\"id\":\"8411bf51-6d1c-5c97-884a-00005a980879\"},\"m2\":{\"start\":7,\"end\":10,\"head\":9,\"type\":null,\"subtype\":null,\"phraseType\":\"NOM\",\"id\":\"8411bf51-6d1c-5c97-884a-00005a98087d\"}}]"
,"relLabels":["NO_RELATION"]}

{"words":["On","a","much","sadder","note",",","the","Minister","of","Defense",",","Reggie","White",",","died","of","heart","attack","this","morning","in","his","home","at","the","age","of","43","."]
,"lemmas":["on","a","much","sadder","note",",","the","Minister","of","Defense",",","Reggie","White",",","die","of","heart","attack","this","morning","in","he","home","at","the","age","of","43","."]
,"posTags":["IN","DT","JJ","JJR","NN",",","DT","NNP","IN","NNP",",","NNP","NNP",",","VBD","IN","NN","NN","DT","NN","IN","PRP$","NN","IN","DT","NN","IN","CD","."]
,"chunks":["B-PP","B-NP","I-NP","I-NP","I-NP","O","B-NP","I-NP","B-PP","B-NP","O","B-NP","I-NP","O","B-VP","B-PP","B-NP","I-NP","B-NP","I-NP","B-PP","B-NP","I-NP","B-PP","B-NP","I-NP","B-PP","B-NP","O"]
,"parents":[14,4,4,2,0,-2,7,14,7,8,-2,12,7,-2,-1,14,17,15,19,14,14,22,20,22,25,23,25,26,-2]
,"deprels":["prep","det","amod","dep","pobj",null,"det","nsubj","prep","pobj",null,"nn","appos",null,"root","prep","nn","pobj","det","tmod","prep","poss","pobj","prep","det","pobj","prep","pobj",null]
,"naryTree":"((ROOT (S (PP (IN On) (NP (DT a) (ADJP (JJ much) (JJR sadder)) (NN note))) (, ,) (NP (NP (NP (DT the) (NNP Minister)) (PP (IN of) (NP (NNP Defense)))) (, ,) (NP (NNP Reggie) (NNP White)) (, ,)) (VP (VBD died) (PP (IN of) (NP (NN heart) (NN attack))) (NP-TMP (DT this) (NN morning)) (PP (IN in) (NP (NP (PRP$ his) (NN home)) (PP (IN at) (NP (NP (DT the) (NN age)) (PP (IN of) (NP (CD 43)))))))) (. .))))"
,"nePairs":"[{\"m1\":{\"start\":21,\"end\":22,\"head\":21,\"type\":null,\"subtype\":null,\"phraseType\":\"PRO\",\"id\":\"8411bf51-6d1c-5c97-884a-00005a980872\"},\"m2\":{\"start\":21,\"end\":23,\"head\":22,\"type\":null,\"subtype\":null,\"phraseType\":\"NOM\",\"id\":\"8411bf51-6d1c-5c97-884a-00005a980888\"}}]"
,"relLabels":["ART"]}

{"words":["On","a","much","sadder","note",",","the","Minister","of","Defense",",","Reggie","White",",","died","of","heart","attack","this","morning","in","his","home","at","the","age","of","43","."]
,"lemmas":["on","a","much","sadder","note",",","the","Minister","of","Defense",",","Reggie","White",",","die","of","heart","attack","this","morning","in","he","home","at","the","age","of","43","."]
,"posTags":["IN","DT","JJ","JJR","NN",",","DT","NNP","IN","NNP",",","NNP","NNP",",","VBD","IN","NN","NN","DT","NN","IN","PRP$","NN","IN","DT","NN","IN","CD","."]
,"chunks":["B-PP","B-NP","I-NP","I-NP","I-NP","O","B-NP","I-NP","B-PP","B-NP","O","B-NP","I-NP","O","B-VP","B-PP","B-NP","I-NP","B-NP","I-NP","B-PP","B-NP","I-NP","B-PP","B-NP","I-NP","B-PP","B-NP","O"]
,"parents":[14,4,4,2,0,-2,7,14,7,8,-2,12,7,-2,-1,14,17,15,19,14,14,22,20,22,25,23,25,26,-2]
,"deprels":["prep","det","amod","dep","pobj",null,"det","nsubj","prep","pobj",null,"nn","appos",null,"root","prep","nn","pobj","det","tmod","prep","poss","pobj","prep","det","pobj","prep","pobj",null]
,"naryTree":"((ROOT (S (PP (IN On) (NP (DT a) (ADJP (JJ much) (JJR sadder)) (NN note))) (, ,) (NP (NP (NP (DT the) (NNP Minister)) (PP (IN of) (NP (NNP Defense)))) (, ,) (NP (NNP Reggie) (NNP White)) (, ,)) (VP (VBD died) (PP (IN of) (NP (NN heart) (NN attack))) (NP-TMP (DT this) (NN morning)) (PP (IN in) (NP (NP (PRP$ his) (NN home)) (PP (IN at) (NP (NP (DT the) (NN age)) (PP (IN of) (NP (CD 43)))))))) (. .))))"
,"nePairs":"[{\"m1\":{\"start\":6,\"end\":10,\"head\":9,\"type\":null,\"subtype\":null,\"phraseType\":\"NOM\",\"id\":\"8411bf51-6d1c-5c97-884a-00005a980871\"},\"m2\":{\"start\":21,\"end\":23,\"head\":22,\"type\":null,\"subtype\":null,\"phraseType\":\"NOM\",\"id\":\"8411bf51-6d1c-5c97-884a-00005a980888\"}}]"
,"relLabels":["PHYS"]}

{"words":["On","a","much","sadder","note",",","the","Minister","of","Defense",",","Reggie","White",",","died","of","heart","attack","this","morning","in","his","home","at","the","age","of","43","."]
,"lemmas":["on","a","much","sadder","note",",","the","Minister","of","Defense",",","Reggie","White",",","die","of","heart","attack","this","morning","in","he","home","at","the","age","of","43","."]
,"posTags":["IN","DT","JJ","JJR","NN",",","DT","NNP","IN","NNP",",","NNP","NNP",",","VBD","IN","NN","NN","DT","NN","IN","PRP$","NN","IN","DT","NN","IN","CD","."]
,"chunks":["B-PP","B-NP","I-NP","I-NP","I-NP","O","B-NP","I-NP","B-PP","B-NP","O","B-NP","I-NP","O","B-VP","B-PP","B-NP","I-NP","B-NP","I-NP","B-PP","B-NP","I-NP","B-PP","B-NP","I-NP","B-PP","B-NP","O"]
,"parents":[14,4,4,2,0,-2,7,14,7,8,-2,12,7,-2,-1,14,17,15,19,14,14,22,20,22,25,23,25,26,-2]
,"deprels":["prep","det","amod","dep","pobj",null,"det","nsubj","prep","pobj",null,"nn","appos",null,"root","prep","nn","pobj","det","tmod","prep","poss","pobj","prep","det","pobj","prep","pobj",null]
,"naryTree":"((ROOT (S (PP (IN On) (NP (DT a) (ADJP (JJ much) (JJR sadder)) (NN note))) (, ,) (NP (NP (NP (DT the) (NNP Minister)) (PP (IN of) (NP (NNP Defense)))) (, ,) (NP (NNP Reggie) (NNP White)) (, ,)) (VP (VBD died) (PP (IN of) (NP (NN heart) (NN attack))) (NP-TMP (DT this) (NN morning)) (PP (IN in) (NP (NP (PRP$ his) (NN home)) (PP (IN at) (NP (NP (DT the) (NN age)) (PP (IN of) (NP (CD 43)))))))) (. .))))"
,"nePairs":"[{\"m1\":{\"start\":6,\"end\":10,\"head\":9,\"type\":null,\"subtype\":null,\"phraseType\":\"NOM\",\"id\":\"8411bf51-6d1c-5c97-884a-00005a980871\"},\"m2\":{\"start\":11,\"end\":13,\"head\":12,\"type\":null,\"subtype\":null,\"phraseType\":\"NAM\",\"id\":\"8411bf51-6d1c-5c97-884a-00005a980870\"}}]"
,"relLabels":["NO_RELATION"]}

{"words":["On","a","much","sadder","note",",","the","Minister","of","Defense",",","Reggie","White",",","died","of","heart","attack","this","morning","in","his","home","at","the","age","of","43","."]
,"lemmas":["on","a","much","sadder","note",",","the","Minister","of","Defense",",","Reggie","White",",","die","of","heart","attack","this","morning","in","he","home","at","the","age","of","43","."]
,"posTags":["IN","DT","JJ","JJR","NN",",","DT","NNP","IN","NNP",",","NNP","NNP",",","VBD","IN","NN","NN","DT","NN","IN","PRP$","NN","IN","DT","NN","IN","CD","."]
,"chunks":["B-PP","B-NP","I-NP","I-NP","I-NP","O","B-NP","I-NP","B-PP","B-NP","O","B-NP","I-NP","O","B-VP","B-PP","B-NP","I-NP","B-NP","I-NP","B-PP","B-NP","I-NP","B-PP","B-NP","I-NP","B-PP","B-NP","O"]
,"parents":[14,4,4,2,0,-2,7,14,7,8,-2,12,7,-2,-1,14,17,15,19,14,14,22,20,22,25,23,25,26,-2]
,"deprels":["prep","det","amod","dep","pobj",null,"det","nsubj","prep","pobj",null,"nn","appos",null,"root","prep","nn","pobj","det","tmod","prep","poss","pobj","prep","det","pobj","prep","pobj",null]
,"naryTree":"((ROOT (S (PP (IN On) (NP (DT a) (ADJP (JJ much) (JJR sadder)) (NN note))) (, ,) (NP (NP (NP (DT the) (NNP Minister)) (PP (IN of) (NP (NNP Defense)))) (, ,) (NP (NNP Reggie) (NNP White)) (, ,)) (VP (VBD died) (PP (IN of) (NP (NN heart) (NN attack))) (NP-TMP (DT this) (NN morning)) (PP (IN in) (NP (NP (PRP$ his) (NN home)) (PP (IN at) (NP (NP (DT the) (NN age)) (PP (IN of) (NP (CD 43)))))))) (. .))))"
,"nePairs":"[{\"m1\":{\"start\":6,\"end\":10,\"head\":9,\"type\":null,\"subtype\":null,\"phraseType\":\"NOM\",\"id\":\"8411bf51-6d1c-5c97-884a-00005a980871\"},\"m2\":{\"start\":21,\"end\":22,\"head\":21,\"type\":null,\"subtype\":null,\"phraseType\":\"PRO\",\"id\":\"8411bf51-6d1c-5c97-884a-00005a980872\"}}]"
,"relLabels":["NO_RELATION"]}

{"words":["On","a","much","sadder","note",",","the","Minister","of","Defense",",","Reggie","White",",","died","of","heart","attack","this","morning","in","his","home","at","the","age","of","43","."]
,"lemmas":["on","a","much","sadder","note",",","the","Minister","of","Defense",",","Reggie","White",",","die","of","heart","attack","this","morning","in","he","home","at","the","age","of","43","."]
,"posTags":["IN","DT","JJ","JJR","NN",",","DT","NNP","IN","NNP",",","NNP","NNP",",","VBD","IN","NN","NN","DT","NN","IN","PRP$","NN","IN","DT","NN","IN","CD","."]
,"chunks":["B-PP","B-NP","I-NP","I-NP","I-NP","O","B-NP","I-NP","B-PP","B-NP","O","B-NP","I-NP","O","B-VP","B-PP","B-NP","I-NP","B-NP","I-NP","B-PP","B-NP","I-NP","B-PP","B-NP","I-NP","B-PP","B-NP","O"]
,"parents":[14,4,4,2,0,-2,7,14,7,8,-2,12,7,-2,-1,14,17,15,19,14,14,22,20,22,25,23,25,26,-2]
,"deprels":["prep","det","amod","dep","pobj",null,"det","nsubj","prep","pobj",null,"nn","appos",null,"root","prep","nn","pobj","det","tmod","prep","poss","pobj","prep","det","pobj","prep","pobj",null]
,"naryTree":"((ROOT (S (PP (IN On) (NP (DT a) (ADJP (JJ much) (JJR sadder)) (NN note))) (, ,) (NP (NP (NP (DT the) (NNP Minister)) (PP (IN of) (NP (NNP Defense)))) (, ,) (NP (NNP Reggie) (NNP White)) (, ,)) (VP (VBD died) (PP (IN of) (NP (NN heart) (NN attack))) (NP-TMP (DT this) (NN morning)) (PP (IN in) (NP (NP (PRP$ his) (NN home)) (PP (IN at) (NP (NP (DT the) (NN age)) (PP (IN of) (NP (CD 43)))))))) (. .))))"
,"nePairs":"[{\"m1\":{\"start\":11,\"end\":13,\"head\":12,\"type\":null,\"subtype\":null,\"phraseType\":\"NAM\",\"id\":\"8411bf51-6d1c-5c97-884a-00005a980870\"},\"m2\":{\"start\":21,\"end\":22,\"head\":21,\"type\":null,\"subtype\":null,\"phraseType\":\"PRO\",\"id\":\"8411bf51-6d1c-5c97-884a-00005a980872\"}}]"
,"relLabels":["NO_RELATION"]}

{"words":["On","a","much","sadder","note",",","the","Minister","of","Defense",",","Reggie","White",",","died","of","heart","attack","this","morning","in","his","home","at","the","age","of","43","."]
,"lemmas":["on","a","much","sadder","note",",","the","Minister","of","Defense",",","Reggie","White",",","die","of","heart","attack","this","morning","in","he","home","at","the","age","of","43","."]
,"posTags":["IN","DT","JJ","JJR","NN",",","DT","NNP","IN","NNP",",","NNP","NNP",",","VBD","IN","NN","NN","DT","NN","IN","PRP$","NN","IN","DT","NN","IN","CD","."]
,"chunks":["B-PP","B-NP","I-NP","I-NP","I-NP","O","B-NP","I-NP","B-PP","B-NP","O","B-NP","I-NP","O","B-VP","B-PP","B-NP","I-NP","B-NP","I-NP","B-PP","B-NP","I-NP","B-PP","B-NP","I-NP","B-PP","B-NP","O"]
,"parents":[14,4,4,2,0,-2,7,14,7,8,-2,12,7,-2,-1,14,17,15,19,14,14,22,20,22,25,23,25,26,-2]
,"deprels":["prep","det","amod","dep","pobj",null,"det","nsubj","prep","pobj",null,"nn","appos",null,"root","prep","nn","pobj","det","tmod","prep","poss","pobj","prep","det","pobj","prep","pobj",null]
,"naryTree":"((ROOT (S (PP (IN On) (NP (DT a) (ADJP (JJ much) (JJR sadder)) (NN note))) (, ,) (NP (NP (NP (DT the) (NNP Minister)) (PP (IN of) (NP (NNP Defense)))) (, ,) (NP (NNP Reggie) (NNP White)) (, ,)) (VP (VBD died) (PP (IN of) (NP (NN heart) (NN attack))) (NP-TMP (DT this) (NN morning)) (PP (IN in) (NP (NP (PRP$ his) (NN home)) (PP (IN at) (NP (NP (DT the) (NN age)) (PP (IN of) (NP (CD 43)))))))) (. .))))"
,"nePairs":"[{\"m1\":{\"start\":11,\"end\":13,\"head\":12,\"type\":null,\"subtype\":null,\"phraseType\":\"NAM\",\"id\":\"8411bf51-6d1c-5c97-884a-00005a980870\"},\"m2\":{\"start\":21,\"end\":23,\"head\":22,\"type\":null,\"subtype\":null,\"phraseType\":\"NOM\",\"id\":\"8411bf51-6d1c-5c97-884a-00005a980888\"}}]"
,"relLabels":["NO_RELATION"]}

{"words":["White","played","a","total","of","15","years","with","Philadelphia",",","Green","Bay","and","Carolina","."]
,"lemmas":["White","play","a","total","of","15","year","with","Philadelphia",",","Green","Bay","and","Carolina","."]
,"posTags":["NNP","VBD","DT","NN","IN","CD","NNS","IN","NNP",",","NNP","NNP","CC","NNP","."]
,"chunks":["B-NP","B-VP","B-NP","I-NP","B-PP","B-NP","I-NP","B-PP","B-NP","I-NP","I-NP","I-NP","I-NP","I-NP","O"]
,"parents":[1,-1,3,1,3,6,4,1,11,-2,11,7,11,11,-2]
,"deprels":["nsubj","root","det","dobj","prep","num","pobj","prep","nn",null,"conj","pobj","cc","conj",null]
,"naryTree":"((ROOT (S (NP (NNP White)) (VP (VBD played) (NP (NP (DT a) (NN total)) (PP (IN of) (NP (CD 15) (NNS years)))) (PP (IN with) (NP (NNP Philadelphia) (, ,) (NNP Green) (NNP Bay) (CC and) (NNP Carolina)))) (. .))))"
,"nePairs":"[{\"m1\":{\"start\":0,\"end\":1,\"head\":0,\"type\":null,\"subtype\":null,\"phraseType\":\"NAM\",\"id\":\"8411bf51-6d1c-5c97-884a-00005a980873\"},\"m2\":{\"start\":10,\"end\":12,\"head\":11,\"type\":null,\"subtype\":null,\"phraseType\":\"NAM\",\"id\":\"8411bf51-6d1c-5c97-884a-00005a980881\"}}]"
,"relLabels":["ORG-AFF"]}

{"words":["White","played","a","total","of","15","years","with","Philadelphia",",","Green","Bay","and","Carolina","."]
,"lemmas":["White","play","a","total","of","15","year","with","Philadelphia",",","Green","Bay","and","Carolina","."]
,"posTags":["NNP","VBD","DT","NN","IN","CD","NNS","IN","NNP",",","NNP","NNP","CC","NNP","."]
,"chunks":["B-NP","B-VP","B-NP","I-NP","B-PP","B-NP","I-NP","B-PP","B-NP","I-NP","I-NP","I-NP","I-NP","I-NP","O"]
,"parents":[1,-1,3,1,3,6,4,1,11,-2,11,7,11,11,-2]
,"deprels":["nsubj","root","det","dobj","prep","num","pobj","prep","nn",null,"conj","pobj","cc","conj",null]
,"naryTree":"((ROOT (S (NP (NNP White)) (VP (VBD played) (NP (NP (DT a) (NN total)) (PP (IN of) (NP (CD 15) (NNS years)))) (PP (IN with) (NP (NNP Philadelphia) (, ,) (NNP Green) (NNP Bay) (CC and) (NNP Carolina)))) (. .))))"
,"nePairs":"[{\"m1\":{\"start\":0,\"end\":1,\"head\":0,\"type\":null,\"subtype\":null,\"phraseType\":\"NAM\",\"id\":\"8411bf51-6d1c-5c97-884a-00005a980873\"},\"m2\":{\"start\":13,\"end\":14,\"head\":13,\"type\":null,\"subtype\":null,\"phraseType\":\"NAM\",\"id\":\"8411bf51-6d1c-5c97-884a-00005a98088e\"}}]"
,"relLabels":["ORG-AFF"]}

{"words":["White","played","a","total","of","15","years","with","Philadelphia",",","Green","Bay","and","Carolina","."]
,"lemmas":["White","play","a","total","of","15","year","with","Philadelphia",",","Green","Bay","and","Carolina","."]
,"posTags":["NNP","VBD","DT","NN","IN","CD","NNS","IN","NNP",",","NNP","NNP","CC","NNP","."]
,"chunks":["B-NP","B-VP","B-NP","I-NP","B-PP","B-NP","I-NP","B-PP","B-NP","I-NP","I-NP","I-NP","I-NP","I-NP","O"]
,"parents":[1,-1,3,1,3,6,4,1,11,-2,11,7,11,11,-2]
,"deprels":["nsubj","root","det","dobj","prep","num","pobj","prep","nn",null,"conj","pobj","cc","conj",null]
,"naryTree":"((ROOT (S (NP (NNP White)) (VP (VBD played) (NP (NP (DT a) (NN total)) (PP (IN of) (NP (CD 15) (NNS years)))) (PP (IN with) (NP (NNP Philadelphia) (, ,) (NNP Green) (NNP Bay) (CC and) (NNP Carolina)))) (. .))))"
,"nePairs":"[{\"m1\":{\"start\":0,\"end\":1,\"head\":0,\"type\":null,\"subtype\":null,\"phraseType\":\"NAM\",\"id\":\"8411bf51-6d1c-5c97-884a-00005a980873\"},\"m2\":{\"start\":8,\"end\":9,\"head\":8,\"type\":null,\"subtype\":null,\"phraseType\":\"NAM\",\"id\":\"8411bf51-6d1c-5c97-884a-00005a98088c\"}}]"
,"relLabels":["ORG-AFF"]}

{"words":["White","played","a","total","of","15","years","with","Philadelphia",",","Green","Bay","and","Carolina","."]
,"lemmas":["White","play","a","total","of","15","year","with","Philadelphia",",","Green","Bay","and","Carolina","."]
,"posTags":["NNP","VBD","DT","NN","IN","CD","NNS","IN","NNP",",","NNP","NNP","CC","NNP","."]
,"chunks":["B-NP","B-VP","B-NP","I-NP","B-PP","B-NP","I-NP","B-PP","B-NP","I-NP","I-NP","I-NP","I-NP","I-NP","O"]
,"parents":[1,-1,3,1,3,6,4,1,11,-2,11,7,11,11,-2]
,"deprels":["nsubj","root","det","dobj","prep","num","pobj","prep","nn",null,"conj","pobj","cc","conj",null]
,"naryTree":"((ROOT (S (NP (NNP White)) (VP (VBD played) (NP (NP (DT a) (NN total)) (PP (IN of) (NP (CD 15) (NNS years)))) (PP (IN with) (NP (NNP Philadelphia) (, ,) (NNP Green) (NNP Bay) (CC and) (NNP Carolina)))) (. .))))"
,"nePairs":"[{\"m1\":{\"start\":8,\"end\":9,\"head\":8,\"type\":null,\"subtype\":null,\"phraseType\":\"NAM\",\"id\":\"8411bf51-6d1c-5c97-884a-00005a98088c\"},\"m2\":{\"start\":10,\"end\":12,\"head\":11,\"type\":null,\"subtype\":null,\"phraseType\":\"NAM\",\"id\":\"8411bf51-6d1c-5c97-884a-00005a980881\"}}]"
,"relLabels":["NO_RELATION"]}

{"words":["White","played","a","total","of","15","years","with","Philadelphia",",","Green","Bay","and","Carolina","."]
,"lemmas":["White","play","a","total","of","15","year","with","Philadelphia",",","Green","Bay","and","Carolina","."]
,"posTags":["NNP","VBD","DT","NN","IN","CD","NNS","IN","NNP",",","NNP","NNP","CC","NNP","."]
,"chunks":["B-NP","B-VP","B-NP","I-NP","B-PP","B-NP","I-NP","B-PP","B-NP","I-NP","I-NP","I-NP","I-NP","I-NP","O"]
,"parents":[1,-1,3,1,3,6,4,1,11,-2,11,7,11,11,-2]
,"deprels":["nsubj","root","det","dobj","prep","num","pobj","prep","nn",null,"conj","pobj","cc","conj",null]
,"naryTree":"((ROOT (S (NP (NNP White)) (VP (VBD played) (NP (NP (DT a) (NN total)) (PP (IN of) (NP (CD 15) (NNS years)))) (PP (IN with) (NP (NNP Philadelphia) (, ,) (NNP Green) (NNP Bay) (CC and) (NNP Carolina)))) (. .))))"
,"nePairs":"[{\"m1\":{\"start\":8,\"end\":9,\"head\":8,\"type\":null,\"subtype\":null,\"phraseType\":\"NAM\",\"id\":\"8411bf51-6d1c-5c97-884a-00005a98088c\"},\"m2\":{\"start\":13,\"end\":14,\"head\":13,\"type\":null,\"subtype\":null,\"phraseType\":\"NAM\",\"id\":\"8411bf51-6d1c-5c97-884a-00005a98088e\"}}]"
,"relLabels":["NO_RELATION"]}

{"words":["White","played","a","total","of","15","years","with","Philadelphia",",","Green","Bay","and","Carolina","."]
,"lemmas":["White","play","a","total","of","15","year","with","Philadelphia",",","Green","Bay","and","Carolina","."]
,"posTags":["NNP","VBD","DT","NN","IN","CD","NNS","IN","NNP",",","NNP","NNP","CC","NNP","."]
,"chunks":["B-NP","B-VP","B-NP","I-NP","B-PP","B-NP","I-NP","B-PP","B-NP","I-NP","I-NP","I-NP","I-NP","I-NP","O"]
,"parents":[1,-1,3,1,3,6,4,1,11,-2,11,7,11,11,-2]
,"deprels":["nsubj","root","det","dobj","prep","num","pobj","prep","nn",null,"conj","pobj","cc","conj",null]
,"naryTree":"((ROOT (S (NP (NNP White)) (VP (VBD played) (NP (NP (DT a) (NN total)) (PP (IN of) (NP (CD 15) (NNS years)))) (PP (IN with) (NP (NNP Philadelphia) (, ,) (NNP Green) (NNP Bay) (CC and) (NNP Carolina)))) (. .))))"
,"nePairs":"[{\"m1\":{\"start\":10,\"end\":12,\"head\":11,\"type\":null,\"subtype\":null,\"phraseType\":\"NAM\",\"id\":\"8411bf51-6d1c-5c97-884a-00005a980881\"},\"m2\":{\"start\":13,\"end\":14,\"head\":13,\"type\":null,\"subtype\":null,\"phraseType\":\"NAM\",\"id\":\"8411bf51-6d1c-5c97-884a-00005a98088e\"}}]"
,"relLabels":["NO_RELATION"]}

{"words":["He","retired","after","the","2000","season","as","the","NFL","'s","all-time","leader","in","sacks","with","198","."]
,"lemmas":["he","retire","after","the","2000","season","as","the","NFL","'s","all-time","leader","in","sack","with","198","."]
,"posTags":["PRP","VBD","IN","DT","CD","NN","IN","DT","NNP","POS","JJ","NN","IN","NNS","IN","CD","."]
,"chunks":["B-NP","B-VP","B-PP","B-NP","I-NP","I-NP","B-PP","B-NP","I-NP","B-NP","I-NP","I-NP","B-PP","B-NP","B-PP","B-NP","O"]
,"parents":[1,-1,1,5,5,2,1,8,11,8,11,6,11,12,13,14,-2]
,"deprels":["nsubj","root","prep","det","num","pobj","prep","det","poss","possessive","amod","pobj","prep","pobj","prep","pobj",null]
,"naryTree":"((ROOT (S (NP (PRP He)) (VP (VBD retired) (PP (IN after) (NP (DT the) (CD 2000) (NN season))) (PP (IN as) (NP (NP (NP (DT the) (NNP NFL) (POS 's)) (JJ all-time) (NN leader)) (PP (IN in) (NP (NP (NNS sacks)) (PP (IN with) (NP (CD 198)))))))) (. .))))"
,"nePairs":"[{\"m1\":{\"start\":0,\"end\":1,\"head\":0,\"type\":null,\"subtype\":null,\"phraseType\":\"PRO\",\"id\":\"8411bf51-6d1c-5c97-884a-00005a98086d\"},\"m2\":{\"start\":8,\"end\":9,\"head\":8,\"type\":null,\"subtype\":null,\"phraseType\":\"NAM\",\"id\":\"8411bf51-6d1c-5c97-884a-00005a98086b\"}}]"
,"relLabels":["NO_RELATION"]}

{"words":["He","retired","after","the","2000","season","as","the","NFL","'s","all-time","leader","in","sacks","with","198","."]
,"lemmas":["he","retire","after","the","2000","season","as","the","NFL","'s","all-time","leader","in","sack","with","198","."]
,"posTags":["PRP","VBD","IN","DT","CD","NN","IN","DT","NNP","POS","JJ","NN","IN","NNS","IN","CD","."]
,"chunks":["B-NP","B-VP","B-PP","B-NP","I-NP","I-NP","B-PP","B-NP","I-NP","B-NP","I-NP","I-NP","B-PP","B-NP","B-PP","B-NP","O"]
,"parents":[1,-1,1,5,5,2,1,8,11,8,11,6,11,12,13,14,-2]
,"deprels":["nsubj","root","prep","det","num","pobj","prep","det","poss","possessive","amod","pobj","prep","pobj","prep","pobj",null]
,"naryTree":"((ROOT (S (NP (PRP He)) (VP (VBD retired) (PP (IN after) (NP (DT the) (CD 2000) (NN season))) (PP (IN as) (NP (NP (NP (DT the) (NNP NFL) (POS 's)) (JJ all-time) (NN leader)) (PP (IN in) (NP (NP (NNS sacks)) (PP (IN with) (NP (CD 198)))))))) (. .))))"
,"nePairs":"[{\"m1\":{\"start\":0,\"end\":1,\"head\":0,\"type\":null,\"subtype\":null,\"phraseType\":\"PRO\",\"id\":\"8411bf51-6d1c-5c97-884a-00005a98086d\"},\"m2\":{\"start\":7,\"end\":12,\"head\":11,\"type\":null,\"subtype\":null,\"phraseType\":\"NOM\",\"id\":\"8411bf51-6d1c-5c97-884a-00005a98086e\"}}]"
,"relLabels":["NO_RELATION"]}

{"words":["He","retired","after","the","2000","season","as","the","NFL","'s","all-time","leader","in","sacks","with","198","."]
,"lemmas":["he","retire","after","the","2000","season","as","the","NFL","'s","all-time","leader","in","sack","with","198","."]
,"posTags":["PRP","VBD","IN","DT","CD","NN","IN","DT","NNP","POS","JJ","NN","IN","NNS","IN","CD","."]
,"chunks":["B-NP","B-VP","B-PP","B-NP","I-NP","I-NP","B-PP","B-NP","I-NP","B-NP","I-NP","I-NP","B-PP","B-NP","B-PP","B-NP","O"]
,"parents":[1,-1,1,5,5,2,1,8,11,8,11,6,11,12,13,14,-2]
,"deprels":["nsubj","root","prep","det","num","pobj","prep","det","poss","possessive","amod","pobj","prep","pobj","prep","pobj",null]
,"naryTree":"((ROOT (S (NP (PRP He)) (VP (VBD retired) (PP (IN after) (NP (DT the) (CD 2000) (NN season))) (PP (IN as) (NP (NP (NP (DT the) (NNP NFL) (POS 's)) (JJ all-time) (NN leader)) (PP (IN in) (NP (NP (NNS sacks)) (PP (IN with) (NP (CD 198)))))))) (. .))))"
,"nePairs":"[{\"m1\":{\"start\":8,\"end\":9,\"head\":8,\"type\":null,\"subtype\":null,\"phraseType\":\"NAM\",\"id\":\"8411bf51-6d1c-5c97-884a-00005a98086b\"},\"m2\":{\"start\":7,\"end\":12,\"head\":11,\"type\":null,\"subtype\":null,\"phraseType\":\"NOM\",\"id\":\"8411bf51-6d1c-5c97-884a-00005a98086e\"}}]"
,"relLabels":["NO_RELATION"]}

