{"words":["Good","plan",";","cigarettes","impose","pretty","high","penalties","on","states",",","inasmuch","as","the","states","are","caretakers","for","plenty","of","people","who","are","ill","thanks","to","cigarettes","."]
,"lemmas":["good","plan",";","cigarette","impose","pretty","high","penalty","on","state",",","inasmuch","as","the","state","be","caretaker","for","plenty","of","people","who","be","ill","thanks","to","cigarette","."]
,"posTags":["JJ","NN",":","NNS","VBP","RB","JJ","NNS","IN","NNS",",","NN","IN","DT","NNS","VBP","NNS","IN","NN","IN","NNS","WP","VBP","JJ","NNS","TO","NNS","."]
,"chunks":["B-NP","I-NP","O","B-NP","B-VP","B-NP","I-NP","I-NP","B-PP","B-NP","O","B-NP","B-SBAR","B-NP","I-NP","B-VP","B-NP","B-PP","B-NP","B-PP","B-NP","B-NP","B-VP","B-ADJP","B-ADVP","B-PP","B-NP","O"]
,"parents":[1,-1,-2,4,1,6,7,4,7,8,-2,9,16,14,16,16,4,16,17,18,19,23,23,20,23,24,25,-2]
,"deprels":["amod","root",null,"nsubj","dep","advmod","amod","dobj","prep","pobj",null,"appos","mark","det","nsubj","cop","advcl","prep","pobj","prep","pobj","nsubj","cop","rcmod","advmod","prep","pobj",null]
,"naryTree":"((ROOT (NP (NP (JJ Good) (NN plan)) (: ;) (S (NP (NNS cigarettes)) (VP (VBP impose) (NP (NP (ADJP (RB pretty) (JJ high)) (NNS penalties)) (PP (IN on) (NP (NP (NNS states)) (, ,) (NP (NN inasmuch))))) (SBAR (IN as) (S (NP (DT the) (NNS states)) (VP (VBP are) (NP (NP (NNS caretakers)) (PP (IN for) (NP (NP (NN plenty)) (PP (IN of) (NP (NP (NNS people)) (SBAR (WHNP (WP who)) (S (VP (VBP are) (ADJP (JJ ill)) (ADVP (NNS thanks) (PP (TO to) (NP (NNS cigarettes))))))))))))))))) (. .))))"
,"nePairs":"[{\"m1\":{\"start\":9,\"end\":10,\"head\":9,\"type\":\"GPE\",\"subtype\":\"State-or-Province\",\"phraseType\":\"NOM\",\"id\":\"700002a9-4292-72e9-dc80-00002ca3c330\"},\"m2\":{\"start\":13,\"end\":15,\"head\":14,\"type\":\"GPE\",\"subtype\":\"State-or-Province\",\"phraseType\":\"NOM\",\"id\":\"700002a9-4292-72e9-dc80-00002ca3c331\"}}]"
,"relLabels":["NO_RELATION(Arg-1,Arg-1)"]}

{"words":["Good","plan",";","cigarettes","impose","pretty","high","penalties","on","states",",","inasmuch","as","the","states","are","caretakers","for","plenty","of","people","who","are","ill","thanks","to","cigarettes","."]
,"lemmas":["good","plan",";","cigarette","impose","pretty","high","penalty","on","state",",","inasmuch","as","the","state","be","caretaker","for","plenty","of","people","who","be","ill","thanks","to","cigarette","."]
,"posTags":["JJ","NN",":","NNS","VBP","RB","JJ","NNS","IN","NNS",",","NN","IN","DT","NNS","VBP","NNS","IN","NN","IN","NNS","WP","VBP","JJ","NNS","TO","NNS","."]
,"chunks":["B-NP","I-NP","O","B-NP","B-VP","B-NP","I-NP","I-NP","B-PP","B-NP","O","B-NP","B-SBAR","B-NP","I-NP","B-VP","B-NP","B-PP","B-NP","B-PP","B-NP","B-NP","B-VP","B-ADJP","B-ADVP","B-PP","B-NP","O"]
,"parents":[1,-1,-2,4,1,6,7,4,7,8,-2,9,16,14,16,16,4,16,17,18,19,23,23,20,23,24,25,-2]
,"deprels":["amod","root",null,"nsubj","dep","advmod","amod","dobj","prep","pobj",null,"appos","mark","det","nsubj","cop","advcl","prep","pobj","prep","pobj","nsubj","cop","rcmod","advmod","prep","pobj",null]
,"naryTree":"((ROOT (NP (NP (JJ Good) (NN plan)) (: ;) (S (NP (NNS cigarettes)) (VP (VBP impose) (NP (NP (ADJP (RB pretty) (JJ high)) (NNS penalties)) (PP (IN on) (NP (NP (NNS states)) (, ,) (NP (NN inasmuch))))) (SBAR (IN as) (S (NP (DT the) (NNS states)) (VP (VBP are) (NP (NP (NNS caretakers)) (PP (IN for) (NP (NP (NN plenty)) (PP (IN of) (NP (NP (NNS people)) (SBAR (WHNP (WP who)) (S (VP (VBP are) (ADJP (JJ ill)) (ADVP (NNS thanks) (PP (TO to) (NP (NNS cigarettes))))))))))))))))) (. .))))"
,"nePairs":"[{\"m1\":{\"start\":9,\"end\":10,\"head\":9,\"type\":\"GPE\",\"subtype\":\"State-or-Province\",\"phraseType\":\"NOM\",\"id\":\"700002a9-4292-72e9-dc80-00002ca3c330\"},\"m2\":{\"start\":16,\"end\":17,\"head\":16,\"type\":\"GPE\",\"subtype\":\"State-or-Province\",\"phraseType\":\"NOM\",\"id\":\"700002a9-4292-72e9-dc80-00002ca3c332\"}}]"
,"relLabels":["NO_RELATION(Arg-1,Arg-1)"]}

{"words":["Good","plan",";","cigarettes","impose","pretty","high","penalties","on","states",",","inasmuch","as","the","states","are","caretakers","for","plenty","of","people","who","are","ill","thanks","to","cigarettes","."]
,"lemmas":["good","plan",";","cigarette","impose","pretty","high","penalty","on","state",",","inasmuch","as","the","state","be","caretaker","for","plenty","of","people","who","be","ill","thanks","to","cigarette","."]
,"posTags":["JJ","NN",":","NNS","VBP","RB","JJ","NNS","IN","NNS",",","NN","IN","DT","NNS","VBP","NNS","IN","NN","IN","NNS","WP","VBP","JJ","NNS","TO","NNS","."]
,"chunks":["B-NP","I-NP","O","B-NP","B-VP","B-NP","I-NP","I-NP","B-PP","B-NP","O","B-NP","B-SBAR","B-NP","I-NP","B-VP","B-NP","B-PP","B-NP","B-PP","B-NP","B-NP","B-VP","B-ADJP","B-ADVP","B-PP","B-NP","O"]
,"parents":[1,-1,-2,4,1,6,7,4,7,8,-2,9,16,14,16,16,4,16,17,18,19,23,23,20,23,24,25,-2]
,"deprels":["amod","root",null,"nsubj","dep","advmod","amod","dobj","prep","pobj",null,"appos","mark","det","nsubj","cop","advcl","prep","pobj","prep","pobj","nsubj","cop","rcmod","advmod","prep","pobj",null]
,"naryTree":"((ROOT (NP (NP (JJ Good) (NN plan)) (: ;) (S (NP (NNS cigarettes)) (VP (VBP impose) (NP (NP (ADJP (RB pretty) (JJ high)) (NNS penalties)) (PP (IN on) (NP (NP (NNS states)) (, ,) (NP (NN inasmuch))))) (SBAR (IN as) (S (NP (DT the) (NNS states)) (VP (VBP are) (NP (NP (NNS caretakers)) (PP (IN for) (NP (NP (NN plenty)) (PP (IN of) (NP (NP (NNS people)) (SBAR (WHNP (WP who)) (S (VP (VBP are) (ADJP (JJ ill)) (ADVP (NNS thanks) (PP (TO to) (NP (NNS cigarettes))))))))))))))))) (. .))))"
,"nePairs":"[{\"m1\":{\"start\":9,\"end\":10,\"head\":9,\"type\":\"GPE\",\"subtype\":\"State-or-Province\",\"phraseType\":\"NOM\",\"id\":\"700002a9-4292-72e9-dc80-00002ca3c330\"},\"m2\":{\"start\":18,\"end\":19,\"head\":18,\"type\":\"PER\",\"subtype\":\"Group\",\"phraseType\":\"PRO\",\"id\":\"700002a9-4292-72e9-dc80-00002ca3c338\"}}]"
,"relLabels":["NO_RELATION(Arg-1,Arg-1)"]}

{"words":["Good","plan",";","cigarettes","impose","pretty","high","penalties","on","states",",","inasmuch","as","the","states","are","caretakers","for","plenty","of","people","who","are","ill","thanks","to","cigarettes","."]
,"lemmas":["good","plan",";","cigarette","impose","pretty","high","penalty","on","state",",","inasmuch","as","the","state","be","caretaker","for","plenty","of","people","who","be","ill","thanks","to","cigarette","."]
,"posTags":["JJ","NN",":","NNS","VBP","RB","JJ","NNS","IN","NNS",",","NN","IN","DT","NNS","VBP","NNS","IN","NN","IN","NNS","WP","VBP","JJ","NNS","TO","NNS","."]
,"chunks":["B-NP","I-NP","O","B-NP","B-VP","B-NP","I-NP","I-NP","B-PP","B-NP","O","B-NP","B-SBAR","B-NP","I-NP","B-VP","B-NP","B-PP","B-NP","B-PP","B-NP","B-NP","B-VP","B-ADJP","B-ADVP","B-PP","B-NP","O"]
,"parents":[1,-1,-2,4,1,6,7,4,7,8,-2,9,16,14,16,16,4,16,17,18,19,23,23,20,23,24,25,-2]
,"deprels":["amod","root",null,"nsubj","dep","advmod","amod","dobj","prep","pobj",null,"appos","mark","det","nsubj","cop","advcl","prep","pobj","prep","pobj","nsubj","cop","rcmod","advmod","prep","pobj",null]
,"naryTree":"((ROOT (NP (NP (JJ Good) (NN plan)) (: ;) (S (NP (NNS cigarettes)) (VP (VBP impose) (NP (NP (ADJP (RB pretty) (JJ high)) (NNS penalties)) (PP (IN on) (NP (NP (NNS states)) (, ,) (NP (NN inasmuch))))) (SBAR (IN as) (S (NP (DT the) (NNS states)) (VP (VBP are) (NP (NP (NNS caretakers)) (PP (IN for) (NP (NP (NN plenty)) (PP (IN of) (NP (NP (NNS people)) (SBAR (WHNP (WP who)) (S (VP (VBP are) (ADJP (JJ ill)) (ADVP (NNS thanks) (PP (TO to) (NP (NNS cigarettes))))))))))))))))) (. .))))"
,"nePairs":"[{\"m1\":{\"start\":9,\"end\":10,\"head\":9,\"type\":\"GPE\",\"subtype\":\"State-or-Province\",\"phraseType\":\"NOM\",\"id\":\"700002a9-4292-72e9-dc80-00002ca3c330\"},\"m2\":{\"start\":20,\"end\":21,\"head\":20,\"type\":\"PER\",\"subtype\":\"Group\",\"phraseType\":\"NOM\",\"id\":\"700002a9-4292-72e9-dc80-00002ca3c336\"}}]"
,"relLabels":["NO_RELATION(Arg-1,Arg-1)"]}

{"words":["Good","plan",";","cigarettes","impose","pretty","high","penalties","on","states",",","inasmuch","as","the","states","are","caretakers","for","plenty","of","people","who","are","ill","thanks","to","cigarettes","."]
,"lemmas":["good","plan",";","cigarette","impose","pretty","high","penalty","on","state",",","inasmuch","as","the","state","be","caretaker","for","plenty","of","people","who","be","ill","thanks","to","cigarette","."]
,"posTags":["JJ","NN",":","NNS","VBP","RB","JJ","NNS","IN","NNS",",","NN","IN","DT","NNS","VBP","NNS","IN","NN","IN","NNS","WP","VBP","JJ","NNS","TO","NNS","."]
,"chunks":["B-NP","I-NP","O","B-NP","B-VP","B-NP","I-NP","I-NP","B-PP","B-NP","O","B-NP","B-SBAR","B-NP","I-NP","B-VP","B-NP","B-PP","B-NP","B-PP","B-NP","B-NP","B-VP","B-ADJP","B-ADVP","B-PP","B-NP","O"]
,"parents":[1,-1,-2,4,1,6,7,4,7,8,-2,9,16,14,16,16,4,16,17,18,19,23,23,20,23,24,25,-2]
,"deprels":["amod","root",null,"nsubj","dep","advmod","amod","dobj","prep","pobj",null,"appos","mark","det","nsubj","cop","advcl","prep","pobj","prep","pobj","nsubj","cop","rcmod","advmod","prep","pobj",null]
,"naryTree":"((ROOT (NP (NP (JJ Good) (NN plan)) (: ;) (S (NP (NNS cigarettes)) (VP (VBP impose) (NP (NP (ADJP (RB pretty) (JJ high)) (NNS penalties)) (PP (IN on) (NP (NP (NNS states)) (, ,) (NP (NN inasmuch))))) (SBAR (IN as) (S (NP (DT the) (NNS states)) (VP (VBP are) (NP (NP (NNS caretakers)) (PP (IN for) (NP (NP (NN plenty)) (PP (IN of) (NP (NP (NNS people)) (SBAR (WHNP (WP who)) (S (VP (VBP are) (ADJP (JJ ill)) (ADVP (NNS thanks) (PP (TO to) (NP (NNS cigarettes))))))))))))))))) (. .))))"
,"nePairs":"[{\"m1\":{\"start\":9,\"end\":10,\"head\":9,\"type\":\"GPE\",\"subtype\":\"State-or-Province\",\"phraseType\":\"NOM\",\"id\":\"700002a9-4292-72e9-dc80-00002ca3c330\"},\"m2\":{\"start\":21,\"end\":22,\"head\":21,\"type\":\"PER\",\"subtype\":\"Group\",\"phraseType\":\"PRO\",\"id\":\"700002a9-4292-72e9-dc80-00002ca3c337\"}}]"
,"relLabels":["NO_RELATION(Arg-1,Arg-1)"]}

{"words":["Good","plan",";","cigarettes","impose","pretty","high","penalties","on","states",",","inasmuch","as","the","states","are","caretakers","for","plenty","of","people","who","are","ill","thanks","to","cigarettes","."]
,"lemmas":["good","plan",";","cigarette","impose","pretty","high","penalty","on","state",",","inasmuch","as","the","state","be","caretaker","for","plenty","of","people","who","be","ill","thanks","to","cigarette","."]
,"posTags":["JJ","NN",":","NNS","VBP","RB","JJ","NNS","IN","NNS",",","NN","IN","DT","NNS","VBP","NNS","IN","NN","IN","NNS","WP","VBP","JJ","NNS","TO","NNS","."]
,"chunks":["B-NP","I-NP","O","B-NP","B-VP","B-NP","I-NP","I-NP","B-PP","B-NP","O","B-NP","B-SBAR","B-NP","I-NP","B-VP","B-NP","B-PP","B-NP","B-PP","B-NP","B-NP","B-VP","B-ADJP","B-ADVP","B-PP","B-NP","O"]
,"parents":[1,-1,-2,4,1,6,7,4,7,8,-2,9,16,14,16,16,4,16,17,18,19,23,23,20,23,24,25,-2]
,"deprels":["amod","root",null,"nsubj","dep","advmod","amod","dobj","prep","pobj",null,"appos","mark","det","nsubj","cop","advcl","prep","pobj","prep","pobj","nsubj","cop","rcmod","advmod","prep","pobj",null]
,"naryTree":"((ROOT (NP (NP (JJ Good) (NN plan)) (: ;) (S (NP (NNS cigarettes)) (VP (VBP impose) (NP (NP (ADJP (RB pretty) (JJ high)) (NNS penalties)) (PP (IN on) (NP (NP (NNS states)) (, ,) (NP (NN inasmuch))))) (SBAR (IN as) (S (NP (DT the) (NNS states)) (VP (VBP are) (NP (NP (NNS caretakers)) (PP (IN for) (NP (NP (NN plenty)) (PP (IN of) (NP (NP (NNS people)) (SBAR (WHNP (WP who)) (S (VP (VBP are) (ADJP (JJ ill)) (ADVP (NNS thanks) (PP (TO to) (NP (NNS cigarettes))))))))))))))))) (. .))))"
,"nePairs":"[{\"m1\":{\"start\":13,\"end\":15,\"head\":14,\"type\":\"GPE\",\"subtype\":\"State-or-Province\",\"phraseType\":\"NOM\",\"id\":\"700002a9-4292-72e9-dc80-00002ca3c331\"},\"m2\":{\"start\":16,\"end\":17,\"head\":16,\"type\":\"GPE\",\"subtype\":\"State-or-Province\",\"phraseType\":\"NOM\",\"id\":\"700002a9-4292-72e9-dc80-00002ca3c332\"}}]"
,"relLabels":["NO_RELATION(Arg-1,Arg-1)"]}

{"words":["Good","plan",";","cigarettes","impose","pretty","high","penalties","on","states",",","inasmuch","as","the","states","are","caretakers","for","plenty","of","people","who","are","ill","thanks","to","cigarettes","."]
,"lemmas":["good","plan",";","cigarette","impose","pretty","high","penalty","on","state",",","inasmuch","as","the","state","be","caretaker","for","plenty","of","people","who","be","ill","thanks","to","cigarette","."]
,"posTags":["JJ","NN",":","NNS","VBP","RB","JJ","NNS","IN","NNS",",","NN","IN","DT","NNS","VBP","NNS","IN","NN","IN","NNS","WP","VBP","JJ","NNS","TO","NNS","."]
,"chunks":["B-NP","I-NP","O","B-NP","B-VP","B-NP","I-NP","I-NP","B-PP","B-NP","O","B-NP","B-SBAR","B-NP","I-NP","B-VP","B-NP","B-PP","B-NP","B-PP","B-NP","B-NP","B-VP","B-ADJP","B-ADVP","B-PP","B-NP","O"]
,"parents":[1,-1,-2,4,1,6,7,4,7,8,-2,9,16,14,16,16,4,16,17,18,19,23,23,20,23,24,25,-2]
,"deprels":["amod","root",null,"nsubj","dep","advmod","amod","dobj","prep","pobj",null,"appos","mark","det","nsubj","cop","advcl","prep","pobj","prep","pobj","nsubj","cop","rcmod","advmod","prep","pobj",null]
,"naryTree":"((ROOT (NP (NP (JJ Good) (NN plan)) (: ;) (S (NP (NNS cigarettes)) (VP (VBP impose) (NP (NP (ADJP (RB pretty) (JJ high)) (NNS penalties)) (PP (IN on) (NP (NP (NNS states)) (, ,) (NP (NN inasmuch))))) (SBAR (IN as) (S (NP (DT the) (NNS states)) (VP (VBP are) (NP (NP (NNS caretakers)) (PP (IN for) (NP (NP (NN plenty)) (PP (IN of) (NP (NP (NNS people)) (SBAR (WHNP (WP who)) (S (VP (VBP are) (ADJP (JJ ill)) (ADVP (NNS thanks) (PP (TO to) (NP (NNS cigarettes))))))))))))))))) (. .))))"
,"nePairs":"[{\"m1\":{\"start\":13,\"end\":15,\"head\":14,\"type\":\"GPE\",\"subtype\":\"State-or-Province\",\"phraseType\":\"NOM\",\"id\":\"700002a9-4292-72e9-dc80-00002ca3c331\"},\"m2\":{\"start\":18,\"end\":19,\"head\":18,\"type\":\"PER\",\"subtype\":\"Group\",\"phraseType\":\"PRO\",\"id\":\"700002a9-4292-72e9-dc80-00002ca3c338\"}}]"
,"relLabels":["NO_RELATION(Arg-1,Arg-1)"]}

{"words":["Good","plan",";","cigarettes","impose","pretty","high","penalties","on","states",",","inasmuch","as","the","states","are","caretakers","for","plenty","of","people","who","are","ill","thanks","to","cigarettes","."]
,"lemmas":["good","plan",";","cigarette","impose","pretty","high","penalty","on","state",",","inasmuch","as","the","state","be","caretaker","for","plenty","of","people","who","be","ill","thanks","to","cigarette","."]
,"posTags":["JJ","NN",":","NNS","VBP","RB","JJ","NNS","IN","NNS",",","NN","IN","DT","NNS","VBP","NNS","IN","NN","IN","NNS","WP","VBP","JJ","NNS","TO","NNS","."]
,"chunks":["B-NP","I-NP","O","B-NP","B-VP","B-NP","I-NP","I-NP","B-PP","B-NP","O","B-NP","B-SBAR","B-NP","I-NP","B-VP","B-NP","B-PP","B-NP","B-PP","B-NP","B-NP","B-VP","B-ADJP","B-ADVP","B-PP","B-NP","O"]
,"parents":[1,-1,-2,4,1,6,7,4,7,8,-2,9,16,14,16,16,4,16,17,18,19,23,23,20,23,24,25,-2]
,"deprels":["amod","root",null,"nsubj","dep","advmod","amod","dobj","prep","pobj",null,"appos","mark","det","nsubj","cop","advcl","prep","pobj","prep","pobj","nsubj","cop","rcmod","advmod","prep","pobj",null]
,"naryTree":"((ROOT (NP (NP (JJ Good) (NN plan)) (: ;) (S (NP (NNS cigarettes)) (VP (VBP impose) (NP (NP (ADJP (RB pretty) (JJ high)) (NNS penalties)) (PP (IN on) (NP (NP (NNS states)) (, ,) (NP (NN inasmuch))))) (SBAR (IN as) (S (NP (DT the) (NNS states)) (VP (VBP are) (NP (NP (NNS caretakers)) (PP (IN for) (NP (NP (NN plenty)) (PP (IN of) (NP (NP (NNS people)) (SBAR (WHNP (WP who)) (S (VP (VBP are) (ADJP (JJ ill)) (ADVP (NNS thanks) (PP (TO to) (NP (NNS cigarettes))))))))))))))))) (. .))))"
,"nePairs":"[{\"m1\":{\"start\":13,\"end\":15,\"head\":14,\"type\":\"GPE\",\"subtype\":\"State-or-Province\",\"phraseType\":\"NOM\",\"id\":\"700002a9-4292-72e9-dc80-00002ca3c331\"},\"m2\":{\"start\":20,\"end\":21,\"head\":20,\"type\":\"PER\",\"subtype\":\"Group\",\"phraseType\":\"NOM\",\"id\":\"700002a9-4292-72e9-dc80-00002ca3c336\"}}]"
,"relLabels":["NO_RELATION(Arg-1,Arg-1)"]}

{"words":["Good","plan",";","cigarettes","impose","pretty","high","penalties","on","states",",","inasmuch","as","the","states","are","caretakers","for","plenty","of","people","who","are","ill","thanks","to","cigarettes","."]
,"lemmas":["good","plan",";","cigarette","impose","pretty","high","penalty","on","state",",","inasmuch","as","the","state","be","caretaker","for","plenty","of","people","who","be","ill","thanks","to","cigarette","."]
,"posTags":["JJ","NN",":","NNS","VBP","RB","JJ","NNS","IN","NNS",",","NN","IN","DT","NNS","VBP","NNS","IN","NN","IN","NNS","WP","VBP","JJ","NNS","TO","NNS","."]
,"chunks":["B-NP","I-NP","O","B-NP","B-VP","B-NP","I-NP","I-NP","B-PP","B-NP","O","B-NP","B-SBAR","B-NP","I-NP","B-VP","B-NP","B-PP","B-NP","B-PP","B-NP","B-NP","B-VP","B-ADJP","B-ADVP","B-PP","B-NP","O"]
,"parents":[1,-1,-2,4,1,6,7,4,7,8,-2,9,16,14,16,16,4,16,17,18,19,23,23,20,23,24,25,-2]
,"deprels":["amod","root",null,"nsubj","dep","advmod","amod","dobj","prep","pobj",null,"appos","mark","det","nsubj","cop","advcl","prep","pobj","prep","pobj","nsubj","cop","rcmod","advmod","prep","pobj",null]
,"naryTree":"((ROOT (NP (NP (JJ Good) (NN plan)) (: ;) (S (NP (NNS cigarettes)) (VP (VBP impose) (NP (NP (ADJP (RB pretty) (JJ high)) (NNS penalties)) (PP (IN on) (NP (NP (NNS states)) (, ,) (NP (NN inasmuch))))) (SBAR (IN as) (S (NP (DT the) (NNS states)) (VP (VBP are) (NP (NP (NNS caretakers)) (PP (IN for) (NP (NP (NN plenty)) (PP (IN of) (NP (NP (NNS people)) (SBAR (WHNP (WP who)) (S (VP (VBP are) (ADJP (JJ ill)) (ADVP (NNS thanks) (PP (TO to) (NP (NNS cigarettes))))))))))))))))) (. .))))"
,"nePairs":"[{\"m1\":{\"start\":13,\"end\":15,\"head\":14,\"type\":\"GPE\",\"subtype\":\"State-or-Province\",\"phraseType\":\"NOM\",\"id\":\"700002a9-4292-72e9-dc80-00002ca3c331\"},\"m2\":{\"start\":21,\"end\":22,\"head\":21,\"type\":\"PER\",\"subtype\":\"Group\",\"phraseType\":\"PRO\",\"id\":\"700002a9-4292-72e9-dc80-00002ca3c337\"}}]"
,"relLabels":["NO_RELATION(Arg-1,Arg-1)"]}

{"words":["Good","plan",";","cigarettes","impose","pretty","high","penalties","on","states",",","inasmuch","as","the","states","are","caretakers","for","plenty","of","people","who","are","ill","thanks","to","cigarettes","."]
,"lemmas":["good","plan",";","cigarette","impose","pretty","high","penalty","on","state",",","inasmuch","as","the","state","be","caretaker","for","plenty","of","people","who","be","ill","thanks","to","cigarette","."]
,"posTags":["JJ","NN",":","NNS","VBP","RB","JJ","NNS","IN","NNS",",","NN","IN","DT","NNS","VBP","NNS","IN","NN","IN","NNS","WP","VBP","JJ","NNS","TO","NNS","."]
,"chunks":["B-NP","I-NP","O","B-NP","B-VP","B-NP","I-NP","I-NP","B-PP","B-NP","O","B-NP","B-SBAR","B-NP","I-NP","B-VP","B-NP","B-PP","B-NP","B-PP","B-NP","B-NP","B-VP","B-ADJP","B-ADVP","B-PP","B-NP","O"]
,"parents":[1,-1,-2,4,1,6,7,4,7,8,-2,9,16,14,16,16,4,16,17,18,19,23,23,20,23,24,25,-2]
,"deprels":["amod","root",null,"nsubj","dep","advmod","amod","dobj","prep","pobj",null,"appos","mark","det","nsubj","cop","advcl","prep","pobj","prep","pobj","nsubj","cop","rcmod","advmod","prep","pobj",null]
,"naryTree":"((ROOT (NP (NP (JJ Good) (NN plan)) (: ;) (S (NP (NNS cigarettes)) (VP (VBP impose) (NP (NP (ADJP (RB pretty) (JJ high)) (NNS penalties)) (PP (IN on) (NP (NP (NNS states)) (, ,) (NP (NN inasmuch))))) (SBAR (IN as) (S (NP (DT the) (NNS states)) (VP (VBP are) (NP (NP (NNS caretakers)) (PP (IN for) (NP (NP (NN plenty)) (PP (IN of) (NP (NP (NNS people)) (SBAR (WHNP (WP who)) (S (VP (VBP are) (ADJP (JJ ill)) (ADVP (NNS thanks) (PP (TO to) (NP (NNS cigarettes))))))))))))))))) (. .))))"
,"nePairs":"[{\"m1\":{\"start\":16,\"end\":17,\"head\":16,\"type\":\"GPE\",\"subtype\":\"State-or-Province\",\"phraseType\":\"NOM\",\"id\":\"700002a9-4292-72e9-dc80-00002ca3c332\"},\"m2\":{\"start\":18,\"end\":19,\"head\":18,\"type\":\"PER\",\"subtype\":\"Group\",\"phraseType\":\"PRO\",\"id\":\"700002a9-4292-72e9-dc80-00002ca3c338\"}}]"
,"relLabels":["NO_RELATION(Arg-1,Arg-1)"]}

{"words":["Good","plan",";","cigarettes","impose","pretty","high","penalties","on","states",",","inasmuch","as","the","states","are","caretakers","for","plenty","of","people","who","are","ill","thanks","to","cigarettes","."]
,"lemmas":["good","plan",";","cigarette","impose","pretty","high","penalty","on","state",",","inasmuch","as","the","state","be","caretaker","for","plenty","of","people","who","be","ill","thanks","to","cigarette","."]
,"posTags":["JJ","NN",":","NNS","VBP","RB","JJ","NNS","IN","NNS",",","NN","IN","DT","NNS","VBP","NNS","IN","NN","IN","NNS","WP","VBP","JJ","NNS","TO","NNS","."]
,"chunks":["B-NP","I-NP","O","B-NP","B-VP","B-NP","I-NP","I-NP","B-PP","B-NP","O","B-NP","B-SBAR","B-NP","I-NP","B-VP","B-NP","B-PP","B-NP","B-PP","B-NP","B-NP","B-VP","B-ADJP","B-ADVP","B-PP","B-NP","O"]
,"parents":[1,-1,-2,4,1,6,7,4,7,8,-2,9,16,14,16,16,4,16,17,18,19,23,23,20,23,24,25,-2]
,"deprels":["amod","root",null,"nsubj","dep","advmod","amod","dobj","prep","pobj",null,"appos","mark","det","nsubj","cop","advcl","prep","pobj","prep","pobj","nsubj","cop","rcmod","advmod","prep","pobj",null]
,"naryTree":"((ROOT (NP (NP (JJ Good) (NN plan)) (: ;) (S (NP (NNS cigarettes)) (VP (VBP impose) (NP (NP (ADJP (RB pretty) (JJ high)) (NNS penalties)) (PP (IN on) (NP (NP (NNS states)) (, ,) (NP (NN inasmuch))))) (SBAR (IN as) (S (NP (DT the) (NNS states)) (VP (VBP are) (NP (NP (NNS caretakers)) (PP (IN for) (NP (NP (NN plenty)) (PP (IN of) (NP (NP (NNS people)) (SBAR (WHNP (WP who)) (S (VP (VBP are) (ADJP (JJ ill)) (ADVP (NNS thanks) (PP (TO to) (NP (NNS cigarettes))))))))))))))))) (. .))))"
,"nePairs":"[{\"m1\":{\"start\":16,\"end\":17,\"head\":16,\"type\":\"GPE\",\"subtype\":\"State-or-Province\",\"phraseType\":\"NOM\",\"id\":\"700002a9-4292-72e9-dc80-00002ca3c332\"},\"m2\":{\"start\":20,\"end\":21,\"head\":20,\"type\":\"PER\",\"subtype\":\"Group\",\"phraseType\":\"NOM\",\"id\":\"700002a9-4292-72e9-dc80-00002ca3c336\"}}]"
,"relLabels":["NO_RELATION(Arg-1,Arg-1)"]}

{"words":["Good","plan",";","cigarettes","impose","pretty","high","penalties","on","states",",","inasmuch","as","the","states","are","caretakers","for","plenty","of","people","who","are","ill","thanks","to","cigarettes","."]
,"lemmas":["good","plan",";","cigarette","impose","pretty","high","penalty","on","state",",","inasmuch","as","the","state","be","caretaker","for","plenty","of","people","who","be","ill","thanks","to","cigarette","."]
,"posTags":["JJ","NN",":","NNS","VBP","RB","JJ","NNS","IN","NNS",",","NN","IN","DT","NNS","VBP","NNS","IN","NN","IN","NNS","WP","VBP","JJ","NNS","TO","NNS","."]
,"chunks":["B-NP","I-NP","O","B-NP","B-VP","B-NP","I-NP","I-NP","B-PP","B-NP","O","B-NP","B-SBAR","B-NP","I-NP","B-VP","B-NP","B-PP","B-NP","B-PP","B-NP","B-NP","B-VP","B-ADJP","B-ADVP","B-PP","B-NP","O"]
,"parents":[1,-1,-2,4,1,6,7,4,7,8,-2,9,16,14,16,16,4,16,17,18,19,23,23,20,23,24,25,-2]
,"deprels":["amod","root",null,"nsubj","dep","advmod","amod","dobj","prep","pobj",null,"appos","mark","det","nsubj","cop","advcl","prep","pobj","prep","pobj","nsubj","cop","rcmod","advmod","prep","pobj",null]
,"naryTree":"((ROOT (NP (NP (JJ Good) (NN plan)) (: ;) (S (NP (NNS cigarettes)) (VP (VBP impose) (NP (NP (ADJP (RB pretty) (JJ high)) (NNS penalties)) (PP (IN on) (NP (NP (NNS states)) (, ,) (NP (NN inasmuch))))) (SBAR (IN as) (S (NP (DT the) (NNS states)) (VP (VBP are) (NP (NP (NNS caretakers)) (PP (IN for) (NP (NP (NN plenty)) (PP (IN of) (NP (NP (NNS people)) (SBAR (WHNP (WP who)) (S (VP (VBP are) (ADJP (JJ ill)) (ADVP (NNS thanks) (PP (TO to) (NP (NNS cigarettes))))))))))))))))) (. .))))"
,"nePairs":"[{\"m1\":{\"start\":16,\"end\":17,\"head\":16,\"type\":\"GPE\",\"subtype\":\"State-or-Province\",\"phraseType\":\"NOM\",\"id\":\"700002a9-4292-72e9-dc80-00002ca3c332\"},\"m2\":{\"start\":21,\"end\":22,\"head\":21,\"type\":\"PER\",\"subtype\":\"Group\",\"phraseType\":\"PRO\",\"id\":\"700002a9-4292-72e9-dc80-00002ca3c337\"}}]"
,"relLabels":["NO_RELATION(Arg-1,Arg-1)"]}

{"words":["Good","plan",";","cigarettes","impose","pretty","high","penalties","on","states",",","inasmuch","as","the","states","are","caretakers","for","plenty","of","people","who","are","ill","thanks","to","cigarettes","."]
,"lemmas":["good","plan",";","cigarette","impose","pretty","high","penalty","on","state",",","inasmuch","as","the","state","be","caretaker","for","plenty","of","people","who","be","ill","thanks","to","cigarette","."]
,"posTags":["JJ","NN",":","NNS","VBP","RB","JJ","NNS","IN","NNS",",","NN","IN","DT","NNS","VBP","NNS","IN","NN","IN","NNS","WP","VBP","JJ","NNS","TO","NNS","."]
,"chunks":["B-NP","I-NP","O","B-NP","B-VP","B-NP","I-NP","I-NP","B-PP","B-NP","O","B-NP","B-SBAR","B-NP","I-NP","B-VP","B-NP","B-PP","B-NP","B-PP","B-NP","B-NP","B-VP","B-ADJP","B-ADVP","B-PP","B-NP","O"]
,"parents":[1,-1,-2,4,1,6,7,4,7,8,-2,9,16,14,16,16,4,16,17,18,19,23,23,20,23,24,25,-2]
,"deprels":["amod","root",null,"nsubj","dep","advmod","amod","dobj","prep","pobj",null,"appos","mark","det","nsubj","cop","advcl","prep","pobj","prep","pobj","nsubj","cop","rcmod","advmod","prep","pobj",null]
,"naryTree":"((ROOT (NP (NP (JJ Good) (NN plan)) (: ;) (S (NP (NNS cigarettes)) (VP (VBP impose) (NP (NP (ADJP (RB pretty) (JJ high)) (NNS penalties)) (PP (IN on) (NP (NP (NNS states)) (, ,) (NP (NN inasmuch))))) (SBAR (IN as) (S (NP (DT the) (NNS states)) (VP (VBP are) (NP (NP (NNS caretakers)) (PP (IN for) (NP (NP (NN plenty)) (PP (IN of) (NP (NP (NNS people)) (SBAR (WHNP (WP who)) (S (VP (VBP are) (ADJP (JJ ill)) (ADVP (NNS thanks) (PP (TO to) (NP (NNS cigarettes))))))))))))))))) (. .))))"
,"nePairs":"[{\"m1\":{\"start\":18,\"end\":19,\"head\":18,\"type\":\"PER\",\"subtype\":\"Group\",\"phraseType\":\"PRO\",\"id\":\"700002a9-4292-72e9-dc80-00002ca3c338\"},\"m2\":{\"start\":20,\"end\":21,\"head\":20,\"type\":\"PER\",\"subtype\":\"Group\",\"phraseType\":\"NOM\",\"id\":\"700002a9-4292-72e9-dc80-00002ca3c336\"}}]"
,"relLabels":["NO_RELATION(Arg-1,Arg-1)"]}

{"words":["Good","plan",";","cigarettes","impose","pretty","high","penalties","on","states",",","inasmuch","as","the","states","are","caretakers","for","plenty","of","people","who","are","ill","thanks","to","cigarettes","."]
,"lemmas":["good","plan",";","cigarette","impose","pretty","high","penalty","on","state",",","inasmuch","as","the","state","be","caretaker","for","plenty","of","people","who","be","ill","thanks","to","cigarette","."]
,"posTags":["JJ","NN",":","NNS","VBP","RB","JJ","NNS","IN","NNS",",","NN","IN","DT","NNS","VBP","NNS","IN","NN","IN","NNS","WP","VBP","JJ","NNS","TO","NNS","."]
,"chunks":["B-NP","I-NP","O","B-NP","B-VP","B-NP","I-NP","I-NP","B-PP","B-NP","O","B-NP","B-SBAR","B-NP","I-NP","B-VP","B-NP","B-PP","B-NP","B-PP","B-NP","B-NP","B-VP","B-ADJP","B-ADVP","B-PP","B-NP","O"]
,"parents":[1,-1,-2,4,1,6,7,4,7,8,-2,9,16,14,16,16,4,16,17,18,19,23,23,20,23,24,25,-2]
,"deprels":["amod","root",null,"nsubj","dep","advmod","amod","dobj","prep","pobj",null,"appos","mark","det","nsubj","cop","advcl","prep","pobj","prep","pobj","nsubj","cop","rcmod","advmod","prep","pobj",null]
,"naryTree":"((ROOT (NP (NP (JJ Good) (NN plan)) (: ;) (S (NP (NNS cigarettes)) (VP (VBP impose) (NP (NP (ADJP (RB pretty) (JJ high)) (NNS penalties)) (PP (IN on) (NP (NP (NNS states)) (, ,) (NP (NN inasmuch))))) (SBAR (IN as) (S (NP (DT the) (NNS states)) (VP (VBP are) (NP (NP (NNS caretakers)) (PP (IN for) (NP (NP (NN plenty)) (PP (IN of) (NP (NP (NNS people)) (SBAR (WHNP (WP who)) (S (VP (VBP are) (ADJP (JJ ill)) (ADVP (NNS thanks) (PP (TO to) (NP (NNS cigarettes))))))))))))))))) (. .))))"
,"nePairs":"[{\"m1\":{\"start\":18,\"end\":19,\"head\":18,\"type\":\"PER\",\"subtype\":\"Group\",\"phraseType\":\"PRO\",\"id\":\"700002a9-4292-72e9-dc80-00002ca3c338\"},\"m2\":{\"start\":21,\"end\":22,\"head\":21,\"type\":\"PER\",\"subtype\":\"Group\",\"phraseType\":\"PRO\",\"id\":\"700002a9-4292-72e9-dc80-00002ca3c337\"}}]"
,"relLabels":["NO_RELATION(Arg-1,Arg-1)"]}

{"words":["Good","plan",";","cigarettes","impose","pretty","high","penalties","on","states",",","inasmuch","as","the","states","are","caretakers","for","plenty","of","people","who","are","ill","thanks","to","cigarettes","."]
,"lemmas":["good","plan",";","cigarette","impose","pretty","high","penalty","on","state",",","inasmuch","as","the","state","be","caretaker","for","plenty","of","people","who","be","ill","thanks","to","cigarette","."]
,"posTags":["JJ","NN",":","NNS","VBP","RB","JJ","NNS","IN","NNS",",","NN","IN","DT","NNS","VBP","NNS","IN","NN","IN","NNS","WP","VBP","JJ","NNS","TO","NNS","."]
,"chunks":["B-NP","I-NP","O","B-NP","B-VP","B-NP","I-NP","I-NP","B-PP","B-NP","O","B-NP","B-SBAR","B-NP","I-NP","B-VP","B-NP","B-PP","B-NP","B-PP","B-NP","B-NP","B-VP","B-ADJP","B-ADVP","B-PP","B-NP","O"]
,"parents":[1,-1,-2,4,1,6,7,4,7,8,-2,9,16,14,16,16,4,16,17,18,19,23,23,20,23,24,25,-2]
,"deprels":["amod","root",null,"nsubj","dep","advmod","amod","dobj","prep","pobj",null,"appos","mark","det","nsubj","cop","advcl","prep","pobj","prep","pobj","nsubj","cop","rcmod","advmod","prep","pobj",null]
,"naryTree":"((ROOT (NP (NP (JJ Good) (NN plan)) (: ;) (S (NP (NNS cigarettes)) (VP (VBP impose) (NP (NP (ADJP (RB pretty) (JJ high)) (NNS penalties)) (PP (IN on) (NP (NP (NNS states)) (, ,) (NP (NN inasmuch))))) (SBAR (IN as) (S (NP (DT the) (NNS states)) (VP (VBP are) (NP (NP (NNS caretakers)) (PP (IN for) (NP (NP (NN plenty)) (PP (IN of) (NP (NP (NNS people)) (SBAR (WHNP (WP who)) (S (VP (VBP are) (ADJP (JJ ill)) (ADVP (NNS thanks) (PP (TO to) (NP (NNS cigarettes))))))))))))))))) (. .))))"
,"nePairs":"[{\"m1\":{\"start\":20,\"end\":21,\"head\":20,\"type\":\"PER\",\"subtype\":\"Group\",\"phraseType\":\"NOM\",\"id\":\"700002a9-4292-72e9-dc80-00002ca3c336\"},\"m2\":{\"start\":21,\"end\":22,\"head\":21,\"type\":\"PER\",\"subtype\":\"Group\",\"phraseType\":\"PRO\",\"id\":\"700002a9-4292-72e9-dc80-00002ca3c337\"}}]"
,"relLabels":["NO_RELATION(Arg-1,Arg-1)"]}

{"words":["What","'s","notable","in","this","debate",",","however",",","is","that","according","to","MSN","Moneycentral",",","tobacco","executives","are","attacking","the","tax","by","noting","that","``","While","North","Carolina","'s","excise","tax","is","only","5","cents",",","the","total","taxes","given","to","North","Carolina","by","smokers","adds","up","to","more","than","61","cents","per","pack","."]
,"lemmas":["what","be","notable","in","this","debate",",","however",",","be","that","accord","to","MSN","Moneycentral",",","tobacco","executive","be","attack","the","tax","by","note","that","``","while","North","Carolina","'s","excise","tax","be","only","5","cent",",","the","total","tax","give","to","North","Carolina","by","smoker","add","up","to","more","than","61","cent","per","pack","."]
,"posTags":["WP","VBZ","JJ","IN","DT","NN",",","RB",",","VBZ","IN","VBG","TO","NNP","NNP",",","NN","NNS","VBP","VBG","DT","NN","IN","VBG","IN","``","IN","NNP","NNP","POS","JJ","NN","VBZ","RB","CD","NNS",",","DT","JJ","NNS","VBN","TO","NNP","NNP","IN","NNS","VBZ","RP","TO","JJR","IN","CD","NNS","IN","NN","."]
,"chunks":["B-NP","B-VP","B-ADJP","B-PP","B-NP","I-NP","O","B-ADVP","O","B-VP","B-SBAR","B-PP","B-PP","B-NP","I-NP","O","B-NP","I-NP","B-VP","I-VP","B-NP","I-NP","B-PP","B-VP","B-SBAR","O","B-SBAR","B-NP","I-NP","B-NP","I-NP","I-NP","B-VP","B-NP","I-NP","I-NP","O","B-NP","I-NP","I-NP","B-PP","B-PP","B-NP","I-NP","B-PP","B-NP","B-VP","B-PRT","B-PP","B-NP","I-NP","I-NP","I-NP","B-PP","B-NP","O"]
,"parents":[2,2,9,2,5,3,-2,9,-2,-1,19,19,11,14,12,-2,17,19,19,9,21,19,19,22,46,-2,35,28,31,28,31,35,35,34,35,46,-2,39,39,46,39,40,43,41,43,44,23,46,46,50,51,52,48,52,53,-2]
,"deprels":["nsubj","cop","dep","prep","det","pobj",null,"advmod",null,"root","mark","prep","pcomp","nn","pobj",null,"nn","nsubj","aux","ccomp","det","dobj","prep","pcomp","mark",null,"mark","nn","poss","possessive","amod","nsubj","cop","quantmod","num","advcl",null,"det","amod","nsubj","prep","pcomp","nn","pobj","prep","pobj","ccomp","prt","prep","mwe","quantmod","num","pobj","prep","pobj",null]
,"naryTree":"((ROOT (S (SBAR (WHNP (WP What)) (S (VP (VBZ 's) (ADJP (JJ notable) (PP (IN in) (NP (DT this) (NN debate))))))) (, ,) (ADVP (RB however)) (, ,) (VP (VBZ is) (SBAR (IN that) (S (PP (VBG according) (PP (TO to) (NP (NNP MSN) (NNP Moneycentral)))) (, ,) (NP (NN tobacco) (NNS executives)) (VP (VBP are) (VP (VBG attacking) (NP (DT the) (NN tax)) (PP (IN by) (S (VP (VBG noting) (SBAR (IN that) (`` ``) (S (SBAR (IN While) (S (NP (NP (NNP North) (NNP Carolina) (POS 's)) (JJ excise) (NN tax)) (VP (VBZ is) (NP (QP (RB only) (CD 5)) (NNS cents))))) (, ,) (NP (NP (DT the) (JJ total) (NNS taxes)) (PP (VBN given) (PP (TO to) (NP (NP (NNP North) (NNP Carolina)) (PP (IN by) (NP (NNS smokers))))))) (VP (VBZ adds) (PRT (RP up)) (PP (TO to) (NP (NP (QP (JJR more) (IN than) (CD 61)) (NNS cents)) (PP (IN per) (NP (NN pack)))))))))))))))) (. .))))"
,"nePairs":"[{\"m1\":{\"start\":13,\"end\":15,\"head\":14,\"type\":\"ORG\",\"subtype\":\"Commercial\",\"phraseType\":\"NAM\",\"id\":\"700002a9-4292-72e9-dc80-00002ca3c33f\"},\"m2\":{\"start\":16,\"end\":18,\"head\":17,\"type\":\"PER\",\"subtype\":\"Group\",\"phraseType\":\"NOM\",\"id\":\"700002a9-4292-72e9-dc80-00002ca3c341\"}}]"
,"relLabels":["NO_RELATION(Arg-1,Arg-1)"]}

{"words":["What","'s","notable","in","this","debate",",","however",",","is","that","according","to","MSN","Moneycentral",",","tobacco","executives","are","attacking","the","tax","by","noting","that","``","While","North","Carolina","'s","excise","tax","is","only","5","cents",",","the","total","taxes","given","to","North","Carolina","by","smokers","adds","up","to","more","than","61","cents","per","pack","."]
,"lemmas":["what","be","notable","in","this","debate",",","however",",","be","that","accord","to","MSN","Moneycentral",",","tobacco","executive","be","attack","the","tax","by","note","that","``","while","North","Carolina","'s","excise","tax","be","only","5","cent",",","the","total","tax","give","to","North","Carolina","by","smoker","add","up","to","more","than","61","cent","per","pack","."]
,"posTags":["WP","VBZ","JJ","IN","DT","NN",",","RB",",","VBZ","IN","VBG","TO","NNP","NNP",",","NN","NNS","VBP","VBG","DT","NN","IN","VBG","IN","``","IN","NNP","NNP","POS","JJ","NN","VBZ","RB","CD","NNS",",","DT","JJ","NNS","VBN","TO","NNP","NNP","IN","NNS","VBZ","RP","TO","JJR","IN","CD","NNS","IN","NN","."]
,"chunks":["B-NP","B-VP","B-ADJP","B-PP","B-NP","I-NP","O","B-ADVP","O","B-VP","B-SBAR","B-PP","B-PP","B-NP","I-NP","O","B-NP","I-NP","B-VP","I-VP","B-NP","I-NP","B-PP","B-VP","B-SBAR","O","B-SBAR","B-NP","I-NP","B-NP","I-NP","I-NP","B-VP","B-NP","I-NP","I-NP","O","B-NP","I-NP","I-NP","B-PP","B-PP","B-NP","I-NP","B-PP","B-NP","B-VP","B-PRT","B-PP","B-NP","I-NP","I-NP","I-NP","B-PP","B-NP","O"]
,"parents":[2,2,9,2,5,3,-2,9,-2,-1,19,19,11,14,12,-2,17,19,19,9,21,19,19,22,46,-2,35,28,31,28,31,35,35,34,35,46,-2,39,39,46,39,40,43,41,43,44,23,46,46,50,51,52,48,52,53,-2]
,"deprels":["nsubj","cop","dep","prep","det","pobj",null,"advmod",null,"root","mark","prep","pcomp","nn","pobj",null,"nn","nsubj","aux","ccomp","det","dobj","prep","pcomp","mark",null,"mark","nn","poss","possessive","amod","nsubj","cop","quantmod","num","advcl",null,"det","amod","nsubj","prep","pcomp","nn","pobj","prep","pobj","ccomp","prt","prep","mwe","quantmod","num","pobj","prep","pobj",null]
,"naryTree":"((ROOT (S (SBAR (WHNP (WP What)) (S (VP (VBZ 's) (ADJP (JJ notable) (PP (IN in) (NP (DT this) (NN debate))))))) (, ,) (ADVP (RB however)) (, ,) (VP (VBZ is) (SBAR (IN that) (S (PP (VBG according) (PP (TO to) (NP (NNP MSN) (NNP Moneycentral)))) (, ,) (NP (NN tobacco) (NNS executives)) (VP (VBP are) (VP (VBG attacking) (NP (DT the) (NN tax)) (PP (IN by) (S (VP (VBG noting) (SBAR (IN that) (`` ``) (S (SBAR (IN While) (S (NP (NP (NNP North) (NNP Carolina) (POS 's)) (JJ excise) (NN tax)) (VP (VBZ is) (NP (QP (RB only) (CD 5)) (NNS cents))))) (, ,) (NP (NP (DT the) (JJ total) (NNS taxes)) (PP (VBN given) (PP (TO to) (NP (NP (NNP North) (NNP Carolina)) (PP (IN by) (NP (NNS smokers))))))) (VP (VBZ adds) (PRT (RP up)) (PP (TO to) (NP (NP (QP (JJR more) (IN than) (CD 61)) (NNS cents)) (PP (IN per) (NP (NN pack)))))))))))))))) (. .))))"
,"nePairs":"[{\"m1\":{\"start\":13,\"end\":15,\"head\":14,\"type\":\"ORG\",\"subtype\":\"Commercial\",\"phraseType\":\"NAM\",\"id\":\"700002a9-4292-72e9-dc80-00002ca3c33f\"},\"m2\":{\"start\":27,\"end\":29,\"head\":28,\"type\":\"GPE\",\"subtype\":\"State-or-Province\",\"phraseType\":\"NAM\",\"id\":\"700002a9-4292-72e9-dc80-00002ca3c343\"}}]"
,"relLabels":["NO_RELATION(Arg-1,Arg-1)"]}

{"words":["What","'s","notable","in","this","debate",",","however",",","is","that","according","to","MSN","Moneycentral",",","tobacco","executives","are","attacking","the","tax","by","noting","that","``","While","North","Carolina","'s","excise","tax","is","only","5","cents",",","the","total","taxes","given","to","North","Carolina","by","smokers","adds","up","to","more","than","61","cents","per","pack","."]
,"lemmas":["what","be","notable","in","this","debate",",","however",",","be","that","accord","to","MSN","Moneycentral",",","tobacco","executive","be","attack","the","tax","by","note","that","``","while","North","Carolina","'s","excise","tax","be","only","5","cent",",","the","total","tax","give","to","North","Carolina","by","smoker","add","up","to","more","than","61","cent","per","pack","."]
,"posTags":["WP","VBZ","JJ","IN","DT","NN",",","RB",",","VBZ","IN","VBG","TO","NNP","NNP",",","NN","NNS","VBP","VBG","DT","NN","IN","VBG","IN","``","IN","NNP","NNP","POS","JJ","NN","VBZ","RB","CD","NNS",",","DT","JJ","NNS","VBN","TO","NNP","NNP","IN","NNS","VBZ","RP","TO","JJR","IN","CD","NNS","IN","NN","."]
,"chunks":["B-NP","B-VP","B-ADJP","B-PP","B-NP","I-NP","O","B-ADVP","O","B-VP","B-SBAR","B-PP","B-PP","B-NP","I-NP","O","B-NP","I-NP","B-VP","I-VP","B-NP","I-NP","B-PP","B-VP","B-SBAR","O","B-SBAR","B-NP","I-NP","B-NP","I-NP","I-NP","B-VP","B-NP","I-NP","I-NP","O","B-NP","I-NP","I-NP","B-PP","B-PP","B-NP","I-NP","B-PP","B-NP","B-VP","B-PRT","B-PP","B-NP","I-NP","I-NP","I-NP","B-PP","B-NP","O"]
,"parents":[2,2,9,2,5,3,-2,9,-2,-1,19,19,11,14,12,-2,17,19,19,9,21,19,19,22,46,-2,35,28,31,28,31,35,35,34,35,46,-2,39,39,46,39,40,43,41,43,44,23,46,46,50,51,52,48,52,53,-2]
,"deprels":["nsubj","cop","dep","prep","det","pobj",null,"advmod",null,"root","mark","prep","pcomp","nn","pobj",null,"nn","nsubj","aux","ccomp","det","dobj","prep","pcomp","mark",null,"mark","nn","poss","possessive","amod","nsubj","cop","quantmod","num","advcl",null,"det","amod","nsubj","prep","pcomp","nn","pobj","prep","pobj","ccomp","prt","prep","mwe","quantmod","num","pobj","prep","pobj",null]
,"naryTree":"((ROOT (S (SBAR (WHNP (WP What)) (S (VP (VBZ 's) (ADJP (JJ notable) (PP (IN in) (NP (DT this) (NN debate))))))) (, ,) (ADVP (RB however)) (, ,) (VP (VBZ is) (SBAR (IN that) (S (PP (VBG according) (PP (TO to) (NP (NNP MSN) (NNP Moneycentral)))) (, ,) (NP (NN tobacco) (NNS executives)) (VP (VBP are) (VP (VBG attacking) (NP (DT the) (NN tax)) (PP (IN by) (S (VP (VBG noting) (SBAR (IN that) (`` ``) (S (SBAR (IN While) (S (NP (NP (NNP North) (NNP Carolina) (POS 's)) (JJ excise) (NN tax)) (VP (VBZ is) (NP (QP (RB only) (CD 5)) (NNS cents))))) (, ,) (NP (NP (DT the) (JJ total) (NNS taxes)) (PP (VBN given) (PP (TO to) (NP (NP (NNP North) (NNP Carolina)) (PP (IN by) (NP (NNS smokers))))))) (VP (VBZ adds) (PRT (RP up)) (PP (TO to) (NP (NP (QP (JJR more) (IN than) (CD 61)) (NNS cents)) (PP (IN per) (NP (NN pack)))))))))))))))) (. .))))"
,"nePairs":"[{\"m1\":{\"start\":13,\"end\":15,\"head\":14,\"type\":\"ORG\",\"subtype\":\"Commercial\",\"phraseType\":\"NAM\",\"id\":\"700002a9-4292-72e9-dc80-00002ca3c33f\"},\"m2\":{\"start\":42,\"end\":44,\"head\":43,\"type\":\"GPE\",\"subtype\":\"State-or-Province\",\"phraseType\":\"NAM\",\"id\":\"700002a9-4292-72e9-dc80-00002ca3c344\"}}]"
,"relLabels":["NO_RELATION(Arg-1,Arg-1)"]}

{"words":["What","'s","notable","in","this","debate",",","however",",","is","that","according","to","MSN","Moneycentral",",","tobacco","executives","are","attacking","the","tax","by","noting","that","``","While","North","Carolina","'s","excise","tax","is","only","5","cents",",","the","total","taxes","given","to","North","Carolina","by","smokers","adds","up","to","more","than","61","cents","per","pack","."]
,"lemmas":["what","be","notable","in","this","debate",",","however",",","be","that","accord","to","MSN","Moneycentral",",","tobacco","executive","be","attack","the","tax","by","note","that","``","while","North","Carolina","'s","excise","tax","be","only","5","cent",",","the","total","tax","give","to","North","Carolina","by","smoker","add","up","to","more","than","61","cent","per","pack","."]
,"posTags":["WP","VBZ","JJ","IN","DT","NN",",","RB",",","VBZ","IN","VBG","TO","NNP","NNP",",","NN","NNS","VBP","VBG","DT","NN","IN","VBG","IN","``","IN","NNP","NNP","POS","JJ","NN","VBZ","RB","CD","NNS",",","DT","JJ","NNS","VBN","TO","NNP","NNP","IN","NNS","VBZ","RP","TO","JJR","IN","CD","NNS","IN","NN","."]
,"chunks":["B-NP","B-VP","B-ADJP","B-PP","B-NP","I-NP","O","B-ADVP","O","B-VP","B-SBAR","B-PP","B-PP","B-NP","I-NP","O","B-NP","I-NP","B-VP","I-VP","B-NP","I-NP","B-PP","B-VP","B-SBAR","O","B-SBAR","B-NP","I-NP","B-NP","I-NP","I-NP","B-VP","B-NP","I-NP","I-NP","O","B-NP","I-NP","I-NP","B-PP","B-PP","B-NP","I-NP","B-PP","B-NP","B-VP","B-PRT","B-PP","B-NP","I-NP","I-NP","I-NP","B-PP","B-NP","O"]
,"parents":[2,2,9,2,5,3,-2,9,-2,-1,19,19,11,14,12,-2,17,19,19,9,21,19,19,22,46,-2,35,28,31,28,31,35,35,34,35,46,-2,39,39,46,39,40,43,41,43,44,23,46,46,50,51,52,48,52,53,-2]
,"deprels":["nsubj","cop","dep","prep","det","pobj",null,"advmod",null,"root","mark","prep","pcomp","nn","pobj",null,"nn","nsubj","aux","ccomp","det","dobj","prep","pcomp","mark",null,"mark","nn","poss","possessive","amod","nsubj","cop","quantmod","num","advcl",null,"det","amod","nsubj","prep","pcomp","nn","pobj","prep","pobj","ccomp","prt","prep","mwe","quantmod","num","pobj","prep","pobj",null]
,"naryTree":"((ROOT (S (SBAR (WHNP (WP What)) (S (VP (VBZ 's) (ADJP (JJ notable) (PP (IN in) (NP (DT this) (NN debate))))))) (, ,) (ADVP (RB however)) (, ,) (VP (VBZ is) (SBAR (IN that) (S (PP (VBG according) (PP (TO to) (NP (NNP MSN) (NNP Moneycentral)))) (, ,) (NP (NN tobacco) (NNS executives)) (VP (VBP are) (VP (VBG attacking) (NP (DT the) (NN tax)) (PP (IN by) (S (VP (VBG noting) (SBAR (IN that) (`` ``) (S (SBAR (IN While) (S (NP (NP (NNP North) (NNP Carolina) (POS 's)) (JJ excise) (NN tax)) (VP (VBZ is) (NP (QP (RB only) (CD 5)) (NNS cents))))) (, ,) (NP (NP (DT the) (JJ total) (NNS taxes)) (PP (VBN given) (PP (TO to) (NP (NP (NNP North) (NNP Carolina)) (PP (IN by) (NP (NNS smokers))))))) (VP (VBZ adds) (PRT (RP up)) (PP (TO to) (NP (NP (QP (JJR more) (IN than) (CD 61)) (NNS cents)) (PP (IN per) (NP (NN pack)))))))))))))))) (. .))))"
,"nePairs":"[{\"m1\":{\"start\":13,\"end\":15,\"head\":14,\"type\":\"ORG\",\"subtype\":\"Commercial\",\"phraseType\":\"NAM\",\"id\":\"700002a9-4292-72e9-dc80-00002ca3c33f\"},\"m2\":{\"start\":45,\"end\":46,\"head\":45,\"type\":\"PER\",\"subtype\":\"Group\",\"phraseType\":\"NOM\",\"id\":\"700002a9-4292-72e9-dc80-00002ca3c347\"}}]"
,"relLabels":["NO_RELATION(Arg-1,Arg-1)"]}

{"words":["What","'s","notable","in","this","debate",",","however",",","is","that","according","to","MSN","Moneycentral",",","tobacco","executives","are","attacking","the","tax","by","noting","that","``","While","North","Carolina","'s","excise","tax","is","only","5","cents",",","the","total","taxes","given","to","North","Carolina","by","smokers","adds","up","to","more","than","61","cents","per","pack","."]
,"lemmas":["what","be","notable","in","this","debate",",","however",",","be","that","accord","to","MSN","Moneycentral",",","tobacco","executive","be","attack","the","tax","by","note","that","``","while","North","Carolina","'s","excise","tax","be","only","5","cent",",","the","total","tax","give","to","North","Carolina","by","smoker","add","up","to","more","than","61","cent","per","pack","."]
,"posTags":["WP","VBZ","JJ","IN","DT","NN",",","RB",",","VBZ","IN","VBG","TO","NNP","NNP",",","NN","NNS","VBP","VBG","DT","NN","IN","VBG","IN","``","IN","NNP","NNP","POS","JJ","NN","VBZ","RB","CD","NNS",",","DT","JJ","NNS","VBN","TO","NNP","NNP","IN","NNS","VBZ","RP","TO","JJR","IN","CD","NNS","IN","NN","."]
,"chunks":["B-NP","B-VP","B-ADJP","B-PP","B-NP","I-NP","O","B-ADVP","O","B-VP","B-SBAR","B-PP","B-PP","B-NP","I-NP","O","B-NP","I-NP","B-VP","I-VP","B-NP","I-NP","B-PP","B-VP","B-SBAR","O","B-SBAR","B-NP","I-NP","B-NP","I-NP","I-NP","B-VP","B-NP","I-NP","I-NP","O","B-NP","I-NP","I-NP","B-PP","B-PP","B-NP","I-NP","B-PP","B-NP","B-VP","B-PRT","B-PP","B-NP","I-NP","I-NP","I-NP","B-PP","B-NP","O"]
,"parents":[2,2,9,2,5,3,-2,9,-2,-1,19,19,11,14,12,-2,17,19,19,9,21,19,19,22,46,-2,35,28,31,28,31,35,35,34,35,46,-2,39,39,46,39,40,43,41,43,44,23,46,46,50,51,52,48,52,53,-2]
,"deprels":["nsubj","cop","dep","prep","det","pobj",null,"advmod",null,"root","mark","prep","pcomp","nn","pobj",null,"nn","nsubj","aux","ccomp","det","dobj","prep","pcomp","mark",null,"mark","nn","poss","possessive","amod","nsubj","cop","quantmod","num","advcl",null,"det","amod","nsubj","prep","pcomp","nn","pobj","prep","pobj","ccomp","prt","prep","mwe","quantmod","num","pobj","prep","pobj",null]
,"naryTree":"((ROOT (S (SBAR (WHNP (WP What)) (S (VP (VBZ 's) (ADJP (JJ notable) (PP (IN in) (NP (DT this) (NN debate))))))) (, ,) (ADVP (RB however)) (, ,) (VP (VBZ is) (SBAR (IN that) (S (PP (VBG according) (PP (TO to) (NP (NNP MSN) (NNP Moneycentral)))) (, ,) (NP (NN tobacco) (NNS executives)) (VP (VBP are) (VP (VBG attacking) (NP (DT the) (NN tax)) (PP (IN by) (S (VP (VBG noting) (SBAR (IN that) (`` ``) (S (SBAR (IN While) (S (NP (NP (NNP North) (NNP Carolina) (POS 's)) (JJ excise) (NN tax)) (VP (VBZ is) (NP (QP (RB only) (CD 5)) (NNS cents))))) (, ,) (NP (NP (DT the) (JJ total) (NNS taxes)) (PP (VBN given) (PP (TO to) (NP (NP (NNP North) (NNP Carolina)) (PP (IN by) (NP (NNS smokers))))))) (VP (VBZ adds) (PRT (RP up)) (PP (TO to) (NP (NP (QP (JJR more) (IN than) (CD 61)) (NNS cents)) (PP (IN per) (NP (NN pack)))))))))))))))) (. .))))"
,"nePairs":"[{\"m1\":{\"start\":16,\"end\":18,\"head\":17,\"type\":\"PER\",\"subtype\":\"Group\",\"phraseType\":\"NOM\",\"id\":\"700002a9-4292-72e9-dc80-00002ca3c341\"},\"m2\":{\"start\":27,\"end\":29,\"head\":28,\"type\":\"GPE\",\"subtype\":\"State-or-Province\",\"phraseType\":\"NAM\",\"id\":\"700002a9-4292-72e9-dc80-00002ca3c343\"}}]"
,"relLabels":["NO_RELATION(Arg-1,Arg-1)"]}

{"words":["What","'s","notable","in","this","debate",",","however",",","is","that","according","to","MSN","Moneycentral",",","tobacco","executives","are","attacking","the","tax","by","noting","that","``","While","North","Carolina","'s","excise","tax","is","only","5","cents",",","the","total","taxes","given","to","North","Carolina","by","smokers","adds","up","to","more","than","61","cents","per","pack","."]
,"lemmas":["what","be","notable","in","this","debate",",","however",",","be","that","accord","to","MSN","Moneycentral",",","tobacco","executive","be","attack","the","tax","by","note","that","``","while","North","Carolina","'s","excise","tax","be","only","5","cent",",","the","total","tax","give","to","North","Carolina","by","smoker","add","up","to","more","than","61","cent","per","pack","."]
,"posTags":["WP","VBZ","JJ","IN","DT","NN",",","RB",",","VBZ","IN","VBG","TO","NNP","NNP",",","NN","NNS","VBP","VBG","DT","NN","IN","VBG","IN","``","IN","NNP","NNP","POS","JJ","NN","VBZ","RB","CD","NNS",",","DT","JJ","NNS","VBN","TO","NNP","NNP","IN","NNS","VBZ","RP","TO","JJR","IN","CD","NNS","IN","NN","."]
,"chunks":["B-NP","B-VP","B-ADJP","B-PP","B-NP","I-NP","O","B-ADVP","O","B-VP","B-SBAR","B-PP","B-PP","B-NP","I-NP","O","B-NP","I-NP","B-VP","I-VP","B-NP","I-NP","B-PP","B-VP","B-SBAR","O","B-SBAR","B-NP","I-NP","B-NP","I-NP","I-NP","B-VP","B-NP","I-NP","I-NP","O","B-NP","I-NP","I-NP","B-PP","B-PP","B-NP","I-NP","B-PP","B-NP","B-VP","B-PRT","B-PP","B-NP","I-NP","I-NP","I-NP","B-PP","B-NP","O"]
,"parents":[2,2,9,2,5,3,-2,9,-2,-1,19,19,11,14,12,-2,17,19,19,9,21,19,19,22,46,-2,35,28,31,28,31,35,35,34,35,46,-2,39,39,46,39,40,43,41,43,44,23,46,46,50,51,52,48,52,53,-2]
,"deprels":["nsubj","cop","dep","prep","det","pobj",null,"advmod",null,"root","mark","prep","pcomp","nn","pobj",null,"nn","nsubj","aux","ccomp","det","dobj","prep","pcomp","mark",null,"mark","nn","poss","possessive","amod","nsubj","cop","quantmod","num","advcl",null,"det","amod","nsubj","prep","pcomp","nn","pobj","prep","pobj","ccomp","prt","prep","mwe","quantmod","num","pobj","prep","pobj",null]
,"naryTree":"((ROOT (S (SBAR (WHNP (WP What)) (S (VP (VBZ 's) (ADJP (JJ notable) (PP (IN in) (NP (DT this) (NN debate))))))) (, ,) (ADVP (RB however)) (, ,) (VP (VBZ is) (SBAR (IN that) (S (PP (VBG according) (PP (TO to) (NP (NNP MSN) (NNP Moneycentral)))) (, ,) (NP (NN tobacco) (NNS executives)) (VP (VBP are) (VP (VBG attacking) (NP (DT the) (NN tax)) (PP (IN by) (S (VP (VBG noting) (SBAR (IN that) (`` ``) (S (SBAR (IN While) (S (NP (NP (NNP North) (NNP Carolina) (POS 's)) (JJ excise) (NN tax)) (VP (VBZ is) (NP (QP (RB only) (CD 5)) (NNS cents))))) (, ,) (NP (NP (DT the) (JJ total) (NNS taxes)) (PP (VBN given) (PP (TO to) (NP (NP (NNP North) (NNP Carolina)) (PP (IN by) (NP (NNS smokers))))))) (VP (VBZ adds) (PRT (RP up)) (PP (TO to) (NP (NP (QP (JJR more) (IN than) (CD 61)) (NNS cents)) (PP (IN per) (NP (NN pack)))))))))))))))) (. .))))"
,"nePairs":"[{\"m1\":{\"start\":16,\"end\":18,\"head\":17,\"type\":\"PER\",\"subtype\":\"Group\",\"phraseType\":\"NOM\",\"id\":\"700002a9-4292-72e9-dc80-00002ca3c341\"},\"m2\":{\"start\":42,\"end\":44,\"head\":43,\"type\":\"GPE\",\"subtype\":\"State-or-Province\",\"phraseType\":\"NAM\",\"id\":\"700002a9-4292-72e9-dc80-00002ca3c344\"}}]"
,"relLabels":["NO_RELATION(Arg-1,Arg-1)"]}

{"words":["What","'s","notable","in","this","debate",",","however",",","is","that","according","to","MSN","Moneycentral",",","tobacco","executives","are","attacking","the","tax","by","noting","that","``","While","North","Carolina","'s","excise","tax","is","only","5","cents",",","the","total","taxes","given","to","North","Carolina","by","smokers","adds","up","to","more","than","61","cents","per","pack","."]
,"lemmas":["what","be","notable","in","this","debate",",","however",",","be","that","accord","to","MSN","Moneycentral",",","tobacco","executive","be","attack","the","tax","by","note","that","``","while","North","Carolina","'s","excise","tax","be","only","5","cent",",","the","total","tax","give","to","North","Carolina","by","smoker","add","up","to","more","than","61","cent","per","pack","."]
,"posTags":["WP","VBZ","JJ","IN","DT","NN",",","RB",",","VBZ","IN","VBG","TO","NNP","NNP",",","NN","NNS","VBP","VBG","DT","NN","IN","VBG","IN","``","IN","NNP","NNP","POS","JJ","NN","VBZ","RB","CD","NNS",",","DT","JJ","NNS","VBN","TO","NNP","NNP","IN","NNS","VBZ","RP","TO","JJR","IN","CD","NNS","IN","NN","."]
,"chunks":["B-NP","B-VP","B-ADJP","B-PP","B-NP","I-NP","O","B-ADVP","O","B-VP","B-SBAR","B-PP","B-PP","B-NP","I-NP","O","B-NP","I-NP","B-VP","I-VP","B-NP","I-NP","B-PP","B-VP","B-SBAR","O","B-SBAR","B-NP","I-NP","B-NP","I-NP","I-NP","B-VP","B-NP","I-NP","I-NP","O","B-NP","I-NP","I-NP","B-PP","B-PP","B-NP","I-NP","B-PP","B-NP","B-VP","B-PRT","B-PP","B-NP","I-NP","I-NP","I-NP","B-PP","B-NP","O"]
,"parents":[2,2,9,2,5,3,-2,9,-2,-1,19,19,11,14,12,-2,17,19,19,9,21,19,19,22,46,-2,35,28,31,28,31,35,35,34,35,46,-2,39,39,46,39,40,43,41,43,44,23,46,46,50,51,52,48,52,53,-2]
,"deprels":["nsubj","cop","dep","prep","det","pobj",null,"advmod",null,"root","mark","prep","pcomp","nn","pobj",null,"nn","nsubj","aux","ccomp","det","dobj","prep","pcomp","mark",null,"mark","nn","poss","possessive","amod","nsubj","cop","quantmod","num","advcl",null,"det","amod","nsubj","prep","pcomp","nn","pobj","prep","pobj","ccomp","prt","prep","mwe","quantmod","num","pobj","prep","pobj",null]
,"naryTree":"((ROOT (S (SBAR (WHNP (WP What)) (S (VP (VBZ 's) (ADJP (JJ notable) (PP (IN in) (NP (DT this) (NN debate))))))) (, ,) (ADVP (RB however)) (, ,) (VP (VBZ is) (SBAR (IN that) (S (PP (VBG according) (PP (TO to) (NP (NNP MSN) (NNP Moneycentral)))) (, ,) (NP (NN tobacco) (NNS executives)) (VP (VBP are) (VP (VBG attacking) (NP (DT the) (NN tax)) (PP (IN by) (S (VP (VBG noting) (SBAR (IN that) (`` ``) (S (SBAR (IN While) (S (NP (NP (NNP North) (NNP Carolina) (POS 's)) (JJ excise) (NN tax)) (VP (VBZ is) (NP (QP (RB only) (CD 5)) (NNS cents))))) (, ,) (NP (NP (DT the) (JJ total) (NNS taxes)) (PP (VBN given) (PP (TO to) (NP (NP (NNP North) (NNP Carolina)) (PP (IN by) (NP (NNS smokers))))))) (VP (VBZ adds) (PRT (RP up)) (PP (TO to) (NP (NP (QP (JJR more) (IN than) (CD 61)) (NNS cents)) (PP (IN per) (NP (NN pack)))))))))))))))) (. .))))"
,"nePairs":"[{\"m1\":{\"start\":16,\"end\":18,\"head\":17,\"type\":\"PER\",\"subtype\":\"Group\",\"phraseType\":\"NOM\",\"id\":\"700002a9-4292-72e9-dc80-00002ca3c341\"},\"m2\":{\"start\":45,\"end\":46,\"head\":45,\"type\":\"PER\",\"subtype\":\"Group\",\"phraseType\":\"NOM\",\"id\":\"700002a9-4292-72e9-dc80-00002ca3c347\"}}]"
,"relLabels":["NO_RELATION(Arg-1,Arg-1)"]}

{"words":["What","'s","notable","in","this","debate",",","however",",","is","that","according","to","MSN","Moneycentral",",","tobacco","executives","are","attacking","the","tax","by","noting","that","``","While","North","Carolina","'s","excise","tax","is","only","5","cents",",","the","total","taxes","given","to","North","Carolina","by","smokers","adds","up","to","more","than","61","cents","per","pack","."]
,"lemmas":["what","be","notable","in","this","debate",",","however",",","be","that","accord","to","MSN","Moneycentral",",","tobacco","executive","be","attack","the","tax","by","note","that","``","while","North","Carolina","'s","excise","tax","be","only","5","cent",",","the","total","tax","give","to","North","Carolina","by","smoker","add","up","to","more","than","61","cent","per","pack","."]
,"posTags":["WP","VBZ","JJ","IN","DT","NN",",","RB",",","VBZ","IN","VBG","TO","NNP","NNP",",","NN","NNS","VBP","VBG","DT","NN","IN","VBG","IN","``","IN","NNP","NNP","POS","JJ","NN","VBZ","RB","CD","NNS",",","DT","JJ","NNS","VBN","TO","NNP","NNP","IN","NNS","VBZ","RP","TO","JJR","IN","CD","NNS","IN","NN","."]
,"chunks":["B-NP","B-VP","B-ADJP","B-PP","B-NP","I-NP","O","B-ADVP","O","B-VP","B-SBAR","B-PP","B-PP","B-NP","I-NP","O","B-NP","I-NP","B-VP","I-VP","B-NP","I-NP","B-PP","B-VP","B-SBAR","O","B-SBAR","B-NP","I-NP","B-NP","I-NP","I-NP","B-VP","B-NP","I-NP","I-NP","O","B-NP","I-NP","I-NP","B-PP","B-PP","B-NP","I-NP","B-PP","B-NP","B-VP","B-PRT","B-PP","B-NP","I-NP","I-NP","I-NP","B-PP","B-NP","O"]
,"parents":[2,2,9,2,5,3,-2,9,-2,-1,19,19,11,14,12,-2,17,19,19,9,21,19,19,22,46,-2,35,28,31,28,31,35,35,34,35,46,-2,39,39,46,39,40,43,41,43,44,23,46,46,50,51,52,48,52,53,-2]
,"deprels":["nsubj","cop","dep","prep","det","pobj",null,"advmod",null,"root","mark","prep","pcomp","nn","pobj",null,"nn","nsubj","aux","ccomp","det","dobj","prep","pcomp","mark",null,"mark","nn","poss","possessive","amod","nsubj","cop","quantmod","num","advcl",null,"det","amod","nsubj","prep","pcomp","nn","pobj","prep","pobj","ccomp","prt","prep","mwe","quantmod","num","pobj","prep","pobj",null]
,"naryTree":"((ROOT (S (SBAR (WHNP (WP What)) (S (VP (VBZ 's) (ADJP (JJ notable) (PP (IN in) (NP (DT this) (NN debate))))))) (, ,) (ADVP (RB however)) (, ,) (VP (VBZ is) (SBAR (IN that) (S (PP (VBG according) (PP (TO to) (NP (NNP MSN) (NNP Moneycentral)))) (, ,) (NP (NN tobacco) (NNS executives)) (VP (VBP are) (VP (VBG attacking) (NP (DT the) (NN tax)) (PP (IN by) (S (VP (VBG noting) (SBAR (IN that) (`` ``) (S (SBAR (IN While) (S (NP (NP (NNP North) (NNP Carolina) (POS 's)) (JJ excise) (NN tax)) (VP (VBZ is) (NP (QP (RB only) (CD 5)) (NNS cents))))) (, ,) (NP (NP (DT the) (JJ total) (NNS taxes)) (PP (VBN given) (PP (TO to) (NP (NP (NNP North) (NNP Carolina)) (PP (IN by) (NP (NNS smokers))))))) (VP (VBZ adds) (PRT (RP up)) (PP (TO to) (NP (NP (QP (JJR more) (IN than) (CD 61)) (NNS cents)) (PP (IN per) (NP (NN pack)))))))))))))))) (. .))))"
,"nePairs":"[{\"m1\":{\"start\":27,\"end\":29,\"head\":28,\"type\":\"GPE\",\"subtype\":\"State-or-Province\",\"phraseType\":\"NAM\",\"id\":\"700002a9-4292-72e9-dc80-00002ca3c343\"},\"m2\":{\"start\":42,\"end\":44,\"head\":43,\"type\":\"GPE\",\"subtype\":\"State-or-Province\",\"phraseType\":\"NAM\",\"id\":\"700002a9-4292-72e9-dc80-00002ca3c344\"}}]"
,"relLabels":["NO_RELATION(Arg-1,Arg-1)"]}

{"words":["What","'s","notable","in","this","debate",",","however",",","is","that","according","to","MSN","Moneycentral",",","tobacco","executives","are","attacking","the","tax","by","noting","that","``","While","North","Carolina","'s","excise","tax","is","only","5","cents",",","the","total","taxes","given","to","North","Carolina","by","smokers","adds","up","to","more","than","61","cents","per","pack","."]
,"lemmas":["what","be","notable","in","this","debate",",","however",",","be","that","accord","to","MSN","Moneycentral",",","tobacco","executive","be","attack","the","tax","by","note","that","``","while","North","Carolina","'s","excise","tax","be","only","5","cent",",","the","total","tax","give","to","North","Carolina","by","smoker","add","up","to","more","than","61","cent","per","pack","."]
,"posTags":["WP","VBZ","JJ","IN","DT","NN",",","RB",",","VBZ","IN","VBG","TO","NNP","NNP",",","NN","NNS","VBP","VBG","DT","NN","IN","VBG","IN","``","IN","NNP","NNP","POS","JJ","NN","VBZ","RB","CD","NNS",",","DT","JJ","NNS","VBN","TO","NNP","NNP","IN","NNS","VBZ","RP","TO","JJR","IN","CD","NNS","IN","NN","."]
,"chunks":["B-NP","B-VP","B-ADJP","B-PP","B-NP","I-NP","O","B-ADVP","O","B-VP","B-SBAR","B-PP","B-PP","B-NP","I-NP","O","B-NP","I-NP","B-VP","I-VP","B-NP","I-NP","B-PP","B-VP","B-SBAR","O","B-SBAR","B-NP","I-NP","B-NP","I-NP","I-NP","B-VP","B-NP","I-NP","I-NP","O","B-NP","I-NP","I-NP","B-PP","B-PP","B-NP","I-NP","B-PP","B-NP","B-VP","B-PRT","B-PP","B-NP","I-NP","I-NP","I-NP","B-PP","B-NP","O"]
,"parents":[2,2,9,2,5,3,-2,9,-2,-1,19,19,11,14,12,-2,17,19,19,9,21,19,19,22,46,-2,35,28,31,28,31,35,35,34,35,46,-2,39,39,46,39,40,43,41,43,44,23,46,46,50,51,52,48,52,53,-2]
,"deprels":["nsubj","cop","dep","prep","det","pobj",null,"advmod",null,"root","mark","prep","pcomp","nn","pobj",null,"nn","nsubj","aux","ccomp","det","dobj","prep","pcomp","mark",null,"mark","nn","poss","possessive","amod","nsubj","cop","quantmod","num","advcl",null,"det","amod","nsubj","prep","pcomp","nn","pobj","prep","pobj","ccomp","prt","prep","mwe","quantmod","num","pobj","prep","pobj",null]
,"naryTree":"((ROOT (S (SBAR (WHNP (WP What)) (S (VP (VBZ 's) (ADJP (JJ notable) (PP (IN in) (NP (DT this) (NN debate))))))) (, ,) (ADVP (RB however)) (, ,) (VP (VBZ is) (SBAR (IN that) (S (PP (VBG according) (PP (TO to) (NP (NNP MSN) (NNP Moneycentral)))) (, ,) (NP (NN tobacco) (NNS executives)) (VP (VBP are) (VP (VBG attacking) (NP (DT the) (NN tax)) (PP (IN by) (S (VP (VBG noting) (SBAR (IN that) (`` ``) (S (SBAR (IN While) (S (NP (NP (NNP North) (NNP Carolina) (POS 's)) (JJ excise) (NN tax)) (VP (VBZ is) (NP (QP (RB only) (CD 5)) (NNS cents))))) (, ,) (NP (NP (DT the) (JJ total) (NNS taxes)) (PP (VBN given) (PP (TO to) (NP (NP (NNP North) (NNP Carolina)) (PP (IN by) (NP (NNS smokers))))))) (VP (VBZ adds) (PRT (RP up)) (PP (TO to) (NP (NP (QP (JJR more) (IN than) (CD 61)) (NNS cents)) (PP (IN per) (NP (NN pack)))))))))))))))) (. .))))"
,"nePairs":"[{\"m1\":{\"start\":27,\"end\":29,\"head\":28,\"type\":\"GPE\",\"subtype\":\"State-or-Province\",\"phraseType\":\"NAM\",\"id\":\"700002a9-4292-72e9-dc80-00002ca3c343\"},\"m2\":{\"start\":45,\"end\":46,\"head\":45,\"type\":\"PER\",\"subtype\":\"Group\",\"phraseType\":\"NOM\",\"id\":\"700002a9-4292-72e9-dc80-00002ca3c347\"}}]"
,"relLabels":["NO_RELATION(Arg-1,Arg-1)"]}

{"words":["What","'s","notable","in","this","debate",",","however",",","is","that","according","to","MSN","Moneycentral",",","tobacco","executives","are","attacking","the","tax","by","noting","that","``","While","North","Carolina","'s","excise","tax","is","only","5","cents",",","the","total","taxes","given","to","North","Carolina","by","smokers","adds","up","to","more","than","61","cents","per","pack","."]
,"lemmas":["what","be","notable","in","this","debate",",","however",",","be","that","accord","to","MSN","Moneycentral",",","tobacco","executive","be","attack","the","tax","by","note","that","``","while","North","Carolina","'s","excise","tax","be","only","5","cent",",","the","total","tax","give","to","North","Carolina","by","smoker","add","up","to","more","than","61","cent","per","pack","."]
,"posTags":["WP","VBZ","JJ","IN","DT","NN",",","RB",",","VBZ","IN","VBG","TO","NNP","NNP",",","NN","NNS","VBP","VBG","DT","NN","IN","VBG","IN","``","IN","NNP","NNP","POS","JJ","NN","VBZ","RB","CD","NNS",",","DT","JJ","NNS","VBN","TO","NNP","NNP","IN","NNS","VBZ","RP","TO","JJR","IN","CD","NNS","IN","NN","."]
,"chunks":["B-NP","B-VP","B-ADJP","B-PP","B-NP","I-NP","O","B-ADVP","O","B-VP","B-SBAR","B-PP","B-PP","B-NP","I-NP","O","B-NP","I-NP","B-VP","I-VP","B-NP","I-NP","B-PP","B-VP","B-SBAR","O","B-SBAR","B-NP","I-NP","B-NP","I-NP","I-NP","B-VP","B-NP","I-NP","I-NP","O","B-NP","I-NP","I-NP","B-PP","B-PP","B-NP","I-NP","B-PP","B-NP","B-VP","B-PRT","B-PP","B-NP","I-NP","I-NP","I-NP","B-PP","B-NP","O"]
,"parents":[2,2,9,2,5,3,-2,9,-2,-1,19,19,11,14,12,-2,17,19,19,9,21,19,19,22,46,-2,35,28,31,28,31,35,35,34,35,46,-2,39,39,46,39,40,43,41,43,44,23,46,46,50,51,52,48,52,53,-2]
,"deprels":["nsubj","cop","dep","prep","det","pobj",null,"advmod",null,"root","mark","prep","pcomp","nn","pobj",null,"nn","nsubj","aux","ccomp","det","dobj","prep","pcomp","mark",null,"mark","nn","poss","possessive","amod","nsubj","cop","quantmod","num","advcl",null,"det","amod","nsubj","prep","pcomp","nn","pobj","prep","pobj","ccomp","prt","prep","mwe","quantmod","num","pobj","prep","pobj",null]
,"naryTree":"((ROOT (S (SBAR (WHNP (WP What)) (S (VP (VBZ 's) (ADJP (JJ notable) (PP (IN in) (NP (DT this) (NN debate))))))) (, ,) (ADVP (RB however)) (, ,) (VP (VBZ is) (SBAR (IN that) (S (PP (VBG according) (PP (TO to) (NP (NNP MSN) (NNP Moneycentral)))) (, ,) (NP (NN tobacco) (NNS executives)) (VP (VBP are) (VP (VBG attacking) (NP (DT the) (NN tax)) (PP (IN by) (S (VP (VBG noting) (SBAR (IN that) (`` ``) (S (SBAR (IN While) (S (NP (NP (NNP North) (NNP Carolina) (POS 's)) (JJ excise) (NN tax)) (VP (VBZ is) (NP (QP (RB only) (CD 5)) (NNS cents))))) (, ,) (NP (NP (DT the) (JJ total) (NNS taxes)) (PP (VBN given) (PP (TO to) (NP (NP (NNP North) (NNP Carolina)) (PP (IN by) (NP (NNS smokers))))))) (VP (VBZ adds) (PRT (RP up)) (PP (TO to) (NP (NP (QP (JJR more) (IN than) (CD 61)) (NNS cents)) (PP (IN per) (NP (NN pack)))))))))))))))) (. .))))"
,"nePairs":"[{\"m1\":{\"start\":42,\"end\":44,\"head\":43,\"type\":\"GPE\",\"subtype\":\"State-or-Province\",\"phraseType\":\"NAM\",\"id\":\"700002a9-4292-72e9-dc80-00002ca3c344\"},\"m2\":{\"start\":45,\"end\":46,\"head\":45,\"type\":\"PER\",\"subtype\":\"Group\",\"phraseType\":\"NOM\",\"id\":\"700002a9-4292-72e9-dc80-00002ca3c347\"}}]"
,"relLabels":["NO_RELATION(Arg-1,Arg-1)"]}

{"words":["''","Okay",",","okay","--","since","the","tobacco","companies","pay","lots","of","money","to","the","states",",","that","'s","technically","accurate","."]
,"lemmas":["''","okay",",","okay","--","since","the","tobacco","company","pay","lot","of","money","to","the","state",",","that","be","technically","accurate","."]
,"posTags":["''","UH",",","JJ",":","IN","DT","NN","NNS","VBP","NNS","IN","NN","TO","DT","NNS",",","DT","VBZ","RB","JJ","."]
,"chunks":["O","B-INTJ","O","B-ADJP","O","B-ADVP","B-NP","I-NP","B-NP","B-VP","B-NP","B-PP","B-NP","B-PP","B-NP","I-NP","O","B-NP","B-VP","B-ADJP","I-ADJP","O"]
,"parents":[-2,9,-2,9,-2,7,7,3,7,20,9,10,11,9,15,13,-2,20,20,20,-1,-2]
,"deprels":[null,"discourse",null,"dep",null,"dep","det","dep","dep","ccomp","dobj","prep","pobj","prep","det","pobj",null,"nsubj","cop","advmod","root",null]
,"naryTree":"((ROOT (S ('' '') (S (INTJ (UH Okay)) (, ,) (ADJP (ADJP (JJ okay)) (PRN (: --) (ADVP (IN since)) (NP (NP (DT the) (NN tobacco)) (NP (NNS companies))))) (VP (VBP pay) (NP (NP (NNS lots)) (PP (IN of) (NP (NN money)))) (PP (TO to) (NP (DT the) (NNS states))))) (, ,) (NP (DT that)) (VP (VBZ 's) (ADJP (RB technically) (JJ accurate))) (. .))))"
,"nePairs":"[{\"m1\":{\"start\":6,\"end\":9,\"head\":8,\"type\":\"ORG\",\"subtype\":\"Commercial\",\"phraseType\":\"NOM\",\"id\":\"700002a9-4292-72e9-dc80-00002ca3c33c\"},\"m2\":{\"start\":14,\"end\":16,\"head\":15,\"type\":\"GPE\",\"subtype\":\"State-or-Province\",\"phraseType\":\"NOM\",\"id\":\"700002a9-4292-72e9-dc80-00002ca3c333\"}}]"
,"relLabels":["NO_RELATION(Arg-1,Arg-1)"]}

{"words":["But","the","point","of","these","taxes","is","to","align","the","price","of","a","pack","with","the","cost","to","society",",","and","inasmuch","as","these","penalties","are","n't","assessed","on","a","per-pack","basis",",","they","do","n't","--","they","'re","a","lump-sum","reflection","of","the","taxes","these","companies","ought","to","have","paid","before","."]
,"lemmas":["but","the","point","of","these","tax","be","to","align","the","price","of","a","pack","with","the","cost","to","society",",","and","inasmuch","as","these","penalty","be","not","assess","on","a","per-pack","basis",",","they","do","not","--","they","be","a","lump-sum","reflection","of","the","tax","these","company","ought","to","have","pay","before","."]
,"posTags":["CC","DT","NN","IN","DT","NNS","VBZ","TO","VB","DT","NN","IN","DT","NN","IN","DT","NN","TO","NN",",","CC","NN","IN","DT","NNS","VBP","RB","VBN","IN","DT","JJ","NN",",","PRP","VBP","RB",":","PRP","VBP","DT","JJ","NN","IN","DT","NNS","DT","NNS","MD","TO","VB","VBN","RB","."]
,"chunks":["O","B-NP","I-NP","B-PP","B-NP","I-NP","B-VP","B-VP","I-VP","B-NP","I-NP","B-PP","B-NP","I-NP","B-PP","B-NP","I-NP","B-PP","B-NP","O","O","B-NP","B-PP","B-NP","I-NP","B-VP","I-VP","I-VP","B-PP","B-NP","I-NP","I-NP","O","B-NP","B-VP","O","O","B-NP","B-VP","B-NP","I-NP","I-NP","B-PP","B-NP","I-NP","B-NP","I-NP","B-VP","B-VP","I-VP","I-VP","B-ADVP","O"]
,"parents":[6,2,6,2,5,3,-1,8,6,10,8,10,13,11,13,16,14,8,17,-2,6,27,21,24,22,27,27,6,27,31,31,28,-2,34,6,34,-2,41,41,41,41,6,41,44,42,46,47,44,50,50,47,50,-2]
,"deprels":["cc","det","nsubj","prep","det","pobj","root","aux","xcomp","det","dobj","prep","det","pobj","prep","det","pobj","prep","pobj",null,"cc","nsubjpass","prep","det","pobj","auxpass","neg","conj","prep","det","amod","pobj",null,"nsubj","parataxis","neg",null,"nsubj","cop","det","amod","parataxis","prep","det","pobj","det","nsubj","rcmod","aux","aux","xcomp","advmod",null]
,"naryTree":"((ROOT (S (S (CC But) (S (NP (NP (DT the) (NN point)) (PP (IN of) (NP (DT these) (NNS taxes)))) (VP (VBZ is) (S (VP (TO to) (VP (VB align) (NP (NP (DT the) (NN price)) (PP (IN of) (NP (NP (DT a) (NN pack)) (PP (IN with) (NP (DT the) (NN cost)))))) (PP (TO to) (NP (NN society)))))))) (, ,) (CC and) (S (NP (NP (NN inasmuch)) (PP (IN as) (NP (DT these) (NNS penalties)))) (VP (VBP are) (RB n't) (VP (VBN assessed) (PP (IN on) (NP (DT a) (JJ per-pack) (NN basis)))))) (, ,) (S (NP (PRP they)) (VP (VBP do) (RB n't)))) (: --) (S (NP (PRP they)) (VP (VBP 're) (NP (NP (DT a) (JJ lump-sum) (NN reflection)) (PP (IN of) (NP (NP (DT the) (NNS taxes)) (SBAR (S (NP (DT these) (NNS companies)) (VP (MD ought) (S (VP (TO to) (VP (VB have) (VP (VBN paid) (ADVP (RB before)))))))))))))) (. .))))"
,"nePairs":"[{\"m1\":{\"start\":18,\"end\":19,\"head\":18,\"type\":\"PER\",\"subtype\":\"Group\",\"phraseType\":\"NOM\",\"id\":\"700002a9-4292-72e9-dc80-00002ca3c32e\"},\"m2\":{\"start\":45,\"end\":47,\"head\":46,\"type\":\"ORG\",\"subtype\":\"Commercial\",\"phraseType\":\"NOM\",\"id\":\"700002a9-4292-72e9-dc80-00002ca3c33d\"}}]"
,"relLabels":["NO_RELATION(Arg-1,Arg-1)"]}

{"words":["Interestingly",",","the","policy","of","making","cigarette","buyers","pay","to","compensate","society","for","the","costs","they","impose","is","a","politically","palatable","synthesis","of","the","unpalatable","notion","of","simply","refusing","treatment","unless","they","pay","full","cost","."]
,"lemmas":["interestingly",",","the","policy","of","make","cigarette","buyer","pay","to","compensate","society","for","the","cost","they","impose","be","a","politically","palatable","synthesis","of","the","unpalatable","notion","of","simply","refuse","treatment","unless","they","pay","full","cost","."]
,"posTags":["RB",",","DT","NN","IN","VBG","NN","NNS","VBP","TO","VB","NN","IN","DT","NNS","PRP","VBP","VBZ","DT","RB","JJ","NN","IN","DT","JJ","NN","IN","RB","VBG","NN","IN","PRP","VBP","JJ","NN","."]
,"chunks":["B-ADVP","O","B-NP","I-NP","B-PP","B-VP","B-NP","I-NP","B-VP","B-VP","I-VP","B-NP","B-PP","B-NP","I-NP","B-NP","B-VP","B-VP","B-NP","I-NP","I-NP","I-NP","B-PP","B-NP","I-NP","I-NP","B-PP","B-VP","I-VP","B-NP","B-SBAR","B-NP","B-VP","B-NP","I-NP","O"]
,"parents":[8,-2,3,8,3,4,7,5,-1,10,8,10,10,14,12,16,10,21,21,20,21,16,21,25,25,22,25,28,26,28,32,32,10,34,32,-2]
,"deprels":["advmod",null,"det","nsubj","prep","pcomp","nn","dobj","root","aux","xcomp","dobj","prep","det","pobj","nsubj","dep","cop","det","advmod","amod","ccomp","prep","det","amod","pobj","prep","advmod","pcomp","dobj","mark","nsubj","advcl","amod","dobj",null]
,"naryTree":"((ROOT (S (ADVP (RB Interestingly)) (, ,) (NP (NP (DT the) (NN policy)) (PP (IN of) (S (VP (VBG making) (NP (NN cigarette) (NNS buyers)))))) (VP (VBP pay) (S (VP (TO to) (VP (VB compensate) (NP (NN society)) (PP (IN for) (NP (DT the) (NNS costs))) (SBAR (S (NP (PRP they)) (VP (VBP impose) (SBAR (S (VP (VBZ is) (NP (NP (DT a) (ADJP (RB politically) (JJ palatable)) (NN synthesis)) (PP (IN of) (NP (NP (DT the) (JJ unpalatable) (NN notion)) (PP (IN of) (S (VP (ADVP (RB simply)) (VBG refusing) (NP (NN treatment)))))))))))))) (SBAR (IN unless) (S (NP (PRP they)) (VP (VBP pay) (NP (JJ full) (NN cost))))))))) (. .))))"
,"nePairs":"[{\"m1\":{\"start\":6,\"end\":8,\"head\":7,\"type\":\"PER\",\"subtype\":\"Group\",\"phraseType\":\"NOM\",\"id\":\"700002a9-4292-72e9-dc80-00002ca3c348\"},\"m2\":{\"start\":11,\"end\":12,\"head\":11,\"type\":\"PER\",\"subtype\":\"Group\",\"phraseType\":\"NOM\",\"id\":\"700002a9-4292-72e9-dc80-00002ca3c32d\"}}]"
,"relLabels":["NO_RELATION(Arg-1,Arg-1)"]}

{"words":["Interestingly",",","the","policy","of","making","cigarette","buyers","pay","to","compensate","society","for","the","costs","they","impose","is","a","politically","palatable","synthesis","of","the","unpalatable","notion","of","simply","refusing","treatment","unless","they","pay","full","cost","."]
,"lemmas":["interestingly",",","the","policy","of","make","cigarette","buyer","pay","to","compensate","society","for","the","cost","they","impose","be","a","politically","palatable","synthesis","of","the","unpalatable","notion","of","simply","refuse","treatment","unless","they","pay","full","cost","."]
,"posTags":["RB",",","DT","NN","IN","VBG","NN","NNS","VBP","TO","VB","NN","IN","DT","NNS","PRP","VBP","VBZ","DT","RB","JJ","NN","IN","DT","JJ","NN","IN","RB","VBG","NN","IN","PRP","VBP","JJ","NN","."]
,"chunks":["B-ADVP","O","B-NP","I-NP","B-PP","B-VP","B-NP","I-NP","B-VP","B-VP","I-VP","B-NP","B-PP","B-NP","I-NP","B-NP","B-VP","B-VP","B-NP","I-NP","I-NP","I-NP","B-PP","B-NP","I-NP","I-NP","B-PP","B-VP","I-VP","B-NP","B-SBAR","B-NP","B-VP","B-NP","I-NP","O"]
,"parents":[8,-2,3,8,3,4,7,5,-1,10,8,10,10,14,12,16,10,21,21,20,21,16,21,25,25,22,25,28,26,28,32,32,10,34,32,-2]
,"deprels":["advmod",null,"det","nsubj","prep","pcomp","nn","dobj","root","aux","xcomp","dobj","prep","det","pobj","nsubj","dep","cop","det","advmod","amod","ccomp","prep","det","amod","pobj","prep","advmod","pcomp","dobj","mark","nsubj","advcl","amod","dobj",null]
,"naryTree":"((ROOT (S (ADVP (RB Interestingly)) (, ,) (NP (NP (DT the) (NN policy)) (PP (IN of) (S (VP (VBG making) (NP (NN cigarette) (NNS buyers)))))) (VP (VBP pay) (S (VP (TO to) (VP (VB compensate) (NP (NN society)) (PP (IN for) (NP (DT the) (NNS costs))) (SBAR (S (NP (PRP they)) (VP (VBP impose) (SBAR (S (VP (VBZ is) (NP (NP (DT a) (ADJP (RB politically) (JJ palatable)) (NN synthesis)) (PP (IN of) (NP (NP (DT the) (JJ unpalatable) (NN notion)) (PP (IN of) (S (VP (ADVP (RB simply)) (VBG refusing) (NP (NN treatment)))))))))))))) (SBAR (IN unless) (S (NP (PRP they)) (VP (VBP pay) (NP (JJ full) (NN cost))))))))) (. .))))"
,"nePairs":"[{\"m1\":{\"start\":6,\"end\":8,\"head\":7,\"type\":\"PER\",\"subtype\":\"Group\",\"phraseType\":\"NOM\",\"id\":\"700002a9-4292-72e9-dc80-00002ca3c348\"},\"m2\":{\"start\":15,\"end\":16,\"head\":15,\"type\":\"PER\",\"subtype\":\"Group\",\"phraseType\":\"PRO\",\"id\":\"700002a9-4292-72e9-dc80-00002ca3c346\"}}]"
,"relLabels":["NO_RELATION(Arg-1,Arg-1)"]}

{"words":["Interestingly",",","the","policy","of","making","cigarette","buyers","pay","to","compensate","society","for","the","costs","they","impose","is","a","politically","palatable","synthesis","of","the","unpalatable","notion","of","simply","refusing","treatment","unless","they","pay","full","cost","."]
,"lemmas":["interestingly",",","the","policy","of","make","cigarette","buyer","pay","to","compensate","society","for","the","cost","they","impose","be","a","politically","palatable","synthesis","of","the","unpalatable","notion","of","simply","refuse","treatment","unless","they","pay","full","cost","."]
,"posTags":["RB",",","DT","NN","IN","VBG","NN","NNS","VBP","TO","VB","NN","IN","DT","NNS","PRP","VBP","VBZ","DT","RB","JJ","NN","IN","DT","JJ","NN","IN","RB","VBG","NN","IN","PRP","VBP","JJ","NN","."]
,"chunks":["B-ADVP","O","B-NP","I-NP","B-PP","B-VP","B-NP","I-NP","B-VP","B-VP","I-VP","B-NP","B-PP","B-NP","I-NP","B-NP","B-VP","B-VP","B-NP","I-NP","I-NP","I-NP","B-PP","B-NP","I-NP","I-NP","B-PP","B-VP","I-VP","B-NP","B-SBAR","B-NP","B-VP","B-NP","I-NP","O"]
,"parents":[8,-2,3,8,3,4,7,5,-1,10,8,10,10,14,12,16,10,21,21,20,21,16,21,25,25,22,25,28,26,28,32,32,10,34,32,-2]
,"deprels":["advmod",null,"det","nsubj","prep","pcomp","nn","dobj","root","aux","xcomp","dobj","prep","det","pobj","nsubj","dep","cop","det","advmod","amod","ccomp","prep","det","amod","pobj","prep","advmod","pcomp","dobj","mark","nsubj","advcl","amod","dobj",null]
,"naryTree":"((ROOT (S (ADVP (RB Interestingly)) (, ,) (NP (NP (DT the) (NN policy)) (PP (IN of) (S (VP (VBG making) (NP (NN cigarette) (NNS buyers)))))) (VP (VBP pay) (S (VP (TO to) (VP (VB compensate) (NP (NN society)) (PP (IN for) (NP (DT the) (NNS costs))) (SBAR (S (NP (PRP they)) (VP (VBP impose) (SBAR (S (VP (VBZ is) (NP (NP (DT a) (ADJP (RB politically) (JJ palatable)) (NN synthesis)) (PP (IN of) (NP (NP (DT the) (JJ unpalatable) (NN notion)) (PP (IN of) (S (VP (ADVP (RB simply)) (VBG refusing) (NP (NN treatment)))))))))))))) (SBAR (IN unless) (S (NP (PRP they)) (VP (VBP pay) (NP (JJ full) (NN cost))))))))) (. .))))"
,"nePairs":"[{\"m1\":{\"start\":6,\"end\":8,\"head\":7,\"type\":\"PER\",\"subtype\":\"Group\",\"phraseType\":\"NOM\",\"id\":\"700002a9-4292-72e9-dc80-00002ca3c348\"},\"m2\":{\"start\":31,\"end\":32,\"head\":31,\"type\":\"PER\",\"subtype\":\"Group\",\"phraseType\":\"PRO\",\"id\":\"700002a9-4292-72e9-dc80-00002ca3c349\"}}]"
,"relLabels":["NO_RELATION(Arg-1,Arg-1)"]}

{"words":["Interestingly",",","the","policy","of","making","cigarette","buyers","pay","to","compensate","society","for","the","costs","they","impose","is","a","politically","palatable","synthesis","of","the","unpalatable","notion","of","simply","refusing","treatment","unless","they","pay","full","cost","."]
,"lemmas":["interestingly",",","the","policy","of","make","cigarette","buyer","pay","to","compensate","society","for","the","cost","they","impose","be","a","politically","palatable","synthesis","of","the","unpalatable","notion","of","simply","refuse","treatment","unless","they","pay","full","cost","."]
,"posTags":["RB",",","DT","NN","IN","VBG","NN","NNS","VBP","TO","VB","NN","IN","DT","NNS","PRP","VBP","VBZ","DT","RB","JJ","NN","IN","DT","JJ","NN","IN","RB","VBG","NN","IN","PRP","VBP","JJ","NN","."]
,"chunks":["B-ADVP","O","B-NP","I-NP","B-PP","B-VP","B-NP","I-NP","B-VP","B-VP","I-VP","B-NP","B-PP","B-NP","I-NP","B-NP","B-VP","B-VP","B-NP","I-NP","I-NP","I-NP","B-PP","B-NP","I-NP","I-NP","B-PP","B-VP","I-VP","B-NP","B-SBAR","B-NP","B-VP","B-NP","I-NP","O"]
,"parents":[8,-2,3,8,3,4,7,5,-1,10,8,10,10,14,12,16,10,21,21,20,21,16,21,25,25,22,25,28,26,28,32,32,10,34,32,-2]
,"deprels":["advmod",null,"det","nsubj","prep","pcomp","nn","dobj","root","aux","xcomp","dobj","prep","det","pobj","nsubj","dep","cop","det","advmod","amod","ccomp","prep","det","amod","pobj","prep","advmod","pcomp","dobj","mark","nsubj","advcl","amod","dobj",null]
,"naryTree":"((ROOT (S (ADVP (RB Interestingly)) (, ,) (NP (NP (DT the) (NN policy)) (PP (IN of) (S (VP (VBG making) (NP (NN cigarette) (NNS buyers)))))) (VP (VBP pay) (S (VP (TO to) (VP (VB compensate) (NP (NN society)) (PP (IN for) (NP (DT the) (NNS costs))) (SBAR (S (NP (PRP they)) (VP (VBP impose) (SBAR (S (VP (VBZ is) (NP (NP (DT a) (ADJP (RB politically) (JJ palatable)) (NN synthesis)) (PP (IN of) (NP (NP (DT the) (JJ unpalatable) (NN notion)) (PP (IN of) (S (VP (ADVP (RB simply)) (VBG refusing) (NP (NN treatment)))))))))))))) (SBAR (IN unless) (S (NP (PRP they)) (VP (VBP pay) (NP (JJ full) (NN cost))))))))) (. .))))"
,"nePairs":"[{\"m1\":{\"start\":11,\"end\":12,\"head\":11,\"type\":\"PER\",\"subtype\":\"Group\",\"phraseType\":\"NOM\",\"id\":\"700002a9-4292-72e9-dc80-00002ca3c32d\"},\"m2\":{\"start\":15,\"end\":16,\"head\":15,\"type\":\"PER\",\"subtype\":\"Group\",\"phraseType\":\"PRO\",\"id\":\"700002a9-4292-72e9-dc80-00002ca3c346\"}}]"
,"relLabels":["NO_RELATION(Arg-1,Arg-1)"]}

{"words":["Interestingly",",","the","policy","of","making","cigarette","buyers","pay","to","compensate","society","for","the","costs","they","impose","is","a","politically","palatable","synthesis","of","the","unpalatable","notion","of","simply","refusing","treatment","unless","they","pay","full","cost","."]
,"lemmas":["interestingly",",","the","policy","of","make","cigarette","buyer","pay","to","compensate","society","for","the","cost","they","impose","be","a","politically","palatable","synthesis","of","the","unpalatable","notion","of","simply","refuse","treatment","unless","they","pay","full","cost","."]
,"posTags":["RB",",","DT","NN","IN","VBG","NN","NNS","VBP","TO","VB","NN","IN","DT","NNS","PRP","VBP","VBZ","DT","RB","JJ","NN","IN","DT","JJ","NN","IN","RB","VBG","NN","IN","PRP","VBP","JJ","NN","."]
,"chunks":["B-ADVP","O","B-NP","I-NP","B-PP","B-VP","B-NP","I-NP","B-VP","B-VP","I-VP","B-NP","B-PP","B-NP","I-NP","B-NP","B-VP","B-VP","B-NP","I-NP","I-NP","I-NP","B-PP","B-NP","I-NP","I-NP","B-PP","B-VP","I-VP","B-NP","B-SBAR","B-NP","B-VP","B-NP","I-NP","O"]
,"parents":[8,-2,3,8,3,4,7,5,-1,10,8,10,10,14,12,16,10,21,21,20,21,16,21,25,25,22,25,28,26,28,32,32,10,34,32,-2]
,"deprels":["advmod",null,"det","nsubj","prep","pcomp","nn","dobj","root","aux","xcomp","dobj","prep","det","pobj","nsubj","dep","cop","det","advmod","amod","ccomp","prep","det","amod","pobj","prep","advmod","pcomp","dobj","mark","nsubj","advcl","amod","dobj",null]
,"naryTree":"((ROOT (S (ADVP (RB Interestingly)) (, ,) (NP (NP (DT the) (NN policy)) (PP (IN of) (S (VP (VBG making) (NP (NN cigarette) (NNS buyers)))))) (VP (VBP pay) (S (VP (TO to) (VP (VB compensate) (NP (NN society)) (PP (IN for) (NP (DT the) (NNS costs))) (SBAR (S (NP (PRP they)) (VP (VBP impose) (SBAR (S (VP (VBZ is) (NP (NP (DT a) (ADJP (RB politically) (JJ palatable)) (NN synthesis)) (PP (IN of) (NP (NP (DT the) (JJ unpalatable) (NN notion)) (PP (IN of) (S (VP (ADVP (RB simply)) (VBG refusing) (NP (NN treatment)))))))))))))) (SBAR (IN unless) (S (NP (PRP they)) (VP (VBP pay) (NP (JJ full) (NN cost))))))))) (. .))))"
,"nePairs":"[{\"m1\":{\"start\":11,\"end\":12,\"head\":11,\"type\":\"PER\",\"subtype\":\"Group\",\"phraseType\":\"NOM\",\"id\":\"700002a9-4292-72e9-dc80-00002ca3c32d\"},\"m2\":{\"start\":31,\"end\":32,\"head\":31,\"type\":\"PER\",\"subtype\":\"Group\",\"phraseType\":\"PRO\",\"id\":\"700002a9-4292-72e9-dc80-00002ca3c349\"}}]"
,"relLabels":["NO_RELATION(Arg-1,Arg-1)"]}

{"words":["Interestingly",",","the","policy","of","making","cigarette","buyers","pay","to","compensate","society","for","the","costs","they","impose","is","a","politically","palatable","synthesis","of","the","unpalatable","notion","of","simply","refusing","treatment","unless","they","pay","full","cost","."]
,"lemmas":["interestingly",",","the","policy","of","make","cigarette","buyer","pay","to","compensate","society","for","the","cost","they","impose","be","a","politically","palatable","synthesis","of","the","unpalatable","notion","of","simply","refuse","treatment","unless","they","pay","full","cost","."]
,"posTags":["RB",",","DT","NN","IN","VBG","NN","NNS","VBP","TO","VB","NN","IN","DT","NNS","PRP","VBP","VBZ","DT","RB","JJ","NN","IN","DT","JJ","NN","IN","RB","VBG","NN","IN","PRP","VBP","JJ","NN","."]
,"chunks":["B-ADVP","O","B-NP","I-NP","B-PP","B-VP","B-NP","I-NP","B-VP","B-VP","I-VP","B-NP","B-PP","B-NP","I-NP","B-NP","B-VP","B-VP","B-NP","I-NP","I-NP","I-NP","B-PP","B-NP","I-NP","I-NP","B-PP","B-VP","I-VP","B-NP","B-SBAR","B-NP","B-VP","B-NP","I-NP","O"]
,"parents":[8,-2,3,8,3,4,7,5,-1,10,8,10,10,14,12,16,10,21,21,20,21,16,21,25,25,22,25,28,26,28,32,32,10,34,32,-2]
,"deprels":["advmod",null,"det","nsubj","prep","pcomp","nn","dobj","root","aux","xcomp","dobj","prep","det","pobj","nsubj","dep","cop","det","advmod","amod","ccomp","prep","det","amod","pobj","prep","advmod","pcomp","dobj","mark","nsubj","advcl","amod","dobj",null]
,"naryTree":"((ROOT (S (ADVP (RB Interestingly)) (, ,) (NP (NP (DT the) (NN policy)) (PP (IN of) (S (VP (VBG making) (NP (NN cigarette) (NNS buyers)))))) (VP (VBP pay) (S (VP (TO to) (VP (VB compensate) (NP (NN society)) (PP (IN for) (NP (DT the) (NNS costs))) (SBAR (S (NP (PRP they)) (VP (VBP impose) (SBAR (S (VP (VBZ is) (NP (NP (DT a) (ADJP (RB politically) (JJ palatable)) (NN synthesis)) (PP (IN of) (NP (NP (DT the) (JJ unpalatable) (NN notion)) (PP (IN of) (S (VP (ADVP (RB simply)) (VBG refusing) (NP (NN treatment)))))))))))))) (SBAR (IN unless) (S (NP (PRP they)) (VP (VBP pay) (NP (JJ full) (NN cost))))))))) (. .))))"
,"nePairs":"[{\"m1\":{\"start\":15,\"end\":16,\"head\":15,\"type\":\"PER\",\"subtype\":\"Group\",\"phraseType\":\"PRO\",\"id\":\"700002a9-4292-72e9-dc80-00002ca3c346\"},\"m2\":{\"start\":31,\"end\":32,\"head\":31,\"type\":\"PER\",\"subtype\":\"Group\",\"phraseType\":\"PRO\",\"id\":\"700002a9-4292-72e9-dc80-00002ca3c349\"}}]"
,"relLabels":["NO_RELATION(Arg-1,Arg-1)"]}

{"words":["They","'re","basically","buying","future","medical","care","throughout","their","lives",",","rather","than","eventually","making","the","-LRB-","healthy","-RRB-","remainder","of","the","populace","pay","up","."]
,"lemmas":["they","be","basically","buy","future","medical","care","throughout","they","life",",","rather","than","eventually","make","the","-lrb-","healthy","-rrb-","remainder","of","the","populace","pay","up","."]
,"posTags":["PRP","VBP","RB","VBG","JJ","JJ","NN","IN","PRP$","NNS",",","RB","IN","RB","VBG","DT","-LRB-","JJ","-RRB-","NN","IN","DT","NN","VB","RP","."]
,"chunks":["B-NP","B-VP","I-VP","I-VP","B-NP","I-NP","I-NP","B-PP","B-NP","I-NP","O","B-PP","I-PP","B-VP","I-VP","O","O","B-ADJP","O","B-NP","B-PP","B-NP","I-NP","B-VP","B-PRT","O"]
,"parents":[3,3,3,-1,6,6,3,6,9,7,-2,12,3,14,12,19,-2,19,-2,14,14,22,20,22,23,-2]
,"deprels":["nsubj","aux","advmod","root","amod","amod","dobj","prep","poss","pobj",null,"advmod","prep","advmod","pcomp","det",null,"dep",null,"dobj","prep","det","pobj","dep","prt",null]
,"naryTree":"((ROOT (S (NP (PRP They)) (VP (VBP 're) (ADVP (RB basically)) (VP (VBG buying) (NP (NP (JJ future) (JJ medical) (NN care)) (PP (IN throughout) (NP (PRP$ their) (NNS lives)))) (, ,) (PP (RB rather) (IN than) (S (VP (ADVP (RB eventually)) (VBG making) (NP (DT the) (PRN (-LRB- -LRB-) (ADJP (JJ healthy)) (-RRB- -RRB-)) (NN remainder)) (PP (IN of) (NP (DT the) (NN populace) (S (VP (VB pay) (PRT (RP up))))))))))) (. .))))"
,"nePairs":"[{\"m1\":{\"start\":0,\"end\":1,\"head\":0,\"type\":\"PER\",\"subtype\":\"Group\",\"phraseType\":\"PRO\",\"id\":\"700002a9-4292-72e9-dc80-00002ca3c34a\"},\"m2\":{\"start\":8,\"end\":9,\"head\":8,\"type\":\"PER\",\"subtype\":\"Group\",\"phraseType\":\"PRO\",\"id\":\"700002a9-4292-72e9-dc80-00002ca3c34b\"}}]"
,"relLabels":["NO_RELATION(Arg-1,Arg-1)"]}

{"words":["They","'re","basically","buying","future","medical","care","throughout","their","lives",",","rather","than","eventually","making","the","-LRB-","healthy","-RRB-","remainder","of","the","populace","pay","up","."]
,"lemmas":["they","be","basically","buy","future","medical","care","throughout","they","life",",","rather","than","eventually","make","the","-lrb-","healthy","-rrb-","remainder","of","the","populace","pay","up","."]
,"posTags":["PRP","VBP","RB","VBG","JJ","JJ","NN","IN","PRP$","NNS",",","RB","IN","RB","VBG","DT","-LRB-","JJ","-RRB-","NN","IN","DT","NN","VB","RP","."]
,"chunks":["B-NP","B-VP","I-VP","I-VP","B-NP","I-NP","I-NP","B-PP","B-NP","I-NP","O","B-PP","I-PP","B-VP","I-VP","O","O","B-ADJP","O","B-NP","B-PP","B-NP","I-NP","B-VP","B-PRT","O"]
,"parents":[3,3,3,-1,6,6,3,6,9,7,-2,12,3,14,12,19,-2,19,-2,14,14,22,20,22,23,-2]
,"deprels":["nsubj","aux","advmod","root","amod","amod","dobj","prep","poss","pobj",null,"advmod","prep","advmod","pcomp","det",null,"dep",null,"dobj","prep","det","pobj","dep","prt",null]
,"naryTree":"((ROOT (S (NP (PRP They)) (VP (VBP 're) (ADVP (RB basically)) (VP (VBG buying) (NP (NP (JJ future) (JJ medical) (NN care)) (PP (IN throughout) (NP (PRP$ their) (NNS lives)))) (, ,) (PP (RB rather) (IN than) (S (VP (ADVP (RB eventually)) (VBG making) (NP (DT the) (PRN (-LRB- -LRB-) (ADJP (JJ healthy)) (-RRB- -RRB-)) (NN remainder)) (PP (IN of) (NP (DT the) (NN populace) (S (VP (VB pay) (PRT (RP up))))))))))) (. .))))"
,"nePairs":"[{\"m1\":{\"start\":0,\"end\":1,\"head\":0,\"type\":\"PER\",\"subtype\":\"Group\",\"phraseType\":\"PRO\",\"id\":\"700002a9-4292-72e9-dc80-00002ca3c34a\"},\"m2\":{\"start\":15,\"end\":20,\"head\":19,\"type\":\"PER\",\"subtype\":\"Group\",\"phraseType\":\"NOM\",\"id\":\"700002a9-4292-72e9-dc80-00002ca3c34d\"}}]"
,"relLabels":["NO_RELATION(Arg-1,Arg-1)"]}

{"words":["They","'re","basically","buying","future","medical","care","throughout","their","lives",",","rather","than","eventually","making","the","-LRB-","healthy","-RRB-","remainder","of","the","populace","pay","up","."]
,"lemmas":["they","be","basically","buy","future","medical","care","throughout","they","life",",","rather","than","eventually","make","the","-lrb-","healthy","-rrb-","remainder","of","the","populace","pay","up","."]
,"posTags":["PRP","VBP","RB","VBG","JJ","JJ","NN","IN","PRP$","NNS",",","RB","IN","RB","VBG","DT","-LRB-","JJ","-RRB-","NN","IN","DT","NN","VB","RP","."]
,"chunks":["B-NP","B-VP","I-VP","I-VP","B-NP","I-NP","I-NP","B-PP","B-NP","I-NP","O","B-PP","I-PP","B-VP","I-VP","O","O","B-ADJP","O","B-NP","B-PP","B-NP","I-NP","B-VP","B-PRT","O"]
,"parents":[3,3,3,-1,6,6,3,6,9,7,-2,12,3,14,12,19,-2,19,-2,14,14,22,20,22,23,-2]
,"deprels":["nsubj","aux","advmod","root","amod","amod","dobj","prep","poss","pobj",null,"advmod","prep","advmod","pcomp","det",null,"dep",null,"dobj","prep","det","pobj","dep","prt",null]
,"naryTree":"((ROOT (S (NP (PRP They)) (VP (VBP 're) (ADVP (RB basically)) (VP (VBG buying) (NP (NP (JJ future) (JJ medical) (NN care)) (PP (IN throughout) (NP (PRP$ their) (NNS lives)))) (, ,) (PP (RB rather) (IN than) (S (VP (ADVP (RB eventually)) (VBG making) (NP (DT the) (PRN (-LRB- -LRB-) (ADJP (JJ healthy)) (-RRB- -RRB-)) (NN remainder)) (PP (IN of) (NP (DT the) (NN populace) (S (VP (VB pay) (PRT (RP up))))))))))) (. .))))"
,"nePairs":"[{\"m1\":{\"start\":0,\"end\":1,\"head\":0,\"type\":\"PER\",\"subtype\":\"Group\",\"phraseType\":\"PRO\",\"id\":\"700002a9-4292-72e9-dc80-00002ca3c34a\"},\"m2\":{\"start\":21,\"end\":23,\"head\":22,\"type\":\"GPE\",\"subtype\":\"State-or-Province\",\"phraseType\":\"NOM\",\"id\":\"700002a9-4292-72e9-dc80-00002ca3c334\"}}]"
,"relLabels":["NO_RELATION(Arg-1,Arg-1)"]}

{"words":["They","'re","basically","buying","future","medical","care","throughout","their","lives",",","rather","than","eventually","making","the","-LRB-","healthy","-RRB-","remainder","of","the","populace","pay","up","."]
,"lemmas":["they","be","basically","buy","future","medical","care","throughout","they","life",",","rather","than","eventually","make","the","-lrb-","healthy","-rrb-","remainder","of","the","populace","pay","up","."]
,"posTags":["PRP","VBP","RB","VBG","JJ","JJ","NN","IN","PRP$","NNS",",","RB","IN","RB","VBG","DT","-LRB-","JJ","-RRB-","NN","IN","DT","NN","VB","RP","."]
,"chunks":["B-NP","B-VP","I-VP","I-VP","B-NP","I-NP","I-NP","B-PP","B-NP","I-NP","O","B-PP","I-PP","B-VP","I-VP","O","O","B-ADJP","O","B-NP","B-PP","B-NP","I-NP","B-VP","B-PRT","O"]
,"parents":[3,3,3,-1,6,6,3,6,9,7,-2,12,3,14,12,19,-2,19,-2,14,14,22,20,22,23,-2]
,"deprels":["nsubj","aux","advmod","root","amod","amod","dobj","prep","poss","pobj",null,"advmod","prep","advmod","pcomp","det",null,"dep",null,"dobj","prep","det","pobj","dep","prt",null]
,"naryTree":"((ROOT (S (NP (PRP They)) (VP (VBP 're) (ADVP (RB basically)) (VP (VBG buying) (NP (NP (JJ future) (JJ medical) (NN care)) (PP (IN throughout) (NP (PRP$ their) (NNS lives)))) (, ,) (PP (RB rather) (IN than) (S (VP (ADVP (RB eventually)) (VBG making) (NP (DT the) (PRN (-LRB- -LRB-) (ADJP (JJ healthy)) (-RRB- -RRB-)) (NN remainder)) (PP (IN of) (NP (DT the) (NN populace) (S (VP (VB pay) (PRT (RP up))))))))))) (. .))))"
,"nePairs":"[{\"m1\":{\"start\":8,\"end\":9,\"head\":8,\"type\":\"PER\",\"subtype\":\"Group\",\"phraseType\":\"PRO\",\"id\":\"700002a9-4292-72e9-dc80-00002ca3c34b\"},\"m2\":{\"start\":15,\"end\":20,\"head\":19,\"type\":\"PER\",\"subtype\":\"Group\",\"phraseType\":\"NOM\",\"id\":\"700002a9-4292-72e9-dc80-00002ca3c34d\"}}]"
,"relLabels":["NO_RELATION(Arg-1,Arg-1)"]}

{"words":["They","'re","basically","buying","future","medical","care","throughout","their","lives",",","rather","than","eventually","making","the","-LRB-","healthy","-RRB-","remainder","of","the","populace","pay","up","."]
,"lemmas":["they","be","basically","buy","future","medical","care","throughout","they","life",",","rather","than","eventually","make","the","-lrb-","healthy","-rrb-","remainder","of","the","populace","pay","up","."]
,"posTags":["PRP","VBP","RB","VBG","JJ","JJ","NN","IN","PRP$","NNS",",","RB","IN","RB","VBG","DT","-LRB-","JJ","-RRB-","NN","IN","DT","NN","VB","RP","."]
,"chunks":["B-NP","B-VP","I-VP","I-VP","B-NP","I-NP","I-NP","B-PP","B-NP","I-NP","O","B-PP","I-PP","B-VP","I-VP","O","O","B-ADJP","O","B-NP","B-PP","B-NP","I-NP","B-VP","B-PRT","O"]
,"parents":[3,3,3,-1,6,6,3,6,9,7,-2,12,3,14,12,19,-2,19,-2,14,14,22,20,22,23,-2]
,"deprels":["nsubj","aux","advmod","root","amod","amod","dobj","prep","poss","pobj",null,"advmod","prep","advmod","pcomp","det",null,"dep",null,"dobj","prep","det","pobj","dep","prt",null]
,"naryTree":"((ROOT (S (NP (PRP They)) (VP (VBP 're) (ADVP (RB basically)) (VP (VBG buying) (NP (NP (JJ future) (JJ medical) (NN care)) (PP (IN throughout) (NP (PRP$ their) (NNS lives)))) (, ,) (PP (RB rather) (IN than) (S (VP (ADVP (RB eventually)) (VBG making) (NP (DT the) (PRN (-LRB- -LRB-) (ADJP (JJ healthy)) (-RRB- -RRB-)) (NN remainder)) (PP (IN of) (NP (DT the) (NN populace) (S (VP (VB pay) (PRT (RP up))))))))))) (. .))))"
,"nePairs":"[{\"m1\":{\"start\":8,\"end\":9,\"head\":8,\"type\":\"PER\",\"subtype\":\"Group\",\"phraseType\":\"PRO\",\"id\":\"700002a9-4292-72e9-dc80-00002ca3c34b\"},\"m2\":{\"start\":21,\"end\":23,\"head\":22,\"type\":\"GPE\",\"subtype\":\"State-or-Province\",\"phraseType\":\"NOM\",\"id\":\"700002a9-4292-72e9-dc80-00002ca3c334\"}}]"
,"relLabels":["NO_RELATION(Arg-1,Arg-1)"]}

{"words":["They","'re","basically","buying","future","medical","care","throughout","their","lives",",","rather","than","eventually","making","the","-LRB-","healthy","-RRB-","remainder","of","the","populace","pay","up","."]
,"lemmas":["they","be","basically","buy","future","medical","care","throughout","they","life",",","rather","than","eventually","make","the","-lrb-","healthy","-rrb-","remainder","of","the","populace","pay","up","."]
,"posTags":["PRP","VBP","RB","VBG","JJ","JJ","NN","IN","PRP$","NNS",",","RB","IN","RB","VBG","DT","-LRB-","JJ","-RRB-","NN","IN","DT","NN","VB","RP","."]
,"chunks":["B-NP","B-VP","I-VP","I-VP","B-NP","I-NP","I-NP","B-PP","B-NP","I-NP","O","B-PP","I-PP","B-VP","I-VP","O","O","B-ADJP","O","B-NP","B-PP","B-NP","I-NP","B-VP","B-PRT","O"]
,"parents":[3,3,3,-1,6,6,3,6,9,7,-2,12,3,14,12,19,-2,19,-2,14,14,22,20,22,23,-2]
,"deprels":["nsubj","aux","advmod","root","amod","amod","dobj","prep","poss","pobj",null,"advmod","prep","advmod","pcomp","det",null,"dep",null,"dobj","prep","det","pobj","dep","prt",null]
,"naryTree":"((ROOT (S (NP (PRP They)) (VP (VBP 're) (ADVP (RB basically)) (VP (VBG buying) (NP (NP (JJ future) (JJ medical) (NN care)) (PP (IN throughout) (NP (PRP$ their) (NNS lives)))) (, ,) (PP (RB rather) (IN than) (S (VP (ADVP (RB eventually)) (VBG making) (NP (DT the) (PRN (-LRB- -LRB-) (ADJP (JJ healthy)) (-RRB- -RRB-)) (NN remainder)) (PP (IN of) (NP (DT the) (NN populace) (S (VP (VB pay) (PRT (RP up))))))))))) (. .))))"
,"nePairs":"[{\"m1\":{\"start\":15,\"end\":20,\"head\":19,\"type\":\"PER\",\"subtype\":\"Group\",\"phraseType\":\"NOM\",\"id\":\"700002a9-4292-72e9-dc80-00002ca3c34d\"},\"m2\":{\"start\":21,\"end\":23,\"head\":22,\"type\":\"GPE\",\"subtype\":\"State-or-Province\",\"phraseType\":\"NOM\",\"id\":\"700002a9-4292-72e9-dc80-00002ca3c334\"}}]"
,"relLabels":["NO_RELATION(Arg-1,Arg-1)"]}

